{
  "ComponentIndexes": {
    "navBarHorizontal": 28,
    "navBarVertical": 29,
    "paginationBar": 30
  },
  "ControlUniqueGuids": {},
  "ControlUniqueIds": {
    "2": 508,
    "47": 584,
    "Action Header": 579,
    "Action Header_1": 866,
    "Action Header_10": 157,
    "Action Header_11": 182,
    "Action Header_12": 21,
    "Action Header_2": 532,
    "Action Header_3": 202,
    "Action Header_4": 496,
    "Action Header_5": 816,
    "Action Header_6": 555,
    "Action Label": 580,
    "Action Label_1": 867,
    "Action Label_10": 158,
    "Action Label_11": 183,
    "Action Label_12": 22,
    "Action Label_2": 533,
    "Action Label_3": 203,
    "Action Label_4": 497,
    "Action Label_5": 817,
    "Action Label_6": 556,
    "Active": 514,
    "App": 1,
    "April-22 / June-23": 512,
    "Button1": 253,
    "Button2": 730,
    "Button2_1": 294,
    "Button2_2": 733,
    "Button2_3": 769,
    "Button3": 223,
    "Button3_1": 226,
    "Button4": 789,
    "Button5": 188,
    "Button5_1": 187,
    "Button5_10": 859,
    "Button5_11": 858,
    "Button5_18": 140,
    "Button5_19": 141,
    "Button5_2": 804,
    "Button5_20": 162,
    "Button5_21": 163,
    "Button5_22": 13,
    "Button5_23": 14,
    "Button5_3": 803,
    "Button5_4": 519,
    "Button5_5": 520,
    "Button5_6": 539,
    "Button5_7": 540,
    "Button5_8": 560,
    "Button5_9": 561,
    "Button8": 586,
    "Button8_1": 588,
    "Button8_2": 591,
    "Capability": 862,
    "Capability_1": 17,
    "capabilitydpdwn": 262,
    "Caregivers": 824,
    "Category": 570,
    "Category Header": 573,
    "Category Header_1": 176,
    "Category Header_10": 39,
    "Category Header_11": 40,
    "Category Header_13": 883,
    "Category Header_14": 884,
    "Category Header_15": 129,
    "Category Header_16": 130,
    "Category Header_2": 528,
    "Category Header_3": 197,
    "Category Header_4": 198,
    "Category Header_5": 484,
    "Category Header_6": 200,
    "Category Header_7": 529,
    "Category Header_8": 812,
    "Category Header_9": 813,
    "Category Label": 574,
    "Category Label_1": 177,
    "Category Label_10": 41,
    "Category Label_11": 869,
    "Category Label_14": 886,
    "Category Label_16": 132,
    "Category Label_17": 23,
    "Category Label_2": 531,
    "Category Label_3": 199,
    "Category Label_4": 530,
    "Category Label_5": 485,
    "Category Label_6": 201,
    "Category Label_7": 815,
    "Category Label_8": 814,
    "Category Label_9": 868,
    "Category_1": 525,
    "Category_2": 194,
    "Category_3": 809,
    "Category_4": 548,
    "Category_5": 36,
    "Category_6": 880,
    "Category_7": 126,
    "Category_8": 150,
    "Category_9": 173,
    "CategoryLabel": 563,
    "CategoryLabel_1": 166,
    "Column - Header 10": 507,
    "Column - Header 11": 513,
    "Column - Header 12": 511,
    "Column - Header 13": 581,
    "Column - Header 13_1": 557,
    "Column - Header 13_2": 501,
    "Column - Header 13_3": 159,
    "Column - Header 13_4": 184,
    "Column - Header 14_1": 509,
    "Column - Header 4_2": 534,
    "Column - Header 4_4": 499,
    "Column - Header 5_4": 503,
    "Column - Header 6": 583,
    "Column - Header 6_1": 505,
    "Column - Header 7_2": 515,
    "ComboBox1": 366,
    "ComboBox1_1": 49,
    "comment": 799,
    "comment_1": 756,
    "comment_2": 757,
    "comment_3": 758,
    "Component2_1": 474,
    "Component2_2": 823,
    "Data Analytics_1": 535,
    "Data Analytics_2": 504,
    "Data Analytics_3": 818,
    "Databrics Spark Tableu": 510,
    "DatePicker1": 346,
    "DatePicker1_1": 347,
    "Description Header": 577,
    "Description Header_1": 486,
    "Description Header_2": 553,
    "Description Header_3": 155,
    "Description Header_4": 180,
    "Description Label": 578,
    "Description Label_1": 487,
    "Description Label_2": 554,
    "Description Label_3": 156,
    "Description Label_4": 181,
    "descriptionlabel": 190,
    "descriptionlabel_1": 32,
    "Edit_3": 516,
    "Favourite Header": 494,
    "Favourite Label": 495,
    "Frame 10": 498,
    "Gallery1": 834,
    "Gallery1_1": 772,
    "Gallery1_2": 279,
    "Gallery1_3": 780,
    "Gallery17": 237,
    "Gallery28": 244,
    "Gallery29": 251,
    "Gallery3": 736,
    "Gallery31": 255,
    "Gallery33": 230,
    "Gallery4": 214,
    "Gallery5": 593,
    "Gallery5_1": 594,
    "Gallery5_2": 671,
    "Gallery5_3": 645,
    "Gallery5_4": 672,
    "Gallery6": 221,
    "Gallery6_1": 224,
    "Gallery7": 728,
    "Gallery7_1": 292,
    "Gallery7_2": 731,
    "Gallery7_3": 767,
    "Gallery8": 207,
    "galleryTemplate1": 835,
    "galleryTemplate1_1": 773,
    "galleryTemplate1_2": 280,
    "galleryTemplate1_3": 781,
    "galleryTemplate18": 238,
    "galleryTemplate2": 843,
    "galleryTemplate29": 245,
    "galleryTemplate30": 252,
    "galleryTemplate32": 256,
    "galleryTemplate34": 231,
    "galleryTemplate4": 737,
    "galleryTemplate5": 215,
    "galleryTemplate6": 620,
    "galleryTemplate6_1": 595,
    "galleryTemplate6_2": 673,
    "galleryTemplate6_3": 646,
    "galleryTemplate6_4": 698,
    "galleryTemplate7": 222,
    "galleryTemplate7_1": 225,
    "galleryTemplate8": 729,
    "galleryTemplate8_1": 293,
    "galleryTemplate8_2": 732,
    "galleryTemplate8_3": 768,
    "galleryTemplate9": 208,
    "Group1": 762,
    "Group3": 759,
    "Group3_1": 760,
    "Group3_2": 761,
    "Group7_4": 800,
    "grouplabel": 191,
    "hiddenGallery": 842,
    "Host": 3,
    "Icon1_1": 367,
    "Icon1_16": 740,
    "Icon1_17": 739,
    "Icon1_18": 376,
    "Icon1_19": 377,
    "Icon1_2": 368,
    "Icon1_20": 378,
    "Icon1_21": 379,
    "Icon1_22": 380,
    "Icon1_23": 381,
    "Icon1_24": 50,
    "Icon1_25": 382,
    "Icon1_26": 51,
    "Icon1_27": 52,
    "Icon1_28": 53,
    "Icon1_29": 54,
    "Icon1_3": 369,
    "Icon1_30": 55,
    "Icon1_31": 56,
    "Icon1_32": 57,
    "Icon1_33": 58,
    "Icon1_34": 59,
    "Icon1_35": 60,
    "Icon1_36": 61,
    "Icon1_37": 62,
    "Icon1_38": 63,
    "Icon1_39": 64,
    "Icon1_4": 370,
    "Icon1_40": 296,
    "Icon1_41": 297,
    "Icon1_42": 315,
    "Icon1_43": 330,
    "Icon1_44": 345,
    "Icon1_45": 455,
    "Icon1_46": 440,
    "Icon1_5": 371,
    "Icon1_6": 372,
    "Icon1_7": 373,
    "Icon1_8": 374,
    "Icon1_9": 375,
    "Image1": 5,
    "Image3": 847,
    "Image4": 846,
    "Image5": 7,
    "Image5_1": 8,
    "Image5_2": 9,
    "Image5_3": 10,
    "Label1": 844,
    "Label10": 227,
    "Label10_1": 228,
    "Label10_2": 229,
    "Label10_3": 254,
    "Label11": 518,
    "Label12": 764,
    "Label12_1": 765,
    "Label12_2": 766,
    "Label13": 383,
    "Label13_1": 385,
    "Label13_2": 384,
    "Label15": 521,
    "Label15_1": 805,
    "Label16": 522,
    "Label16_1": 806,
    "Label16_2": 877,
    "Label16_3": 123,
    "Label2": 830,
    "Label2_1": 831,
    "Label2_10": 276,
    "Label2_12": 277,
    "Label2_13": 278,
    "Label2_14": 273,
    "Label2_15": 274,
    "Label2_2": 832,
    "Label2_3": 833,
    "Label2_8": 271,
    "Label2_9": 275,
    "Label23": 802,
    "Label25": 849,
    "Label3": 860,
    "Label3_1": 65,
    "Label3_10": 72,
    "Label3_11": 73,
    "Label3_12": 74,
    "Label3_13": 399,
    "Label3_14": 401,
    "Label3_15": 403,
    "Label3_16": 411,
    "Label3_17": 413,
    "Label3_18": 415,
    "Label3_19": 420,
    "Label3_2": 66,
    "Label3_20": 430,
    "Label3_21": 78,
    "Label3_22": 76,
    "Label3_23": 428,
    "Label3_24": 113,
    "Label3_25": 114,
    "Label3_26": 393,
    "Label3_27": 88,
    "Label3_28": 85,
    "Label3_29": 387,
    "Label3_3": 68,
    "Label3_30": 389,
    "Label3_31": 388,
    "Label3_4": 397,
    "Label3_5": 396,
    "Label3_6": 15,
    "Label3_7": 69,
    "Label3_8": 70,
    "Label3_9": 71,
    "Label4": 726,
    "Label6": 75,
    "Label6_1": 77,
    "Label6_10": 407,
    "Label6_11": 409,
    "Label6_12": 416,
    "Label6_13": 422,
    "Label6_14": 84,
    "Label6_15": 424,
    "Label6_16": 425,
    "Label6_17": 426,
    "Label6_18": 427,
    "Label6_19": 417,
    "Label6_2": 79,
    "Label6_20": 310,
    "Label6_21": 311,
    "Label6_22": 312,
    "Label6_23": 326,
    "Label6_24": 327,
    "Label6_25": 361,
    "Label6_26": 362,
    "Label6_27": 363,
    "Label6_28": 364,
    "Label6_29": 457,
    "Label6_3": 80,
    "Label6_30": 458,
    "Label6_31": 442,
    "Label6_32": 443,
    "Label6_33": 423,
    "Label6_34": 82,
    "Label6_35": 342,
    "Label6_36": 343,
    "Label6_37": 93,
    "Label6_38": 390,
    "Label6_4": 81,
    "Label6_5": 83,
    "Label6_6": 86,
    "Label6_7": 87,
    "Label6_8": 89,
    "Label6_9": 405,
    "Label7": 587,
    "Label7_1": 589,
    "Label7_2": 590,
    "Label8": 738,
    "Manasa": 506,
    "msft_Button": 309,
    "msft_Button_10": 871,
    "msft_Button_11": 285,
    "msft_Button_12": 288,
    "msft_Button_13": 471,
    "msft_Button_14": 204,
    "msft_Button_15": 205,
    "msft_Button_16": 851,
    "msft_Button_17": 852,
    "msft_Button_18": 287,
    "msft_Button_19": 328,
    "msft_Button_20": 92,
    "msft_Button_21": 94,
    "msft_Button_22": 286,
    "msft_Button_23": 456,
    "msft_Button_24": 289,
    "msft_Button_25": 825,
    "msft_Button_26": 95,
    "msft_Button_27": 402,
    "msft_Button_28": 406,
    "msft_Button_29": 404,
    "msft_Button_30": 468,
    "msft_Button_31": 441,
    "msft_Button_32": 453,
    "msft_Button_33": 870,
    "msft_Button_34": 536,
    "msft_Button_35": 819,
    "msft_Button_36": 820,
    "msft_Button_37": 537,
    "msft_Button_38": 290,
    "msft_Button_39": 542,
    "msft_Button_4": 325,
    "msft_Button_40": 543,
    "msft_Button_41": 340,
    "msft_Button_42": 341,
    "msft_Button_43": 313,
    "msft_Button_44": 46,
    "msft_Button_45": 47,
    "msft_Button_46": 890,
    "msft_Button_47": 891,
    "msft_Button_48": 137,
    "msft_Button_49": 138,
    "msft_Button_50": 144,
    "msft_Button_51": 145,
    "msft_Button_52": 167,
    "msft_Button_53": 168,
    "msft_Button_54": 24,
    "msft_Button_55": 25,
    "msft_Button_6": 359,
    "msft_Button_7": 360,
    "msft_Button_8": 564,
    "msft_Button_9": 565,
    "msft_ComboBox_5": 478,
    "msft_DatePicker_2": 106,
    "msft_DatePicker_3": 107,
    "msft_DatePicker_4": 431,
    "msft_DatePicker_5": 432,
    "msft_Dropdown": 306,
    "msft_Dropdown_10": 103,
    "msft_Dropdown_12": 109,
    "msft_Dropdown_16": 477,
    "msft_Dropdown_18": 110,
    "msft_Dropdown_19": 418,
    "msft_Dropdown_20": 419,
    "msft_Dropdown_21": 421,
    "msft_Dropdown_22": 433,
    "msft_Dropdown_23": 435,
    "msft_Dropdown_24": 436,
    "msft_Dropdown_25": 395,
    "msft_Dropdown_27": 438,
    "msft_Dropdown_28": 99,
    "msft_Dropdown_29": 104,
    "msft_Dropdown_30": 101,
    "msft_Dropdown_31": 116,
    "msft_Dropdown_32": 117,
    "msft_Dropdown_33": 394,
    "msft_Dropdown_9": 102,
    "msft_Label": 302,
    "msft_Label_1": 305,
    "msft_Label_10": 727,
    "msft_Label_11": 357,
    "msft_Label_12": 464,
    "msft_Label_13": 466,
    "msft_Label_14": 449,
    "msft_Label_15": 451,
    "msft_Label_16": 355,
    "msft_Label_17": 336,
    "msft_Label_18": 338,
    "msft_Label_2": 307,
    "msft_Label_34": 795,
    "msft_Label_35": 796,
    "msft_Label_36": 794,
    "msft_Label_37": 744,
    "msft_Label_38": 747,
    "msft_Label_39": 741,
    "msft_Label_40": 745,
    "msft_Label_41": 748,
    "msft_Label_42": 742,
    "msft_Label_43": 746,
    "msft_Label_44": 749,
    "msft_Label_45": 743,
    "msft_Label_5": 321,
    "msft_Label_6": 323,
    "msft_Label_7": 353,
    "msft_Label_8": 354,
    "msft_Label_9": 734,
    "msft_TextInput": 303,
    "msft_TextInput_1": 308,
    "msft_TextInput_10": 339,
    "msft_TextInput_11": 112,
    "msft_TextInput_12": 105,
    "msft_TextInput_13": 414,
    "msft_TextInput_14": 115,
    "msft_TextInput_15": 391,
    "msft_TextInput_16": 429,
    "msft_TextInput_17": 392,
    "msft_TextInput_19": 465,
    "msft_TextInput_20": 467,
    "msft_TextInput_21": 450,
    "msft_TextInput_22": 452,
    "msft_TextInput_4": 322,
    "msft_TextInput_5": 324,
    "msft_TextInput_6": 356,
    "msft_TextInput_7": 358,
    "msft_TextInput_8": 100,
    "msft_TextInput_9": 337,
    "msftBirthday_DOJ": 763,
    "msftcapability": 801,
    "msftcaregivers": 821,
    "msftconfirmationscreen": 848,
    "msftDashboard": 853,
    "msftdiscipline": 857,
    "msfteditcapability": 873,
    "msfteditdiscipline": 12,
    "msfteditgroup": 28,
    "msfteditproject": 48,
    "msfteditprojectgoal": 118,
    "msfteditprojecttype": 139,
    "msftedittechnology": 161,
    "msftgroup": 186,
    "msftMasterData": 206,
    "msftnewcategory": 295,
    "msftnewcategory2": 314,
    "msftnewdiscipline": 329,
    "msftnewgroup": 344,
    "msftnewproject": 365,
    "msftnewprojectgoal": 439,
    "msftnewprojecttype": 454,
    "msftproject": 469,
    "msftprojectgoal": 517,
    "msftprojecttype": 538,
    "msfttechnology": 559,
    "msftUpdatecaregivers": 585,
    "msftUpdateSkill_Caregiver": 788,
    "navBar_1": 473,
    "navBar_2": 822,
    "navBarHorizontal": 4,
    "navBarHorizontal_1": 724,
    "navBarHorizontal_10": 349,
    "navBarHorizontal_11": 192,
    "navBarHorizontal_12": 460,
    "navBarHorizontal_13": 523,
    "navBarHorizontal_14": 445,
    "navBarHorizontal_15": 807,
    "navBarHorizontal_16": 544,
    "navBarHorizontal_17": 332,
    "navBarHorizontal_18": 790,
    "navBarHorizontal_19": 770,
    "navBarHorizontal_2": 304,
    "navBarHorizontal_20": 34,
    "navBarHorizontal_21": 878,
    "navBarHorizontal_22": 124,
    "navBarHorizontal_23": 146,
    "navBarHorizontal_24": 169,
    "navBarHorizontal_25": 16,
    "navBarHorizontal_3": 317,
    "navBarHorizontal_4": 854,
    "navBarHorizontal_5": 264,
    "navBarHorizontal_6": 90,
    "navBarHorizontal_7": 398,
    "navBarHorizontal_8": 566,
    "navBarHorizontal_9": 861,
    "navBarVertical": 6,
    "navBarVertical_1": 592,
    "navBarVertical_10": 351,
    "navBarVertical_11": 193,
    "navBarVertical_12": 462,
    "navBarVertical_13": 524,
    "navBarVertical_14": 447,
    "navBarVertical_15": 808,
    "navBarVertical_16": 545,
    "navBarVertical_17": 334,
    "navBarVertical_18": 791,
    "navBarVertical_19": 771,
    "navBarVertical_2": 301,
    "navBarVertical_20": 35,
    "navBarVertical_21": 879,
    "navBarVertical_22": 125,
    "navBarVertical_23": 147,
    "navBarVertical_24": 170,
    "navBarVertical_25": 18,
    "navBarVertical_3": 319,
    "navBarVertical_4": 855,
    "navBarVertical_5": 265,
    "navBarVertical_6": 91,
    "navBarVertical_7": 400,
    "navBarVertical_8": 567,
    "navBarVertical_9": 863,
    "New Category": 320,
    "New Category_1": 352,
    "New Category_2": 463,
    "New Category_3": 448,
    "New Category_4": 335,
    "New Project_1": 98,
    "New Project_2": 412,
    "New Project_3": 31,
    "New Project_4": 892,
    "New Project_5": 121,
    "New Project_6": 142,
    "New Project_7": 164,
    "New Project_8": 27,
    "New Technology": 300,
    "NextArrow11": 241,
    "NextArrow13": 248,
    "NextArrow17": 259,
    "NextArrow19": 234,
    "NextArrow4": 218,
    "Owner Header": 492,
    "Owner Label": 493,
    "paginationBar": 11,
    "PowerBI1": 856,
    "Predictive scheduling": 500,
    "Projects_1": 476,
    "projectsactivelabel": 189,
    "React is a JavaScript library for building user interfaces. It is declarative, efficient, and flexible. React makes it easy to create interactive UIs by using a component-based approach.": 582,
    "React is a JavaScript library for building user interfaces. It is declarative, efficient, and flexible. React makes it easy to create interactive UIs by using a component-based approach._1": 872,
    "React is a JavaScript library for building user interfaces. It is declarative, efficient, and flexible. React makes it easy to create interactive UIs by using a component-based approach._2": 558,
    "React is a JavaScript library for building user interfaces. It is declarative, efficient, and flexible. React makes it easy to create interactive UIs by using a component-based approach._3": 160,
    "React is a JavaScript library for building user interfaces. It is declarative, efficient, and flexible. React makes it easy to create interactive UIs by using a component-based approach._4": 185,
    "React is a JavaScript library for building user interfaces. It is declarative, efficient, and flexible. React makes it easy to create interactive UIs by using a component-based approach._5": 26,
    "Rectangle 31": 298,
    "Rectangle 31_10": 444,
    "Rectangle 31_11": 331,
    "Rectangle 31_12": 148,
    "Rectangle 31_13": 171,
    "Rectangle 31_2": 316,
    "Rectangle 31_3": 408,
    "Rectangle 31_4": 96,
    "Rectangle 31_5": 568,
    "Rectangle 31_6": 348,
    "Rectangle 31_7": 546,
    "Rectangle 31_8": 459,
    "Rectangle 31_9": 472,
    "Rectangle 32": 299,
    "Rectangle 32_10": 446,
    "Rectangle 32_11": 333,
    "Rectangle 32_12": 149,
    "Rectangle 32_13": 172,
    "Rectangle 32_2": 318,
    "Rectangle 32_3": 410,
    "Rectangle 32_4": 97,
    "Rectangle 32_5": 569,
    "Rectangle 32_6": 350,
    "Rectangle 32_7": 547,
    "Rectangle 32_8": 461,
    "Rectangle 32_9": 475,
    "Rectangle1": 212,
    "Rectangle12": 239,
    "Rectangle14": 246,
    "Rectangle18": 257,
    "Rectangle2": 850,
    "Rectangle20": 232,
    "Rectangle3": 735,
    "Rectangle3_1": 111,
    "Rectangle3_2": 437,
    "Rectangle3_3": 793,
    "Rectangle5": 216,
    "Refreshed On Header": 488,
    "Refreshed On Header_1": 490,
    "Refreshed On Label": 489,
    "Refreshed On Label_1": 491,
    "Report Header": 571,
    "Report Header_1": 575,
    "Report Header_10": 37,
    "Report Header_11": 881,
    "Report Header_12": 127,
    "Report Header_13": 151,
    "Report Header_14": 153,
    "Report Header_15": 174,
    "Report Header_16": 178,
    "Report Header_17": 19,
    "Report Header_2": 864,
    "Report Header_3": 526,
    "Report Header_4": 195,
    "Report Header_5": 810,
    "Report Header_6": 480,
    "Report Header_7": 482,
    "Report Header_8": 549,
    "Report Header_9": 551,
    "Report Label": 572,
    "Report Label_1": 576,
    "Report Label_10": 38,
    "Report Label_11": 882,
    "Report Label_12": 128,
    "Report Label_13": 152,
    "Report Label_14": 154,
    "Report Label_15": 175,
    "Report Label_16": 179,
    "Report Label_17": 20,
    "Report Label_2": 865,
    "Report Label_3": 527,
    "Report Label_4": 196,
    "Report Label_5": 811,
    "Report Label_6": 481,
    "Report Label_7": 483,
    "Report Label_8": 550,
    "Report Label_9": 552,
    "rowCount": 845,
    "search": 826,
    "search_1": 470,
    "search_3": 272,
    "search_4": 266,
    "search_5": 267,
    "search_6": 268,
    "search_7": 269,
    "search_8": 270,
    "searchClass": 829,
    "searchDesignation": 827,
    "searchLevel": 828,
    "Separator1": 841,
    "Separator1_1": 779,
    "Separator1_2": 284,
    "Separator1_3": 787,
    "Separator12": 240,
    "Separator14": 247,
    "Separator18": 258,
    "Separator2": 211,
    "Separator20": 233,
    "Separator6": 217,
    "skillCategory_6": 797,
    "skillCategory_7": 750,
    "skillCategory_8": 751,
    "skillCategory_9": 752,
    "SkillLabel": 562,
    "SkillLabel_1": 541,
    "SkillLabel_2": 143,
    "SkillLabel_3": 165,
    "skillName": 798,
    "skillName_1": 753,
    "skillName_2": 754,
    "skillName_3": 755,
    "Streamlining the process of schdeduling and staffing that could potentially save $47M": 502,
    "Subtitle1": 837,
    "Subtitle1_1": 838,
    "Subtitle1_10": 783,
    "Subtitle1_11": 784,
    "Subtitle1_12": 785,
    "Subtitle1_13": 786,
    "Subtitle1_2": 839,
    "Subtitle1_3": 840,
    "Subtitle1_4": 775,
    "Subtitle1_5": 776,
    "Subtitle1_6": 777,
    "Subtitle1_7": 778,
    "Subtitle1_8": 282,
    "Subtitle1_9": 283,
    "Subtitle13": 242,
    "Subtitle22": 249,
    "Subtitle25": 260,
    "Subtitle27": 235,
    "Subtitle6": 219,
    "Subtitle7": 210,
    "Table Headers Container": 479,
    "Team_1": 108,
    "Team_2": 434,
    "TextInput1": 213,
    "TextInput1_1": 263,
    "TextInput2": 893,
    "TextInput2_1": 894,
    "TextInput2_2": 895,
    "TextInput2_3": 896,
    "TextInput2_4": 897,
    "TextInput2_5": 898,
    "Title1": 836,
    "Title1_1": 774,
    "Title1_2": 281,
    "Title1_3": 782,
    "Title14": 243,
    "Title2": 621,
    "Title2_1": 638,
    "Title2_10": 632,
    "Title2_100": 703,
    "Title2_101": 704,
    "Title2_102": 705,
    "Title2_103": 706,
    "Title2_104": 707,
    "Title2_105": 708,
    "Title2_106": 709,
    "Title2_107": 710,
    "Title2_108": 711,
    "Title2_109": 712,
    "Title2_11": 633,
    "Title2_110": 713,
    "Title2_111": 714,
    "Title2_112": 715,
    "Title2_113": 716,
    "Title2_114": 717,
    "Title2_115": 718,
    "Title2_116": 719,
    "Title2_117": 720,
    "Title2_118": 721,
    "Title2_119": 722,
    "Title2_12": 634,
    "Title2_13": 635,
    "Title2_14": 636,
    "Title2_15": 637,
    "Title2_16": 596,
    "Title2_17": 597,
    "Title2_18": 606,
    "Title2_19": 607,
    "Title2_2": 640,
    "Title2_20": 608,
    "Title2_21": 609,
    "Title2_22": 610,
    "Title2_23": 611,
    "Title2_24": 612,
    "Title2_25": 674,
    "Title2_26": 675,
    "Title2_27": 684,
    "Title2_28": 685,
    "Title2_29": 686,
    "Title2_3": 639,
    "Title2_30": 687,
    "Title2_31": 688,
    "Title2_32": 689,
    "Title2_33": 613,
    "Title2_34": 614,
    "Title2_35": 615,
    "Title2_36": 616,
    "Title2_37": 617,
    "Title2_38": 618,
    "Title2_39": 619,
    "Title2_4": 641,
    "Title2_40": 690,
    "Title2_41": 691,
    "Title2_42": 692,
    "Title2_43": 693,
    "Title2_44": 694,
    "Title2_45": 695,
    "Title2_46": 696,
    "Title2_47": 697,
    "Title2_48": 623,
    "Title2_49": 624,
    "Title2_5": 642,
    "Title2_50": 625,
    "Title2_51": 626,
    "Title2_52": 627,
    "Title2_53": 628,
    "Title2_54": 629,
    "Title2_55": 598,
    "Title2_56": 599,
    "Title2_57": 600,
    "Title2_58": 601,
    "Title2_59": 602,
    "Title2_6": 643,
    "Title2_60": 630,
    "Title2_61": 603,
    "Title2_62": 604,
    "Title2_63": 605,
    "Title2_64": 647,
    "Title2_65": 648,
    "Title2_66": 649,
    "Title2_67": 650,
    "Title2_68": 651,
    "Title2_69": 652,
    "Title2_7": 644,
    "Title2_70": 653,
    "Title2_71": 654,
    "Title2_72": 655,
    "Title2_73": 656,
    "Title2_74": 657,
    "Title2_75": 658,
    "Title2_76": 659,
    "Title2_77": 660,
    "Title2_78": 661,
    "Title2_79": 662,
    "Title2_8": 622,
    "Title2_80": 663,
    "Title2_81": 664,
    "Title2_82": 665,
    "Title2_83": 666,
    "Title2_84": 667,
    "Title2_85": 668,
    "Title2_86": 669,
    "Title2_87": 670,
    "Title2_88": 676,
    "Title2_89": 677,
    "Title2_9": 631,
    "Title2_90": 678,
    "Title2_91": 679,
    "Title2_92": 680,
    "Title2_93": 681,
    "Title2_94": 682,
    "Title2_95": 683,
    "Title2_96": 699,
    "Title2_97": 700,
    "Title2_98": 701,
    "Title2_99": 702,
    "Title23": 250,
    "Title27": 261,
    "Title29": 236,
    "Title7": 209,
    "Title9": 220,
    "Toggle1": 67,
    "Toggle1_1": 386,
    "txtCaregiverID": 723,
    "Update Caregivers": 725,
    "Update Caregivers_1": 291,
    "Update Caregivers_2": 792
  },
  "FunctionParamsInvariantScripts": {},
  "FunctionParamsInvariantScriptsOnInstances": {},
  "HeaderLastSavedDateTimeUTC": "01/27/2024 14:49:12",
  "IsLegacyComponentAllowGlobalScopeCase": false,
  "LocalConnectionIDReferences": {
    "ac5e3fa2-316b-4d7d-9cd1-ba57171d3f8a": "\"/providers/microsoft.powerapps/apis/shared_sharepointonline/connections/9633fd352ce246268519c44be9cf01d5\""
  },
  "LocalDatabaseReferencesAsEmpty": false,
  "LocalResourceFileNames": {
    "caregivers": "0001.png",
    "dashboard": "0002.png",
    "leftArrow": "0003.png",
    "logo": "0004.png",
    "master_data": "0005.png",
    "Projects_2": "0006.png",
    "rightArrow": "0007.png"
  },
  "LocalResourceRootPaths": {
    "caregivers": "https://docserverpwaprodeus.blob.core.windows.net/e1d02bcc-db80-42b7-bda4-c62aa09fa300-1/resource/Assets0Images00001.png?skoid=58690ece-ec83-4ce2-9ce8-883d4d6a54ee&sktid=975f013f-7f24-47e8-a7d3-abc4752bf346&skt=2024-01-27T13%3A35%3A25Z&ske=2024-01-28T13%3A50%3A25Z&sks=b&skv=2022-11-02&sv=2022-11-02&spr=https&se=2024-01-28T13%3A50%3A25Z&sr=b&sp=r&sig=Aubk6g12IdFkmKBGor6zVcNjnr94SLRUbaJ9311%2F5NQ%3D",
    "dashboard": "https://docserverpwaprodeus.blob.core.windows.net/e1d02bcc-db80-42b7-bda4-c62aa09fa300-1/resource/Assets0Images00002.png?skoid=58690ece-ec83-4ce2-9ce8-883d4d6a54ee&sktid=975f013f-7f24-47e8-a7d3-abc4752bf346&skt=2024-01-27T13%3A35%3A25Z&ske=2024-01-28T13%3A50%3A25Z&sks=b&skv=2022-11-02&sv=2022-11-02&spr=https&se=2024-01-28T13%3A50%3A25Z&sr=b&sp=r&sig=27EpO5PDYhu%2Beoj3VaZlt1Py21t2G9wvvcre65RfjyM%3D",
    "leftArrow": "https://docserverpwaprodeus.blob.core.windows.net/e1d02bcc-db80-42b7-bda4-c62aa09fa300-1/resource/Assets0Images00003.png?skoid=58690ece-ec83-4ce2-9ce8-883d4d6a54ee&sktid=975f013f-7f24-47e8-a7d3-abc4752bf346&skt=2024-01-27T13%3A35%3A25Z&ske=2024-01-28T13%3A50%3A25Z&sks=b&skv=2022-11-02&sv=2022-11-02&spr=https&se=2024-01-28T13%3A50%3A25Z&sr=b&sp=r&sig=P89Q8QF%2BnW3z26BygSPIf0YcWTD90TmmftA%2FSvDKd%2Bc%3D",
    "logo": "https://docserverpwaprodeus.blob.core.windows.net/e1d02bcc-db80-42b7-bda4-c62aa09fa300-1/resource/Assets0Images00004.png?skoid=58690ece-ec83-4ce2-9ce8-883d4d6a54ee&sktid=975f013f-7f24-47e8-a7d3-abc4752bf346&skt=2024-01-27T13%3A35%3A25Z&ske=2024-01-28T13%3A50%3A25Z&sks=b&skv=2022-11-02&sv=2022-11-02&spr=https&se=2024-01-28T13%3A50%3A25Z&sr=b&sp=r&sig=3bajAkVR%2BMJFAQbc1jE08wJo0S72bEqchCUWS94%2BtMQ%3D",
    "master_data": "https://docserverpwaprodeus.blob.core.windows.net/e1d02bcc-db80-42b7-bda4-c62aa09fa300-1/resource/Assets0Images00005.png?skoid=58690ece-ec83-4ce2-9ce8-883d4d6a54ee&sktid=975f013f-7f24-47e8-a7d3-abc4752bf346&skt=2024-01-27T13%3A35%3A25Z&ske=2024-01-28T13%3A50%3A25Z&sks=b&skv=2022-11-02&sv=2022-11-02&spr=https&se=2024-01-28T13%3A50%3A25Z&sr=b&sp=r&sig=Yw6gtK52%2BTVHC4ugMSdKdJPd9Oje%2FXDQon83ahfG6bs%3D",
    "Projects_2": "https://docserverpwaprodeus.blob.core.windows.net/e1d02bcc-db80-42b7-bda4-c62aa09fa300-1/resource/Assets0Images00006.png?skoid=58690ece-ec83-4ce2-9ce8-883d4d6a54ee&sktid=975f013f-7f24-47e8-a7d3-abc4752bf346&skt=2024-01-27T13%3A35%3A25Z&ske=2024-01-28T13%3A50%3A25Z&sks=b&skv=2022-11-02&sv=2022-11-02&spr=https&se=2024-01-28T13%3A50%3A25Z&sr=b&sp=r&sig=Vpo103jpkxNgU0ErA2xWEueUYuf8PzMn11%2B2Fu1Ihe0%3D",
    "rightArrow": "https://docserverpwaprodeus.blob.core.windows.net/e1d02bcc-db80-42b7-bda4-c62aa09fa300-1/resource/Assets0Images00007.png?skoid=58690ece-ec83-4ce2-9ce8-883d4d6a54ee&sktid=975f013f-7f24-47e8-a7d3-abc4752bf346&skt=2024-01-27T13%3A35%3A25Z&ske=2024-01-28T13%3A50%3A25Z&sks=b&skv=2022-11-02&sv=2022-11-02&spr=https&se=2024-01-28T13%3A50%3A25Z&sr=b&sp=r&sig=1kOpCH6TiRMO1%2FFAjfWADEWFnZ14%2FNg15ilx6mX3ClY%3D"
  },
  "OldLogoFileName": "logo.jpg",
  "OrderComponentMetadata": {
    "d8d0600eb50240e7988dae5ff84131d3": 1,
    "e4379836dfc64dbda2b19049e588929b": 2,
    "f8bd1ef8470046c38c37a4a87233147e": 0
  },
  "OrderComponentTemplate": {
    "d8d0600eb50240e7988dae5ff84131d3": 1,
    "e4379836dfc64dbda2b19049e588929b": 2,
    "f8bd1ef8470046c38c37a4a87233147e": 0
  },
  "OrderDataSource": {
    "Advanced": 0,
    "Beginner": 1,
    "Capabilities": 2,
    "Capabilities_1": 3,
    "Caregiver Skills": 4,
    "Caregivers_1": 5,
    "Certifications": 6,
    "ComboBoxSample": 7,
    "CustomGallerySample": 8,
    "Discipline": 9,
    "DropDownSample": 10,
    "FilteredProjects": 18,
    "FilteredProjectsCapability": 19,
    "FilteredProjectsGroup": 20,
    "FilteredProjectsType": 21,
    "Intermediate": 11,
    "Project": 15,
    "Project Goals": 12,
    "Project Parent Group": 13,
    "Project Type": 14,
    "SelectedCapabilities": 22,
    "Skills": 16,
    "Skills_1": 17
  },
  "OrderGroupControls": {
    "Group1": {},
    "Group3": {
      "Button8": 6,
      "comment_1": 4,
      "Label7": 7,
      "msft_Label_37": 2,
      "msft_Label_38": 3,
      "msft_Label_39": 5,
      "skillCategory_7": 1,
      "skillName_1": 0
    },
    "Group3_1": {
      "Button8_1": 6,
      "comment_2": 4,
      "Label7_1": 7,
      "msft_Label_40": 2,
      "msft_Label_41": 3,
      "msft_Label_42": 5,
      "skillCategory_8": 1,
      "skillName_2": 0
    },
    "Group3_2": {
      "Button8_2": 8,
      "comment_3": 4,
      "Icon1_16": 5,
      "Icon1_17": 7,
      "Label7_2": 9,
      "msft_Label_43": 2,
      "msft_Label_44": 3,
      "msft_Label_45": 6,
      "skillCategory_9": 1,
      "skillName_3": 0
    },
    "Group7_4": {
      "comment": 4,
      "msft_Label_34": 2,
      "msft_Label_35": 3,
      "msft_Label_36": 5,
      "skillCategory_6": 1,
      "skillName": 0
    }
  },
  "OrderPcfTemplate": {},
  "OrderTemplate": {},
  "OrderXMLTemplate": {
    "button": 0,
    "combobox": 5,
    "datepicker": 10,
    "dropdown": 9,
    "gallery": 11,
    "groupContainer": 3,
    "icon": 6,
    "image": 2,
    "label": 1,
    "powerbi": 12,
    "rectangle": 8,
    "text": 4,
    "toggleSwitch": 7
  },
  "OverridablePropertiesEntry": {
    "2": {},
    "47": {},
    "Action Header": {},
    "Action Header_1": {},
    "Action Header_10": {},
    "Action Header_11": {},
    "Action Header_12": {},
    "Action Header_2": {},
    "Action Header_3": {},
    "Action Header_4": {},
    "Action Header_5": {},
    "Action Header_6": {},
    "Action Label": {},
    "Action Label_1": {},
    "Action Label_10": {},
    "Action Label_11": {},
    "Action Label_12": {},
    "Action Label_2": {},
    "Action Label_3": {},
    "Action Label_4": {},
    "Action Label_5": {},
    "Action Label_6": {},
    "Active": {},
    "App": {},
    "April-22 / June-23": {},
    "Button1": {},
    "Button2": {},
    "Button2_1": {},
    "Button2_2": {},
    "Button2_3": {},
    "Button3": {},
    "Button3_1": {},
    "Button4": {},
    "Button5": {},
    "Button5_1": {},
    "Button5_10": {},
    "Button5_11": {},
    "Button5_18": {},
    "Button5_19": {},
    "Button5_2": {},
    "Button5_20": {},
    "Button5_21": {},
    "Button5_22": {},
    "Button5_23": {},
    "Button5_3": {},
    "Button5_4": {},
    "Button5_5": {},
    "Button5_6": {},
    "Button5_7": {},
    "Button5_8": {},
    "Button5_9": {},
    "Button8": {},
    "Button8_1": {},
    "Button8_2": {},
    "Capability": {},
    "Capability_1": {},
    "capabilitydpdwn": {},
    "Caregivers": {},
    "Category": {},
    "Category Header": {},
    "Category Header_1": {},
    "Category Header_10": {},
    "Category Header_11": {},
    "Category Header_13": {},
    "Category Header_14": {},
    "Category Header_15": {},
    "Category Header_16": {},
    "Category Header_2": {},
    "Category Header_3": {},
    "Category Header_4": {},
    "Category Header_5": {},
    "Category Header_6": {},
    "Category Header_7": {},
    "Category Header_8": {},
    "Category Header_9": {},
    "Category Label": {},
    "Category Label_1": {},
    "Category Label_10": {},
    "Category Label_11": {},
    "Category Label_14": {},
    "Category Label_16": {},
    "Category Label_17": {},
    "Category Label_2": {},
    "Category Label_3": {},
    "Category Label_4": {},
    "Category Label_5": {},
    "Category Label_6": {},
    "Category Label_7": {},
    "Category Label_8": {},
    "Category Label_9": {},
    "Category_1": {},
    "Category_2": {},
    "Category_3": {},
    "Category_4": {},
    "Category_5": {},
    "Category_6": {},
    "Category_7": {},
    "Category_8": {},
    "Category_9": {},
    "CategoryLabel": {},
    "CategoryLabel_1": {},
    "Column - Header 10": {},
    "Column - Header 11": {},
    "Column - Header 12": {},
    "Column - Header 13": {},
    "Column - Header 13_1": {},
    "Column - Header 13_2": {},
    "Column - Header 13_3": {},
    "Column - Header 13_4": {},
    "Column - Header 14_1": {},
    "Column - Header 4_2": {},
    "Column - Header 4_4": {},
    "Column - Header 5_4": {},
    "Column - Header 6": {},
    "Column - Header 6_1": {},
    "Column - Header 7_2": {},
    "ComboBox1": {},
    "ComboBox1_1": {},
    "comment": {},
    "comment_1": {},
    "comment_2": {},
    "comment_3": {},
    "Component2_1": {},
    "Component2_2": {},
    "Data Analytics_1": {},
    "Data Analytics_2": {},
    "Data Analytics_3": {},
    "Databrics Spark Tableu": {},
    "DatePicker1": {},
    "DatePicker1_1": {},
    "Description Header": {},
    "Description Header_1": {},
    "Description Header_2": {},
    "Description Header_3": {},
    "Description Header_4": {},
    "Description Label": {},
    "Description Label_1": {},
    "Description Label_2": {},
    "Description Label_3": {},
    "Description Label_4": {},
    "descriptionlabel": {},
    "descriptionlabel_1": {},
    "Edit_3": {},
    "Favourite Header": {},
    "Favourite Label": {},
    "Frame 10": {},
    "Gallery1": {},
    "Gallery1_1": {},
    "Gallery1_2": {},
    "Gallery1_3": {},
    "Gallery17": {},
    "Gallery28": {},
    "Gallery29": {},
    "Gallery3": {},
    "Gallery31": {},
    "Gallery33": {},
    "Gallery4": {},
    "Gallery5": {},
    "Gallery5_1": {},
    "Gallery5_2": {},
    "Gallery5_3": {},
    "Gallery5_4": {},
    "Gallery6": {},
    "Gallery6_1": {},
    "Gallery7": {},
    "Gallery7_1": {},
    "Gallery7_2": {},
    "Gallery7_3": {},
    "Gallery8": {},
    "galleryTemplate1": {},
    "galleryTemplate1_1": {},
    "galleryTemplate1_2": {},
    "galleryTemplate1_3": {},
    "galleryTemplate18": {},
    "galleryTemplate2": {},
    "galleryTemplate29": {},
    "galleryTemplate30": {},
    "galleryTemplate32": {},
    "galleryTemplate34": {},
    "galleryTemplate4": {},
    "galleryTemplate5": {},
    "galleryTemplate6": {},
    "galleryTemplate6_1": {},
    "galleryTemplate6_2": {},
    "galleryTemplate6_3": {},
    "galleryTemplate6_4": {},
    "galleryTemplate7": {},
    "galleryTemplate7_1": {},
    "galleryTemplate8": {},
    "galleryTemplate8_1": {},
    "galleryTemplate8_2": {},
    "galleryTemplate8_3": {},
    "galleryTemplate9": {},
    "Group1": {},
    "Group3": {},
    "Group3_1": {},
    "Group3_2": {},
    "Group7_4": {},
    "grouplabel": {},
    "hiddenGallery": {},
    "Host": {},
    "Icon1_1": {},
    "Icon1_16": {},
    "Icon1_17": {},
    "Icon1_18": {},
    "Icon1_19": {},
    "Icon1_2": {},
    "Icon1_20": {},
    "Icon1_21": {},
    "Icon1_22": {},
    "Icon1_23": {},
    "Icon1_24": {},
    "Icon1_25": {},
    "Icon1_26": {},
    "Icon1_27": {},
    "Icon1_28": {},
    "Icon1_29": {},
    "Icon1_3": {},
    "Icon1_30": {},
    "Icon1_31": {},
    "Icon1_32": {},
    "Icon1_33": {},
    "Icon1_34": {},
    "Icon1_35": {},
    "Icon1_36": {},
    "Icon1_37": {},
    "Icon1_38": {},
    "Icon1_39": {},
    "Icon1_4": {},
    "Icon1_40": {},
    "Icon1_41": {},
    "Icon1_42": {},
    "Icon1_43": {},
    "Icon1_44": {},
    "Icon1_45": {},
    "Icon1_46": {},
    "Icon1_5": {},
    "Icon1_6": {},
    "Icon1_7": {},
    "Icon1_8": {},
    "Icon1_9": {},
    "Image1": {},
    "Image3": {},
    "Image4": {},
    "Image5": {},
    "Image5_1": {},
    "Image5_2": {},
    "Image5_3": {},
    "Label1": {},
    "Label10": {},
    "Label10_1": {},
    "Label10_2": {},
    "Label10_3": {},
    "Label11": {},
    "Label12": {},
    "Label12_1": {},
    "Label12_2": {},
    "Label13": {},
    "Label13_1": {},
    "Label13_2": {},
    "Label15": {},
    "Label15_1": {},
    "Label16": {},
    "Label16_1": {},
    "Label16_2": {},
    "Label16_3": {},
    "Label2": {},
    "Label2_1": {},
    "Label2_10": {},
    "Label2_12": {},
    "Label2_13": {},
    "Label2_14": {},
    "Label2_15": {},
    "Label2_2": {},
    "Label2_3": {},
    "Label2_8": {},
    "Label2_9": {},
    "Label23": {},
    "Label25": {},
    "Label3": {},
    "Label3_1": {},
    "Label3_10": {},
    "Label3_11": {},
    "Label3_12": {},
    "Label3_13": {},
    "Label3_14": {},
    "Label3_15": {},
    "Label3_16": {},
    "Label3_17": {},
    "Label3_18": {},
    "Label3_19": {},
    "Label3_2": {},
    "Label3_20": {},
    "Label3_21": {},
    "Label3_22": {},
    "Label3_23": {},
    "Label3_24": {},
    "Label3_25": {},
    "Label3_26": {},
    "Label3_27": {},
    "Label3_28": {},
    "Label3_29": {},
    "Label3_3": {},
    "Label3_30": {},
    "Label3_31": {},
    "Label3_4": {},
    "Label3_5": {},
    "Label3_6": {},
    "Label3_7": {},
    "Label3_8": {},
    "Label3_9": {},
    "Label4": {},
    "Label6": {},
    "Label6_1": {},
    "Label6_10": {},
    "Label6_11": {},
    "Label6_12": {},
    "Label6_13": {},
    "Label6_14": {},
    "Label6_15": {},
    "Label6_16": {},
    "Label6_17": {},
    "Label6_18": {},
    "Label6_19": {},
    "Label6_2": {},
    "Label6_20": {},
    "Label6_21": {},
    "Label6_22": {},
    "Label6_23": {},
    "Label6_24": {},
    "Label6_25": {},
    "Label6_26": {},
    "Label6_27": {},
    "Label6_28": {},
    "Label6_29": {},
    "Label6_3": {},
    "Label6_30": {},
    "Label6_31": {},
    "Label6_32": {},
    "Label6_33": {},
    "Label6_34": {},
    "Label6_35": {},
    "Label6_36": {},
    "Label6_37": {},
    "Label6_38": {},
    "Label6_4": {},
    "Label6_5": {},
    "Label6_6": {},
    "Label6_7": {},
    "Label6_8": {},
    "Label6_9": {},
    "Label7": {},
    "Label7_1": {},
    "Label7_2": {},
    "Label8": {},
    "Manasa": {},
    "msft_Button": {},
    "msft_Button_10": {},
    "msft_Button_11": {},
    "msft_Button_12": {},
    "msft_Button_13": {},
    "msft_Button_14": {},
    "msft_Button_15": {},
    "msft_Button_16": {},
    "msft_Button_17": {},
    "msft_Button_18": {},
    "msft_Button_19": {},
    "msft_Button_20": {},
    "msft_Button_21": {},
    "msft_Button_22": {},
    "msft_Button_23": {},
    "msft_Button_24": {},
    "msft_Button_25": {},
    "msft_Button_26": {},
    "msft_Button_27": {},
    "msft_Button_28": {},
    "msft_Button_29": {},
    "msft_Button_30": {},
    "msft_Button_31": {},
    "msft_Button_32": {},
    "msft_Button_33": {},
    "msft_Button_34": {},
    "msft_Button_35": {},
    "msft_Button_36": {},
    "msft_Button_37": {},
    "msft_Button_38": {},
    "msft_Button_39": {},
    "msft_Button_4": {},
    "msft_Button_40": {},
    "msft_Button_41": {},
    "msft_Button_42": {},
    "msft_Button_43": {},
    "msft_Button_44": {},
    "msft_Button_45": {},
    "msft_Button_46": {},
    "msft_Button_47": {},
    "msft_Button_48": {},
    "msft_Button_49": {},
    "msft_Button_50": {},
    "msft_Button_51": {},
    "msft_Button_52": {},
    "msft_Button_53": {},
    "msft_Button_54": {},
    "msft_Button_55": {},
    "msft_Button_6": {},
    "msft_Button_7": {},
    "msft_Button_8": {},
    "msft_Button_9": {},
    "msft_ComboBox_5": {},
    "msft_DatePicker_2": {},
    "msft_DatePicker_3": {},
    "msft_DatePicker_4": {},
    "msft_DatePicker_5": {},
    "msft_Dropdown": {},
    "msft_Dropdown_10": {},
    "msft_Dropdown_12": {},
    "msft_Dropdown_16": {},
    "msft_Dropdown_18": {},
    "msft_Dropdown_19": {},
    "msft_Dropdown_20": {},
    "msft_Dropdown_21": {},
    "msft_Dropdown_22": {},
    "msft_Dropdown_23": {},
    "msft_Dropdown_24": {},
    "msft_Dropdown_25": {},
    "msft_Dropdown_27": {},
    "msft_Dropdown_28": {},
    "msft_Dropdown_29": {},
    "msft_Dropdown_30": {},
    "msft_Dropdown_31": {},
    "msft_Dropdown_32": {},
    "msft_Dropdown_33": {},
    "msft_Dropdown_9": {},
    "msft_Label": {},
    "msft_Label_1": {},
    "msft_Label_10": {},
    "msft_Label_11": {},
    "msft_Label_12": {},
    "msft_Label_13": {},
    "msft_Label_14": {},
    "msft_Label_15": {},
    "msft_Label_16": {},
    "msft_Label_17": {},
    "msft_Label_18": {},
    "msft_Label_2": {},
    "msft_Label_34": {},
    "msft_Label_35": {},
    "msft_Label_36": {},
    "msft_Label_37": {},
    "msft_Label_38": {},
    "msft_Label_39": {},
    "msft_Label_40": {},
    "msft_Label_41": {},
    "msft_Label_42": {},
    "msft_Label_43": {},
    "msft_Label_44": {},
    "msft_Label_45": {},
    "msft_Label_5": {},
    "msft_Label_6": {},
    "msft_Label_7": {},
    "msft_Label_8": {},
    "msft_Label_9": {},
    "msft_TextInput": {},
    "msft_TextInput_1": {},
    "msft_TextInput_10": {},
    "msft_TextInput_11": {},
    "msft_TextInput_12": {},
    "msft_TextInput_13": {},
    "msft_TextInput_14": {},
    "msft_TextInput_15": {},
    "msft_TextInput_16": {},
    "msft_TextInput_17": {},
    "msft_TextInput_19": {},
    "msft_TextInput_20": {},
    "msft_TextInput_21": {},
    "msft_TextInput_22": {},
    "msft_TextInput_4": {},
    "msft_TextInput_5": {},
    "msft_TextInput_6": {},
    "msft_TextInput_7": {},
    "msft_TextInput_8": {},
    "msft_TextInput_9": {},
    "msftBirthday_DOJ": {},
    "msftcapability": {},
    "msftcaregivers": {},
    "msftconfirmationscreen": {},
    "msftDashboard": {},
    "msftdiscipline": {},
    "msfteditcapability": {},
    "msfteditdiscipline": {},
    "msfteditgroup": {},
    "msfteditproject": {},
    "msfteditprojectgoal": {},
    "msfteditprojecttype": {},
    "msftedittechnology": {},
    "msftgroup": {},
    "msftMasterData": {},
    "msftnewcategory": {},
    "msftnewcategory2": {},
    "msftnewdiscipline": {},
    "msftnewgroup": {},
    "msftnewproject": {},
    "msftnewprojectgoal": {},
    "msftnewprojecttype": {},
    "msftproject": {},
    "msftprojectgoal": {},
    "msftprojecttype": {},
    "msfttechnology": {},
    "msftUpdatecaregivers": {},
    "msftUpdateSkill_Caregiver": {},
    "navBar_1": {},
    "navBar_2": {},
    "navBarHorizontal": {},
    "navBarHorizontal_1": {},
    "navBarHorizontal_10": {},
    "navBarHorizontal_11": {},
    "navBarHorizontal_12": {},
    "navBarHorizontal_13": {},
    "navBarHorizontal_14": {},
    "navBarHorizontal_15": {},
    "navBarHorizontal_16": {},
    "navBarHorizontal_17": {},
    "navBarHorizontal_18": {},
    "navBarHorizontal_19": {},
    "navBarHorizontal_2": {},
    "navBarHorizontal_20": {},
    "navBarHorizontal_21": {},
    "navBarHorizontal_22": {},
    "navBarHorizontal_23": {},
    "navBarHorizontal_24": {},
    "navBarHorizontal_25": {},
    "navBarHorizontal_3": {},
    "navBarHorizontal_4": {},
    "navBarHorizontal_5": {},
    "navBarHorizontal_6": {},
    "navBarHorizontal_7": {},
    "navBarHorizontal_8": {},
    "navBarHorizontal_9": {},
    "navBarVertical": {},
    "navBarVertical_1": {},
    "navBarVertical_10": {},
    "navBarVertical_11": {},
    "navBarVertical_12": {},
    "navBarVertical_13": {},
    "navBarVertical_14": {},
    "navBarVertical_15": {},
    "navBarVertical_16": {},
    "navBarVertical_17": {},
    "navBarVertical_18": {},
    "navBarVertical_19": {},
    "navBarVertical_2": {},
    "navBarVertical_20": {},
    "navBarVertical_21": {},
    "navBarVertical_22": {},
    "navBarVertical_23": {},
    "navBarVertical_24": {},
    "navBarVertical_25": {},
    "navBarVertical_3": {},
    "navBarVertical_4": {},
    "navBarVertical_5": {},
    "navBarVertical_6": {},
    "navBarVertical_7": {},
    "navBarVertical_8": {},
    "navBarVertical_9": {},
    "New Category": {},
    "New Category_1": {},
    "New Category_2": {},
    "New Category_3": {},
    "New Category_4": {},
    "New Project_1": {},
    "New Project_2": {},
    "New Project_3": {},
    "New Project_4": {},
    "New Project_5": {},
    "New Project_6": {},
    "New Project_7": {},
    "New Project_8": {},
    "New Technology": {},
    "NextArrow11": {},
    "NextArrow13": {},
    "NextArrow17": {},
    "NextArrow19": {},
    "NextArrow4": {},
    "Owner Header": {},
    "Owner Label": {},
    "paginationBar": {},
    "PowerBI1": {},
    "Predictive scheduling": {},
    "Projects_1": {},
    "projectsactivelabel": {},
    "React is a JavaScript library for building user interfaces. It is declarative, efficient, and flexible. React makes it easy to create interactive UIs by using a component-based approach.": {},
    "React is a JavaScript library for building user interfaces. It is declarative, efficient, and flexible. React makes it easy to create interactive UIs by using a component-based approach._1": {},
    "React is a JavaScript library for building user interfaces. It is declarative, efficient, and flexible. React makes it easy to create interactive UIs by using a component-based approach._2": {},
    "React is a JavaScript library for building user interfaces. It is declarative, efficient, and flexible. React makes it easy to create interactive UIs by using a component-based approach._3": {},
    "React is a JavaScript library for building user interfaces. It is declarative, efficient, and flexible. React makes it easy to create interactive UIs by using a component-based approach._4": {},
    "React is a JavaScript library for building user interfaces. It is declarative, efficient, and flexible. React makes it easy to create interactive UIs by using a component-based approach._5": {},
    "Rectangle 31": {},
    "Rectangle 31_10": {},
    "Rectangle 31_11": {},
    "Rectangle 31_12": {},
    "Rectangle 31_13": {},
    "Rectangle 31_2": {},
    "Rectangle 31_3": {},
    "Rectangle 31_4": {},
    "Rectangle 31_5": {},
    "Rectangle 31_6": {},
    "Rectangle 31_7": {},
    "Rectangle 31_8": {},
    "Rectangle 31_9": {},
    "Rectangle 32": {},
    "Rectangle 32_10": {},
    "Rectangle 32_11": {},
    "Rectangle 32_12": {},
    "Rectangle 32_13": {},
    "Rectangle 32_2": {},
    "Rectangle 32_3": {},
    "Rectangle 32_4": {},
    "Rectangle 32_5": {},
    "Rectangle 32_6": {},
    "Rectangle 32_7": {},
    "Rectangle 32_8": {},
    "Rectangle 32_9": {},
    "Rectangle1": {},
    "Rectangle12": {},
    "Rectangle14": {},
    "Rectangle18": {},
    "Rectangle2": {},
    "Rectangle20": {},
    "Rectangle3": {},
    "Rectangle3_1": {},
    "Rectangle3_2": {},
    "Rectangle3_3": {},
    "Rectangle5": {},
    "Refreshed On Header": {},
    "Refreshed On Header_1": {},
    "Refreshed On Label": {},
    "Refreshed On Label_1": {},
    "Report Header": {},
    "Report Header_1": {},
    "Report Header_10": {},
    "Report Header_11": {},
    "Report Header_12": {},
    "Report Header_13": {},
    "Report Header_14": {},
    "Report Header_15": {},
    "Report Header_16": {},
    "Report Header_17": {},
    "Report Header_2": {},
    "Report Header_3": {},
    "Report Header_4": {},
    "Report Header_5": {},
    "Report Header_6": {},
    "Report Header_7": {},
    "Report Header_8": {},
    "Report Header_9": {},
    "Report Label": {},
    "Report Label_1": {},
    "Report Label_10": {},
    "Report Label_11": {},
    "Report Label_12": {},
    "Report Label_13": {},
    "Report Label_14": {},
    "Report Label_15": {},
    "Report Label_16": {},
    "Report Label_17": {},
    "Report Label_2": {},
    "Report Label_3": {},
    "Report Label_4": {},
    "Report Label_5": {},
    "Report Label_6": {},
    "Report Label_7": {},
    "Report Label_8": {},
    "Report Label_9": {},
    "rowCount": {},
    "search": {},
    "search_1": {},
    "search_3": {},
    "search_4": {},
    "search_5": {},
    "search_6": {},
    "search_7": {},
    "search_8": {},
    "searchClass": {},
    "searchDesignation": {},
    "searchLevel": {},
    "Separator1": {},
    "Separator1_1": {},
    "Separator1_2": {},
    "Separator1_3": {},
    "Separator12": {},
    "Separator14": {},
    "Separator18": {},
    "Separator2": {},
    "Separator20": {},
    "Separator6": {},
    "skillCategory_6": {},
    "skillCategory_7": {},
    "skillCategory_8": {},
    "skillCategory_9": {},
    "SkillLabel": {},
    "SkillLabel_1": {},
    "SkillLabel_2": {},
    "SkillLabel_3": {},
    "skillName": {},
    "skillName_1": {},
    "skillName_2": {},
    "skillName_3": {},
    "Streamlining the process of schdeduling and staffing that could potentially save $47M": {},
    "Subtitle1": {},
    "Subtitle1_1": {},
    "Subtitle1_10": {},
    "Subtitle1_11": {},
    "Subtitle1_12": {},
    "Subtitle1_13": {},
    "Subtitle1_2": {},
    "Subtitle1_3": {},
    "Subtitle1_4": {},
    "Subtitle1_5": {},
    "Subtitle1_6": {},
    "Subtitle1_7": {},
    "Subtitle1_8": {},
    "Subtitle1_9": {},
    "Subtitle13": {},
    "Subtitle22": {},
    "Subtitle25": {},
    "Subtitle27": {},
    "Subtitle6": {},
    "Subtitle7": {},
    "Table Headers Container": {},
    "Team_1": {},
    "Team_2": {},
    "TextInput1": {},
    "TextInput1_1": {},
    "TextInput2": {},
    "TextInput2_1": {},
    "TextInput2_2": {},
    "TextInput2_3": {},
    "TextInput2_4": {},
    "TextInput2_5": {},
    "Title1": {},
    "Title1_1": {},
    "Title1_2": {},
    "Title1_3": {},
    "Title14": {},
    "Title2": {},
    "Title2_1": {},
    "Title2_10": {},
    "Title2_100": {},
    "Title2_101": {},
    "Title2_102": {},
    "Title2_103": {},
    "Title2_104": {},
    "Title2_105": {},
    "Title2_106": {},
    "Title2_107": {},
    "Title2_108": {},
    "Title2_109": {},
    "Title2_11": {},
    "Title2_110": {},
    "Title2_111": {},
    "Title2_112": {},
    "Title2_113": {},
    "Title2_114": {},
    "Title2_115": {},
    "Title2_116": {},
    "Title2_117": {},
    "Title2_118": {},
    "Title2_119": {},
    "Title2_12": {},
    "Title2_13": {},
    "Title2_14": {},
    "Title2_15": {},
    "Title2_16": {},
    "Title2_17": {},
    "Title2_18": {},
    "Title2_19": {},
    "Title2_2": {},
    "Title2_20": {},
    "Title2_21": {},
    "Title2_22": {},
    "Title2_23": {},
    "Title2_24": {},
    "Title2_25": {},
    "Title2_26": {},
    "Title2_27": {},
    "Title2_28": {},
    "Title2_29": {},
    "Title2_3": {},
    "Title2_30": {},
    "Title2_31": {},
    "Title2_32": {},
    "Title2_33": {},
    "Title2_34": {},
    "Title2_35": {},
    "Title2_36": {},
    "Title2_37": {},
    "Title2_38": {},
    "Title2_39": {},
    "Title2_4": {},
    "Title2_40": {},
    "Title2_41": {},
    "Title2_42": {},
    "Title2_43": {},
    "Title2_44": {},
    "Title2_45": {},
    "Title2_46": {},
    "Title2_47": {},
    "Title2_48": {},
    "Title2_49": {},
    "Title2_5": {},
    "Title2_50": {},
    "Title2_51": {},
    "Title2_52": {},
    "Title2_53": {},
    "Title2_54": {},
    "Title2_55": {},
    "Title2_56": {},
    "Title2_57": {},
    "Title2_58": {},
    "Title2_59": {},
    "Title2_6": {},
    "Title2_60": {},
    "Title2_61": {},
    "Title2_62": {},
    "Title2_63": {},
    "Title2_64": {},
    "Title2_65": {},
    "Title2_66": {},
    "Title2_67": {},
    "Title2_68": {},
    "Title2_69": {},
    "Title2_7": {},
    "Title2_70": {},
    "Title2_71": {},
    "Title2_72": {},
    "Title2_73": {},
    "Title2_74": {},
    "Title2_75": {},
    "Title2_76": {},
    "Title2_77": {},
    "Title2_78": {},
    "Title2_79": {},
    "Title2_8": {},
    "Title2_80": {},
    "Title2_81": {},
    "Title2_82": {},
    "Title2_83": {},
    "Title2_84": {},
    "Title2_85": {},
    "Title2_86": {},
    "Title2_87": {},
    "Title2_88": {},
    "Title2_89": {},
    "Title2_9": {},
    "Title2_90": {},
    "Title2_91": {},
    "Title2_92": {},
    "Title2_93": {},
    "Title2_94": {},
    "Title2_95": {},
    "Title2_96": {},
    "Title2_97": {},
    "Title2_98": {},
    "Title2_99": {},
    "Title23": {},
    "Title27": {},
    "Title29": {},
    "Title7": {},
    "Title9": {},
    "Toggle1": {},
    "Toggle1_1": {},
    "txtCaregiverID": {},
    "Update Caregivers": {},
    "Update Caregivers_1": {},
    "Update Caregivers_2": {}
  },
  "PCFDynamicSchemaForIRRetrievalEntry": {},
  "PCFTemplateEntry": {},
  "PublishOrderIndices": {
    "2": 628,
    "47": 700,
    "Action Header": 691,
    "Action Header_1": 100,
    "Action Header_10": 270,
    "Action Header_11": 294,
    "Action Header_12": 136,
    "Action Header_2": 644,
    "Action Header_3": 314,
    "Action Header_4": 605,
    "Action Header_5": 47,
    "Action Header_6": 668,
    "Action Label": 698,
    "Action Label_1": 107,
    "Action Label_10": 275,
    "Action Label_11": 300,
    "Action Label_12": 143,
    "Action Label_2": 652,
    "Action Label_3": 321,
    "Action Label_4": 614,
    "Action Label_5": 55,
    "Action Label_6": 673,
    "Active": 631,
    "App": 0,
    "April-22 / June-23": 630,
    "Button1": 397,
    "Button2": 874,
    "Button2_1": 410,
    "Button2_2": 876,
    "Button2_3": 21,
    "Button3": 375,
    "Button3_1": 377,
    "Button4": 880,
    "Button5": 304,
    "Button5_1": 303,
    "Button5_10": 94,
    "Button5_11": 93,
    "Button5_18": 256,
    "Button5_19": 257,
    "Button5_2": 39,
    "Button5_20": 278,
    "Button5_21": 279,
    "Button5_22": 129,
    "Button5_23": 130,
    "Button5_3": 38,
    "Button5_4": 635,
    "Button5_5": 636,
    "Button5_6": 655,
    "Button5_7": 656,
    "Button5_8": 676,
    "Button5_9": 677,
    "Button8": 702,
    "Button8_1": 704,
    "Button8_2": 707,
    "Capability": 97,
    "Capability_1": 133,
    "capabilitydpdwn": 337,
    "Caregivers": 59,
    "Category": 686,
    "Category Header": 688,
    "Category Header_1": 291,
    "Category Header_10": 154,
    "Category Header_11": 160,
    "Category Header_13": 117,
    "Category Header_14": 124,
    "Category Header_15": 244,
    "Category Header_16": 250,
    "Category Header_2": 643,
    "Category Header_3": 312,
    "Category Header_4": 318,
    "Category Header_5": 599,
    "Category Header_6": 313,
    "Category Header_7": 649,
    "Category Header_8": 46,
    "Category Header_9": 52,
    "Category Label": 695,
    "Category Label_1": 297,
    "Category Label_10": 161,
    "Category Label_11": 102,
    "Category Label_14": 125,
    "Category Label_16": 251,
    "Category Label_17": 137,
    "Category Label_2": 650,
    "Category Label_3": 319,
    "Category Label_4": 651,
    "Category Label_5": 608,
    "Category Label_6": 320,
    "Category Label_7": 53,
    "Category Label_8": 54,
    "Category Label_9": 101,
    "Category_1": 641,
    "Category_2": 310,
    "Category_3": 44,
    "Category_4": 664,
    "Category_5": 152,
    "Category_6": 115,
    "Category_7": 242,
    "Category_8": 266,
    "Category_9": 289,
    "CategoryLabel": 679,
    "CategoryLabel_1": 282,
    "Column - Header 10": 619,
    "Column - Header 11": 622,
    "Column - Header 12": 621,
    "Column - Header 13": 692,
    "Column - Header 13_1": 669,
    "Column - Header 13_2": 616,
    "Column - Header 13_3": 271,
    "Column - Header 13_4": 295,
    "Column - Header 14_1": 620,
    "Column - Header 4_2": 645,
    "Column - Header 4_4": 615,
    "Column - Header 5_4": 617,
    "Column - Header 6": 693,
    "Column - Header 6_1": 618,
    "Column - Header 7_2": 623,
    "ComboBox1": 482,
    "ComboBox1_1": 165,
    "comment": 890,
    "comment_1": 739,
    "comment_2": 740,
    "comment_3": 741,
    "Component2_1": 590,
    "Component2_2": 58,
    "Data Analytics_1": 653,
    "Data Analytics_2": 626,
    "Data Analytics_3": 48,
    "Databrics Spark Tableu": 629,
    "DatePicker1": 462,
    "DatePicker1_1": 463,
    "Description Header": 690,
    "Description Header_1": 600,
    "Description Header_2": 667,
    "Description Header_3": 269,
    "Description Header_4": 293,
    "Description Label": 697,
    "Description Label_1": 609,
    "Description Label_2": 672,
    "Description Label_3": 274,
    "Description Label_4": 299,
    "descriptionlabel": 306,
    "descriptionlabel_1": 148,
    "Edit_3": 632,
    "Favourite Header": 604,
    "Favourite Label": 613,
    "Frame 10": 596,
    "Gallery1": 69,
    "Gallery1_1": 18,
    "Gallery1_2": 354,
    "Gallery1_3": 19,
    "Gallery17": 332,
    "Gallery28": 333,
    "Gallery29": 334,
    "Gallery3": 721,
    "Gallery31": 336,
    "Gallery33": 331,
    "Gallery4": 325,
    "Gallery5": 709,
    "Gallery5_1": 746,
    "Gallery5_2": 711,
    "Gallery5_3": 710,
    "Gallery5_4": 822,
    "Gallery6": 326,
    "Gallery6_1": 327,
    "Gallery7": 717,
    "Gallery7_1": 362,
    "Gallery7_2": 718,
    "Gallery7_3": 15,
    "Gallery8": 323,
    "galleryTemplate1": 75,
    "galleryTemplate1_1": 22,
    "galleryTemplate1_2": 404,
    "galleryTemplate1_3": 29,
    "galleryTemplate18": 384,
    "galleryTemplate2": 82,
    "galleryTemplate29": 390,
    "galleryTemplate30": 396,
    "galleryTemplate32": 398,
    "galleryTemplate34": 378,
    "galleryTemplate4": 877,
    "galleryTemplate5": 368,
    "galleryTemplate6": 747,
    "galleryTemplate6_1": 772,
    "galleryTemplate6_2": 848,
    "galleryTemplate6_3": 797,
    "galleryTemplate6_4": 823,
    "galleryTemplate7": 374,
    "galleryTemplate7_1": 376,
    "galleryTemplate8": 873,
    "galleryTemplate8_1": 409,
    "galleryTemplate8_2": 875,
    "galleryTemplate8_3": 20,
    "galleryTemplate9": 363,
    "Group1": 745,
    "Group3": 742,
    "Group3_1": 743,
    "Group3_2": 744,
    "Group7_4": 891,
    "grouplabel": 307,
    "hiddenGallery": 70,
    "Host": 0,
    "Icon1_1": 483,
    "Icon1_16": 723,
    "Icon1_17": 722,
    "Icon1_18": 492,
    "Icon1_19": 493,
    "Icon1_2": 484,
    "Icon1_20": 494,
    "Icon1_21": 495,
    "Icon1_22": 496,
    "Icon1_23": 497,
    "Icon1_24": 166,
    "Icon1_25": 498,
    "Icon1_26": 167,
    "Icon1_27": 168,
    "Icon1_28": 169,
    "Icon1_29": 170,
    "Icon1_3": 485,
    "Icon1_30": 171,
    "Icon1_31": 172,
    "Icon1_32": 173,
    "Icon1_33": 174,
    "Icon1_34": 175,
    "Icon1_35": 176,
    "Icon1_36": 177,
    "Icon1_37": 178,
    "Icon1_38": 179,
    "Icon1_39": 180,
    "Icon1_4": 486,
    "Icon1_40": 412,
    "Icon1_41": 413,
    "Icon1_42": 431,
    "Icon1_43": 446,
    "Icon1_44": 461,
    "Icon1_45": 571,
    "Icon1_46": 556,
    "Icon1_5": 487,
    "Icon1_6": 488,
    "Icon1_7": 489,
    "Icon1_8": 490,
    "Icon1_9": 491,
    "Image1": 2,
    "Image3": 74,
    "Image4": 73,
    "Image5": 4,
    "Image5_1": 5,
    "Image5_2": 6,
    "Image5_3": 7,
    "Label1": 71,
    "Label10": 328,
    "Label10_1": 329,
    "Label10_2": 330,
    "Label10_3": 335,
    "Label11": 634,
    "Label12": 12,
    "Label12_1": 13,
    "Label12_2": 14,
    "Label13": 499,
    "Label13_1": 501,
    "Label13_2": 500,
    "Label15": 637,
    "Label15_1": 40,
    "Label16": 638,
    "Label16_1": 41,
    "Label16_2": 112,
    "Label16_3": 239,
    "Label2": 65,
    "Label2_1": 66,
    "Label2_10": 351,
    "Label2_12": 352,
    "Label2_13": 353,
    "Label2_14": 348,
    "Label2_15": 349,
    "Label2_2": 67,
    "Label2_3": 68,
    "Label2_8": 346,
    "Label2_9": 350,
    "Label23": 37,
    "Label25": 84,
    "Label3": 95,
    "Label3_1": 181,
    "Label3_10": 188,
    "Label3_11": 189,
    "Label3_12": 190,
    "Label3_13": 515,
    "Label3_14": 517,
    "Label3_15": 519,
    "Label3_16": 527,
    "Label3_17": 529,
    "Label3_18": 531,
    "Label3_19": 536,
    "Label3_2": 182,
    "Label3_20": 546,
    "Label3_21": 194,
    "Label3_22": 192,
    "Label3_23": 544,
    "Label3_24": 229,
    "Label3_25": 230,
    "Label3_26": 509,
    "Label3_27": 204,
    "Label3_28": 201,
    "Label3_29": 503,
    "Label3_3": 184,
    "Label3_30": 505,
    "Label3_31": 504,
    "Label3_4": 513,
    "Label3_5": 512,
    "Label3_6": 131,
    "Label3_7": 185,
    "Label3_8": 186,
    "Label3_9": 187,
    "Label4": 715,
    "Label6": 191,
    "Label6_1": 193,
    "Label6_10": 523,
    "Label6_11": 525,
    "Label6_12": 532,
    "Label6_13": 538,
    "Label6_14": 200,
    "Label6_15": 540,
    "Label6_16": 541,
    "Label6_17": 542,
    "Label6_18": 543,
    "Label6_19": 533,
    "Label6_2": 195,
    "Label6_20": 426,
    "Label6_21": 427,
    "Label6_22": 428,
    "Label6_23": 442,
    "Label6_24": 443,
    "Label6_25": 477,
    "Label6_26": 478,
    "Label6_27": 479,
    "Label6_28": 480,
    "Label6_29": 573,
    "Label6_3": 196,
    "Label6_30": 574,
    "Label6_31": 558,
    "Label6_32": 559,
    "Label6_33": 539,
    "Label6_34": 198,
    "Label6_35": 458,
    "Label6_36": 459,
    "Label6_37": 209,
    "Label6_38": 506,
    "Label6_4": 197,
    "Label6_5": 199,
    "Label6_6": 202,
    "Label6_7": 203,
    "Label6_8": 205,
    "Label6_9": 521,
    "Label7": 703,
    "Label7_1": 705,
    "Label7_2": 706,
    "Label8": 878,
    "Manasa": 627,
    "msft_Button": 425,
    "msft_Button_10": 104,
    "msft_Button_11": 355,
    "msft_Button_12": 358,
    "msft_Button_13": 587,
    "msft_Button_14": 315,
    "msft_Button_15": 316,
    "msft_Button_16": 86,
    "msft_Button_17": 87,
    "msft_Button_18": 357,
    "msft_Button_19": 444,
    "msft_Button_20": 208,
    "msft_Button_21": 210,
    "msft_Button_22": 356,
    "msft_Button_23": 572,
    "msft_Button_24": 359,
    "msft_Button_25": 60,
    "msft_Button_26": 211,
    "msft_Button_27": 518,
    "msft_Button_28": 522,
    "msft_Button_29": 520,
    "msft_Button_30": 584,
    "msft_Button_31": 557,
    "msft_Button_32": 569,
    "msft_Button_33": 103,
    "msft_Button_34": 646,
    "msft_Button_35": 49,
    "msft_Button_36": 50,
    "msft_Button_37": 647,
    "msft_Button_38": 360,
    "msft_Button_39": 658,
    "msft_Button_4": 441,
    "msft_Button_40": 659,
    "msft_Button_41": 456,
    "msft_Button_42": 457,
    "msft_Button_43": 429,
    "msft_Button_44": 157,
    "msft_Button_45": 158,
    "msft_Button_46": 120,
    "msft_Button_47": 121,
    "msft_Button_48": 247,
    "msft_Button_49": 248,
    "msft_Button_50": 260,
    "msft_Button_51": 261,
    "msft_Button_52": 283,
    "msft_Button_53": 284,
    "msft_Button_54": 138,
    "msft_Button_55": 139,
    "msft_Button_6": 475,
    "msft_Button_7": 476,
    "msft_Button_8": 680,
    "msft_Button_9": 681,
    "msft_ComboBox_5": 594,
    "msft_DatePicker_2": 222,
    "msft_DatePicker_3": 223,
    "msft_DatePicker_4": 547,
    "msft_DatePicker_5": 548,
    "msft_Dropdown": 422,
    "msft_Dropdown_10": 219,
    "msft_Dropdown_12": 225,
    "msft_Dropdown_16": 593,
    "msft_Dropdown_18": 226,
    "msft_Dropdown_19": 534,
    "msft_Dropdown_20": 535,
    "msft_Dropdown_21": 537,
    "msft_Dropdown_22": 549,
    "msft_Dropdown_23": 551,
    "msft_Dropdown_24": 552,
    "msft_Dropdown_25": 511,
    "msft_Dropdown_27": 554,
    "msft_Dropdown_28": 215,
    "msft_Dropdown_29": 220,
    "msft_Dropdown_30": 217,
    "msft_Dropdown_31": 232,
    "msft_Dropdown_32": 233,
    "msft_Dropdown_33": 510,
    "msft_Dropdown_9": 218,
    "msft_Label": 418,
    "msft_Label_1": 421,
    "msft_Label_10": 716,
    "msft_Label_11": 473,
    "msft_Label_12": 580,
    "msft_Label_13": 582,
    "msft_Label_14": 565,
    "msft_Label_15": 567,
    "msft_Label_16": 471,
    "msft_Label_17": 452,
    "msft_Label_18": 454,
    "msft_Label_2": 423,
    "msft_Label_34": 886,
    "msft_Label_35": 887,
    "msft_Label_36": 885,
    "msft_Label_37": 727,
    "msft_Label_38": 730,
    "msft_Label_39": 724,
    "msft_Label_40": 728,
    "msft_Label_41": 731,
    "msft_Label_42": 725,
    "msft_Label_43": 729,
    "msft_Label_44": 732,
    "msft_Label_45": 726,
    "msft_Label_5": 437,
    "msft_Label_6": 439,
    "msft_Label_7": 469,
    "msft_Label_8": 470,
    "msft_Label_9": 719,
    "msft_TextInput": 419,
    "msft_TextInput_1": 424,
    "msft_TextInput_10": 455,
    "msft_TextInput_11": 228,
    "msft_TextInput_12": 221,
    "msft_TextInput_13": 530,
    "msft_TextInput_14": 231,
    "msft_TextInput_15": 507,
    "msft_TextInput_16": 545,
    "msft_TextInput_17": 508,
    "msft_TextInput_19": 581,
    "msft_TextInput_20": 583,
    "msft_TextInput_21": 566,
    "msft_TextInput_22": 568,
    "msft_TextInput_4": 438,
    "msft_TextInput_5": 440,
    "msft_TextInput_6": 472,
    "msft_TextInput_7": 474,
    "msft_TextInput_8": 216,
    "msft_TextInput_9": 453,
    "msftBirthday_DOJ": 11,
    "msftcapability": 36,
    "msftcaregivers": 56,
    "msftconfirmationscreen": 83,
    "msftDashboard": 88,
    "msftdiscipline": 92,
    "msfteditcapability": 108,
    "msfteditdiscipline": 128,
    "msfteditgroup": 144,
    "msfteditproject": 164,
    "msfteditprojectgoal": 234,
    "msfteditprojecttype": 255,
    "msftedittechnology": 277,
    "msftgroup": 302,
    "msftMasterData": 322,
    "msftnewcategory": 411,
    "msftnewcategory2": 430,
    "msftnewdiscipline": 445,
    "msftnewgroup": 460,
    "msftnewproject": 481,
    "msftnewprojectgoal": 555,
    "msftnewprojecttype": 570,
    "msftproject": 585,
    "msftprojectgoal": 633,
    "msftprojecttype": 654,
    "msfttechnology": 675,
    "msftUpdatecaregivers": 701,
    "msftUpdateSkill_Caregiver": 879,
    "navBar_1": 589,
    "navBar_2": 57,
    "navBarHorizontal": 1,
    "navBarHorizontal_1": 713,
    "navBarHorizontal_10": 465,
    "navBarHorizontal_11": 308,
    "navBarHorizontal_12": 576,
    "navBarHorizontal_13": 639,
    "navBarHorizontal_14": 561,
    "navBarHorizontal_15": 42,
    "navBarHorizontal_16": 660,
    "navBarHorizontal_17": 448,
    "navBarHorizontal_18": 881,
    "navBarHorizontal_19": 16,
    "navBarHorizontal_2": 420,
    "navBarHorizontal_20": 150,
    "navBarHorizontal_21": 113,
    "navBarHorizontal_22": 240,
    "navBarHorizontal_23": 262,
    "navBarHorizontal_24": 285,
    "navBarHorizontal_25": 132,
    "navBarHorizontal_3": 433,
    "navBarHorizontal_4": 89,
    "navBarHorizontal_5": 339,
    "navBarHorizontal_6": 206,
    "navBarHorizontal_7": 514,
    "navBarHorizontal_8": 682,
    "navBarHorizontal_9": 96,
    "navBarVertical": 3,
    "navBarVertical_1": 708,
    "navBarVertical_10": 467,
    "navBarVertical_11": 309,
    "navBarVertical_12": 578,
    "navBarVertical_13": 640,
    "navBarVertical_14": 563,
    "navBarVertical_15": 43,
    "navBarVertical_16": 661,
    "navBarVertical_17": 450,
    "navBarVertical_18": 882,
    "navBarVertical_19": 17,
    "navBarVertical_2": 417,
    "navBarVertical_20": 151,
    "navBarVertical_21": 114,
    "navBarVertical_22": 241,
    "navBarVertical_23": 263,
    "navBarVertical_24": 286,
    "navBarVertical_25": 134,
    "navBarVertical_3": 435,
    "navBarVertical_4": 90,
    "navBarVertical_5": 340,
    "navBarVertical_6": 207,
    "navBarVertical_7": 516,
    "navBarVertical_8": 683,
    "navBarVertical_9": 98,
    "New Category": 436,
    "New Category_1": 468,
    "New Category_2": 579,
    "New Category_3": 564,
    "New Category_4": 451,
    "New Project_1": 214,
    "New Project_2": 528,
    "New Project_3": 147,
    "New Project_4": 122,
    "New Project_5": 237,
    "New Project_6": 258,
    "New Project_7": 280,
    "New Project_8": 141,
    "New Technology": 416,
    "NextArrow11": 387,
    "NextArrow13": 393,
    "NextArrow17": 401,
    "NextArrow19": 381,
    "NextArrow4": 371,
    "Owner Header": 603,
    "Owner Label": 612,
    "paginationBar": 8,
    "PowerBI1": 91,
    "Predictive scheduling": 624,
    "Projects_1": 592,
    "projectsactivelabel": 305,
    "React is a JavaScript library for building user interfaces. It is declarative, efficient, and flexible. React makes it easy to create interactive UIs by using a component-based approach.": 699,
    "React is a JavaScript library for building user interfaces. It is declarative, efficient, and flexible. React makes it easy to create interactive UIs by using a component-based approach._1": 105,
    "React is a JavaScript library for building user interfaces. It is declarative, efficient, and flexible. React makes it easy to create interactive UIs by using a component-based approach._2": 674,
    "React is a JavaScript library for building user interfaces. It is declarative, efficient, and flexible. React makes it easy to create interactive UIs by using a component-based approach._3": 276,
    "React is a JavaScript library for building user interfaces. It is declarative, efficient, and flexible. React makes it easy to create interactive UIs by using a component-based approach._4": 301,
    "React is a JavaScript library for building user interfaces. It is declarative, efficient, and flexible. React makes it easy to create interactive UIs by using a component-based approach._5": 140,
    "Rectangle 31": 414,
    "Rectangle 31_10": 560,
    "Rectangle 31_11": 447,
    "Rectangle 31_12": 264,
    "Rectangle 31_13": 287,
    "Rectangle 31_2": 432,
    "Rectangle 31_3": 524,
    "Rectangle 31_4": 212,
    "Rectangle 31_5": 684,
    "Rectangle 31_6": 464,
    "Rectangle 31_7": 662,
    "Rectangle 31_8": 575,
    "Rectangle 31_9": 588,
    "Rectangle 32": 415,
    "Rectangle 32_10": 562,
    "Rectangle 32_11": 449,
    "Rectangle 32_12": 265,
    "Rectangle 32_13": 288,
    "Rectangle 32_2": 434,
    "Rectangle 32_3": 526,
    "Rectangle 32_4": 213,
    "Rectangle 32_5": 685,
    "Rectangle 32_6": 466,
    "Rectangle 32_7": 663,
    "Rectangle 32_8": 577,
    "Rectangle 32_9": 591,
    "Rectangle1": 367,
    "Rectangle12": 385,
    "Rectangle14": 391,
    "Rectangle18": 399,
    "Rectangle2": 85,
    "Rectangle20": 379,
    "Rectangle3": 720,
    "Rectangle3_1": 227,
    "Rectangle3_2": 553,
    "Rectangle3_3": 884,
    "Rectangle5": 369,
    "Refreshed On Header": 601,
    "Refreshed On Header_1": 602,
    "Refreshed On Label": 610,
    "Refreshed On Label_1": 611,
    "Report Header": 687,
    "Report Header_1": 689,
    "Report Header_10": 153,
    "Report Header_11": 116,
    "Report Header_12": 243,
    "Report Header_13": 267,
    "Report Header_14": 268,
    "Report Header_15": 290,
    "Report Header_16": 292,
    "Report Header_17": 135,
    "Report Header_2": 99,
    "Report Header_3": 642,
    "Report Header_4": 311,
    "Report Header_5": 45,
    "Report Header_6": 597,
    "Report Header_7": 598,
    "Report Header_8": 665,
    "Report Header_9": 666,
    "Report Label": 694,
    "Report Label_1": 696,
    "Report Label_10": 159,
    "Report Label_11": 123,
    "Report Label_12": 249,
    "Report Label_13": 272,
    "Report Label_14": 273,
    "Report Label_15": 296,
    "Report Label_16": 298,
    "Report Label_17": 142,
    "Report Label_2": 106,
    "Report Label_3": 648,
    "Report Label_4": 317,
    "Report Label_5": 51,
    "Report Label_6": 606,
    "Report Label_7": 607,
    "Report Label_8": 670,
    "Report Label_9": 671,
    "rowCount": 72,
    "search": 61,
    "search_1": 586,
    "search_3": 347,
    "search_4": 341,
    "search_5": 342,
    "search_6": 343,
    "search_7": 344,
    "search_8": 345,
    "searchClass": 64,
    "searchDesignation": 62,
    "searchLevel": 63,
    "Separator1": 81,
    "Separator1_1": 28,
    "Separator1_2": 408,
    "Separator1_3": 35,
    "Separator12": 386,
    "Separator14": 392,
    "Separator18": 400,
    "Separator2": 366,
    "Separator20": 380,
    "Separator6": 370,
    "skillCategory_6": 888,
    "skillCategory_7": 733,
    "skillCategory_8": 734,
    "skillCategory_9": 735,
    "SkillLabel": 678,
    "SkillLabel_1": 657,
    "SkillLabel_2": 259,
    "SkillLabel_3": 281,
    "skillName": 889,
    "skillName_1": 736,
    "skillName_2": 737,
    "skillName_3": 738,
    "Streamlining the process of schdeduling and staffing that could potentially save $47M": 625,
    "Subtitle1": 77,
    "Subtitle1_1": 78,
    "Subtitle1_10": 31,
    "Subtitle1_11": 32,
    "Subtitle1_12": 33,
    "Subtitle1_13": 34,
    "Subtitle1_2": 79,
    "Subtitle1_3": 80,
    "Subtitle1_4": 24,
    "Subtitle1_5": 25,
    "Subtitle1_6": 26,
    "Subtitle1_7": 27,
    "Subtitle1_8": 406,
    "Subtitle1_9": 407,
    "Subtitle13": 388,
    "Subtitle22": 394,
    "Subtitle25": 402,
    "Subtitle27": 382,
    "Subtitle6": 372,
    "Subtitle7": 365,
    "Table Headers Container": 595,
    "Team_1": 224,
    "Team_2": 550,
    "TextInput1": 324,
    "TextInput1_1": 338,
    "TextInput2": 0,
    "TextInput2_1": 0,
    "TextInput2_2": 0,
    "TextInput2_3": 0,
    "TextInput2_4": 0,
    "TextInput2_5": 0,
    "Title1": 76,
    "Title1_1": 23,
    "Title1_2": 405,
    "Title1_3": 30,
    "Title14": 389,
    "Title2": 748,
    "Title2_1": 765,
    "Title2_10": 759,
    "Title2_100": 828,
    "Title2_101": 829,
    "Title2_102": 830,
    "Title2_103": 831,
    "Title2_104": 832,
    "Title2_105": 833,
    "Title2_106": 834,
    "Title2_107": 835,
    "Title2_108": 836,
    "Title2_109": 837,
    "Title2_11": 760,
    "Title2_110": 838,
    "Title2_111": 839,
    "Title2_112": 840,
    "Title2_113": 841,
    "Title2_114": 842,
    "Title2_115": 843,
    "Title2_116": 844,
    "Title2_117": 845,
    "Title2_118": 846,
    "Title2_119": 847,
    "Title2_12": 761,
    "Title2_13": 762,
    "Title2_14": 763,
    "Title2_15": 764,
    "Title2_16": 773,
    "Title2_17": 774,
    "Title2_18": 783,
    "Title2_19": 784,
    "Title2_2": 767,
    "Title2_20": 785,
    "Title2_21": 786,
    "Title2_22": 787,
    "Title2_23": 788,
    "Title2_24": 789,
    "Title2_25": 849,
    "Title2_26": 850,
    "Title2_27": 859,
    "Title2_28": 860,
    "Title2_29": 861,
    "Title2_3": 766,
    "Title2_30": 862,
    "Title2_31": 863,
    "Title2_32": 864,
    "Title2_33": 790,
    "Title2_34": 791,
    "Title2_35": 792,
    "Title2_36": 793,
    "Title2_37": 794,
    "Title2_38": 795,
    "Title2_39": 796,
    "Title2_4": 768,
    "Title2_40": 865,
    "Title2_41": 866,
    "Title2_42": 867,
    "Title2_43": 868,
    "Title2_44": 869,
    "Title2_45": 870,
    "Title2_46": 871,
    "Title2_47": 872,
    "Title2_48": 750,
    "Title2_49": 751,
    "Title2_5": 769,
    "Title2_50": 752,
    "Title2_51": 753,
    "Title2_52": 754,
    "Title2_53": 755,
    "Title2_54": 756,
    "Title2_55": 775,
    "Title2_56": 776,
    "Title2_57": 777,
    "Title2_58": 778,
    "Title2_59": 779,
    "Title2_6": 770,
    "Title2_60": 757,
    "Title2_61": 780,
    "Title2_62": 781,
    "Title2_63": 782,
    "Title2_64": 798,
    "Title2_65": 799,
    "Title2_66": 800,
    "Title2_67": 801,
    "Title2_68": 802,
    "Title2_69": 803,
    "Title2_7": 771,
    "Title2_70": 804,
    "Title2_71": 805,
    "Title2_72": 806,
    "Title2_73": 807,
    "Title2_74": 808,
    "Title2_75": 809,
    "Title2_76": 810,
    "Title2_77": 811,
    "Title2_78": 812,
    "Title2_79": 813,
    "Title2_8": 749,
    "Title2_80": 814,
    "Title2_81": 815,
    "Title2_82": 816,
    "Title2_83": 817,
    "Title2_84": 818,
    "Title2_85": 819,
    "Title2_86": 820,
    "Title2_87": 821,
    "Title2_88": 851,
    "Title2_89": 852,
    "Title2_9": 758,
    "Title2_90": 853,
    "Title2_91": 854,
    "Title2_92": 855,
    "Title2_93": 856,
    "Title2_94": 857,
    "Title2_95": 858,
    "Title2_96": 824,
    "Title2_97": 825,
    "Title2_98": 826,
    "Title2_99": 827,
    "Title23": 395,
    "Title27": 403,
    "Title29": 383,
    "Title7": 364,
    "Title9": 373,
    "Toggle1": 183,
    "Toggle1_1": 502,
    "txtCaregiverID": 712,
    "Update Caregivers": 714,
    "Update Caregivers_1": 361,
    "Update Caregivers_2": 883
  },
  "ResourcesJsonIndices": {
    "Image-caregivers": 1,
    "Image-dashboard": 2,
    "Image-leftArrow": 3,
    "Image-logo": 4,
    "Image-master_data": 5,
    "Image-Projects_2": 6,
    "Image-rightArrow": 7,
    "Image-SampleImage": 0
  },
  "RuleScreenIdWithoutScreen": {},
  "TemplateVersions": {},
  "VolatileProperties": {
    "AnalysisLoadTime": 2.8985101,
    "ControlCount": {
      "button": 87,
      "combobox": 3,
      "d8d0600eb50240e7988dae5ff84131d3": 28,
      "datepicker": 6,
      "dropdown": 32,
      "e4379836dfc64dbda2b19049e588929b": 1,
      "f8bd1ef8470046c38c37a4a87233147e": 28,
      "gallery": 24,
      "galleryTemplate": 24,
      "group": 5,
      "groupContainer": 75,
      "icon": 45,
      "image": 7,
      "label": 412,
      "powerbi": 1,
      "rectangle": 47,
      "screen": 28,
      "text": 39,
      "toggleSwitch": 2
    },
    "DeserializationLoadTime": 3.2408779
  },
  "WasLocalDatabaseReferencesEmpty": true
}