{
  "ComponentIndexes": {
    "navBarHorizontal": 44,
    "navBarVertical_admin": 45,
    "navBarVertical_cg": 46,
    "paginationBar": 47
  },
  "ControlUniqueGuids": {},
  "ControlUniqueIds": {
    "Action Header": 800,
    "Action Header_2": 712,
    "Action Header_3": 210,
    "Action Header_4": 678,
    "Action Header_5": 510,
    "Action Header_6": 763,
    "Action Header_7": 23,
    "Action Label": 801,
    "Action Label_2": 713,
    "Action Label_3": 211,
    "Action Label_4": 679,
    "Action Label_5": 511,
    "Action Label_6": 764,
    "Action Label_7": 24,
    "App": 1,
    "attachCard_1": 995,
    "Body3": 288,
    "Button1": 254,
    "Button2": 834,
    "Button2_1": 242,
    "Button2_2": 837,
    "Button3": 246,
    "Button3_1": 250,
    "Button4": 990,
    "Button5": 216,
    "Button5_1": 215,
    "Button5_10": 31,
    "Button5_11": 32,
    "Button5_12": 697,
    "Button5_13": 809,
    "Button5_2": 516,
    "Button5_3": 515,
    "Button5_4": 718,
    "Button5_5": 719,
    "Button5_6": 772,
    "Button5_7": 771,
    "Button5_8": 808,
    "Button5_9": 807,
    "Button7": 997,
    "Button7_3": 398,
    "Button7_4": 411,
    "Button7_6": 533,
    "Button8": 859,
    "Button8_1": 857,
    "Button8_2": 858,
    "Button9": 1066,
    "Button9_1": 1067,
    "Button9_2": 603,
    "Button9_3": 604,
    "Button9_4": 605,
    "Capability": 22,
    "Capability_1": 53,
    "capabilitydpdwn": 268,
    "Caregivers": 1013,
    "Category": 791,
    "Category Header": 794,
    "Category Header_1": 190,
    "Category Header_10": 69,
    "Category Header_11": 70,
    "Category Header_12": 681,
    "Category Header_13": 42,
    "Category Header_14": 43,
    "Category Header_15": 136,
    "Category Header_16": 137,
    "Category Header_2": 707,
    "Category Header_3": 205,
    "Category Header_4": 206,
    "Category Header_5": 666,
    "Category Header_6": 208,
    "Category Header_7": 708,
    "Category Header_8": 505,
    "Category Header_9": 506,
    "Category Label": 795,
    "Category Label_1": 191,
    "Category Label_10": 71,
    "Category Label_11": 682,
    "Category Label_14": 44,
    "Category Label_16": 138,
    "Category Label_17": 57,
    "Category Label_2": 710,
    "Category Label_3": 207,
    "Category Label_4": 709,
    "Category Label_5": 667,
    "Category Label_6": 209,
    "Category Label_7": 508,
    "Category Label_8": 507,
    "Category Label_9": 28,
    "Category_1": 704,
    "Category_10": 222,
    "Category_11": 736,
    "Category_12": 725,
    "Category_13": 780,
    "Category_14": 1059,
    "Category_15": 1060,
    "Category_16": 1044,
    "Category_17": 1043,
    "Category_18": 747,
    "Category_19": 746,
    "Category_2": 202,
    "Category_20": 592,
    "Category_21": 593,
    "Category_23": 622,
    "Category_24": 623,
    "Category_25": 624,
    "Category_26": 635,
    "Category_27": 636,
    "Category_28": 637,
    "Category_29": 610,
    "Category_3": 502,
    "Category_30": 612,
    "Category_31": 611,
    "Category_32": 1002,
    "Category_4": 760,
    "Category_5": 65,
    "Category_6": 38,
    "Category_7": 133,
    "Category_8": 149,
    "Category_9": 187,
    "CategoryLabel": 805,
    "Checkbox1": 1019,
    "Column - Header 13": 802,
    "Column - Header 4_2": 715,
    "ComboBox1": 495,
    "ComboBox1_1": 125,
    "ComboBox2": 169,
    "ComboBox2_1": 429,
    "ComboBox3": 645,
    "ComboBox3_1": 646,
    "ComboBox3_2": 647,
    "ComboBox5": 171,
    "ComboBox5_1": 431,
    "comment": 989,
    "comment_1": 868,
    "comment_2": 864,
    "comment_3": 865,
    "Data Analytics_1": 716,
    "Data Analytics_3": 513,
    "DatePicker1": 420,
    "DatePicker1_1": 423,
    "Description Header": 798,
    "Description Header_1": 668,
    "Description Header_2": 767,
    "Description Label": 799,
    "Description Label_1": 669,
    "Description Label_2": 768,
    "descriptionlabel": 212,
    "descriptionlabel_1": 72,
    "descriptionlabel_2": 224,
    "Dropdown1_1": 195,
    "Dropdown1_2": 58,
    "Favourite Header": 676,
    "Favourite Label": 677,
    "Gallery1": 1024,
    "Gallery1_2": 291,
    "Gallery1_4": 297,
    "Gallery10": 228,
    "Gallery11": 225,
    "Gallery12": 782,
    "Gallery13": 1034,
    "Gallery14": 739,
    "Gallery15": 726,
    "Gallery16": 685,
    "Gallery17": 317,
    "Gallery18": 1047,
    "Gallery18_1": 628,
    "Gallery18_2": 640,
    "Gallery18_3": 615,
    "Gallery19": 750,
    "Gallery2_1": 576,
    "Gallery20": 1005,
    "Gallery21": 167,
    "Gallery28": 331,
    "Gallery29": 252,
    "Gallery3": 826,
    "Gallery3_1": 842,
    "Gallery31": 310,
    "Gallery33": 303,
    "Gallery4": 324,
    "Gallery5": 869,
    "Gallery5_1": 870,
    "Gallery5_2": 947,
    "Gallery5_3": 921,
    "Gallery6": 244,
    "Gallery6_1": 248,
    "Gallery7": 832,
    "Gallery7_1": 240,
    "Gallery7_2": 835,
    "Gallery8": 283,
    "Gallery9": 810,
    "Gallery9_1": 812,
    "Gallery9_2": 814,
    "galleryTemplate1": 1025,
    "galleryTemplate1_2": 292,
    "galleryTemplate1_4": 298,
    "galleryTemplate10": 811,
    "galleryTemplate10_1": 813,
    "galleryTemplate10_2": 815,
    "galleryTemplate11": 229,
    "galleryTemplate12": 226,
    "galleryTemplate13": 783,
    "galleryTemplate14": 1035,
    "galleryTemplate15": 740,
    "galleryTemplate16": 727,
    "galleryTemplate17": 690,
    "galleryTemplate18": 318,
    "galleryTemplate19": 1048,
    "galleryTemplate19_1": 629,
    "galleryTemplate19_2": 641,
    "galleryTemplate19_3": 616,
    "galleryTemplate2": 1033,
    "galleryTemplate20": 751,
    "galleryTemplate21": 1006,
    "galleryTemplate22": 168,
    "galleryTemplate29": 332,
    "galleryTemplate3_1": 577,
    "galleryTemplate30": 253,
    "galleryTemplate32": 311,
    "galleryTemplate34": 304,
    "galleryTemplate4": 827,
    "galleryTemplate4_1": 843,
    "galleryTemplate5": 325,
    "galleryTemplate6": 896,
    "galleryTemplate6_1": 871,
    "galleryTemplate6_3": 922,
    "galleryTemplate6_4": 948,
    "galleryTemplate7": 245,
    "galleryTemplate7_1": 249,
    "galleryTemplate8": 833,
    "galleryTemplate8_1": 241,
    "galleryTemplate8_2": 836,
    "galleryTemplate9": 284,
    "Group1": 976,
    "Group2_3": 401,
    "Group2_4": 426,
    "Group2_6": 536,
    "Group3": 977,
    "Group3_1": 974,
    "Group3_2": 975,
    "Group7_4": 991,
    "grouplabel": 213,
    "hiddenGallery": 1032,
    "Host": 3,
    "Icon1_19": 483,
    "Icon1_2": 454,
    "Icon1_20": 484,
    "Icon1_21": 485,
    "Icon1_24": 88,
    "Icon1_26": 97,
    "Icon1_27": 565,
    "Icon1_28": 106,
    "Icon1_29": 105,
    "Icon1_3": 467,
    "Icon1_30": 121,
    "Icon1_31": 120,
    "Icon1_32": 566,
    "Icon1_33": 441,
    "Icon1_34": 113,
    "Icon1_35": 114,
    "Icon1_36": 115,
    "Icon1_37": 442,
    "Icon1_40": 348,
    "Icon1_41": 349,
    "Icon1_42": 365,
    "Icon1_43": 392,
    "Icon1_44": 415,
    "Icon1_45": 546,
    "Icon1_46": 528,
    "Icon1_47": 377,
    "Icon1_48": 378,
    "Icon1_5": 475,
    "Icon1_51": 567,
    "Icon1_52": 443,
    "Icon1_6": 476,
    "Icon1_7": 493,
    "Icon1_8": 494,
    "Image1": 5,
    "Image3": 1038,
    "Image4": 1037,
    "Image5_10": 10,
    "Image5_11": 7,
    "Image5_6": 12,
    "Image5_7": 13,
    "Image5_8": 9,
    "Image5_9": 8,
    "Image8": 235,
    "Image8_1": 233,
    "Image8_2": 237,
    "Image8_3": 239,
    "Image8_4": 243,
    "Image8_5": 247,
    "Image8_6": 251,
    "Image8_7": 255,
    "Label1": 1036,
    "Label10": 275,
    "Label10_1": 276,
    "Label10_2": 277,
    "Label10_3": 279,
    "Label11": 717,
    "Label11_1": 30,
    "Label11_2": 770,
    "Label12": 698,
    "Label13": 755,
    "Label13_3": 582,
    "Label13_4": 583,
    "Label13_5": 584,
    "Label14": 173,
    "Label14_1": 573,
    "Label15": 711,
    "Label15_1": 509,
    "Label15_2": 27,
    "Label16": 714,
    "Label16_1": 512,
    "Label16_2": 45,
    "Label16_4": 738,
    "Label16_5": 730,
    "Label16_6": 1004,
    "Label17": 175,
    "Label17_1": 585,
    "Label18": 627,
    "Label19_3": 578,
    "Label19_4": 579,
    "Label19_5": 580,
    "Label2": 1020,
    "Label2_1": 1021,
    "Label2_10": 278,
    "Label2_12": 273,
    "Label2_13": 272,
    "Label2_14": 282,
    "Label2_15": 281,
    "Label2_2": 1022,
    "Label2_3": 1023,
    "Label2_8": 280,
    "Label2_9": 274,
    "Label20": 689,
    "Label20_1": 699,
    "Label21": 221,
    "Label21_1": 735,
    "Label21_2": 724,
    "Label21_3": 779,
    "Label21_4": 1001,
    "Label22": 784,
    "Label23": 514,
    "Label24": 686,
    "Label24_1": 687,
    "Label24_3": 691,
    "Label24_4": 695,
    "Label24_5": 693,
    "Label24_6": 688,
    "Label24_7": 696,
    "Label24_8": 692,
    "Label24_9": 694,
    "Label25": 1053,
    "Label26": 227,
    "Label27": 223,
    "Label27_1": 737,
    "Label27_2": 728,
    "Label27_3": 781,
    "Label27_4": 1003,
    "Label28": 1026,
    "Label28_1": 1027,
    "Label29": 741,
    "Label3": 33,
    "Label3_1": 84,
    "Label3_11": 94,
    "Label3_12": 111,
    "Label3_13": 87,
    "Label3_16": 489,
    "Label3_17": 471,
    "Label3_18": 473,
    "Label3_19": 465,
    "Label3_2": 85,
    "Label3_20": 453,
    "Label3_21": 119,
    "Label3_22": 96,
    "Label3_23": 466,
    "Label3_24": 562,
    "Label3_25": 86,
    "Label3_26": 487,
    "Label3_27": 110,
    "Label3_28": 112,
    "Label3_29": 482,
    "Label3_30": 479,
    "Label3_31": 477,
    "Label3_32": 564,
    "Label3_33": 438,
    "Label3_34": 440,
    "Label3_35": 174,
    "Label3_36": 172,
    "Label3_37": 563,
    "Label3_38": 439,
    "Label3_4": 457,
    "Label3_5": 458,
    "Label3_7": 117,
    "Label3_8": 103,
    "Label3_9": 104,
    "Label30": 729,
    "Label31": 700,
    "Label32": 806,
    "Label32_3": 397,
    "Label32_4": 409,
    "Label32_6": 532,
    "Label33": 1018,
    "Label34": 1065,
    "Label34_1": 1064,
    "Label34_2": 601,
    "Label34_3": 602,
    "Label34_5": 600,
    "Label35": 1007,
    "Label36": 653,
    "Label36_1": 654,
    "Label36_2": 655,
    "Label37": 1049,
    "Label37_1": 630,
    "Label37_2": 642,
    "Label38": 752,
    "Label4": 822,
    "Label5": 617,
    "Label6": 95,
    "Label6_12": 490,
    "Label6_13": 463,
    "Label6_14": 93,
    "Label6_15": 456,
    "Label6_16": 455,
    "Label6_17": 472,
    "Label6_18": 474,
    "Label6_19": 486,
    "Label6_20": 344,
    "Label6_21": 345,
    "Label6_23": 362,
    "Label6_25": 412,
    "Label6_26": 418,
    "Label6_27": 421,
    "Label6_29": 543,
    "Label6_3": 102,
    "Label6_31": 525,
    "Label6_33": 464,
    "Label6_34": 116,
    "Label6_35": 390,
    "Label6_37": 109,
    "Label6_38": 478,
    "Label6_39": 374,
    "Label6_4": 101,
    "Label6_40": 560,
    "Label6_41": 561,
    "Label6_42": 559,
    "Label6_43": 435,
    "Label6_44": 436,
    "Label6_45": 437,
    "Label6_5": 118,
    "Label7": 841,
    "Label7_1": 838,
    "Label7_2": 839,
    "Label8": 828,
    "Label8_1": 829,
    "Label8_2": 830,
    "Label8_3": 844,
    "Label8_4": 845,
    "Label8_5": 846,
    "Label8_6": 847,
    "Label9": 232,
    "Label9_1": 572,
    "msft_Button": 354,
    "msft_Button_11": 263,
    "msft_Button_12": 270,
    "msft_Button_13": 656,
    "msft_Button_14": 217,
    "msft_Button_15": 230,
    "msft_Button_16": 1054,
    "msft_Button_17": 1055,
    "msft_Button_18": 258,
    "msft_Button_19": 368,
    "msft_Button_20": 127,
    "msft_Button_21": 128,
    "msft_Button_22": 269,
    "msft_Button_23": 549,
    "msft_Button_24": 271,
    "msft_Button_25": 1015,
    "msft_Button_27": 497,
    "msft_Button_28": 498,
    "msft_Button_30": 550,
    "msft_Button_31": 534,
    "msft_Button_32": 535,
    "msft_Button_33": 34,
    "msft_Button_34": 720,
    "msft_Button_35": 517,
    "msft_Button_36": 773,
    "msft_Button_37": 816,
    "msft_Button_38": 257,
    "msft_Button_39": 742,
    "msft_Button_4": 369,
    "msft_Button_40": 731,
    "msft_Button_41": 399,
    "msft_Button_42": 400,
    "msft_Button_43": 355,
    "msft_Button_44": 785,
    "msft_Button_45": 76,
    "msft_Button_46": 256,
    "msft_Button_47": 49,
    "msft_Button_48": 1014,
    "msft_Button_49": 141,
    "msft_Button_5": 382,
    "msft_Button_50": 996,
    "msft_Button_51": 156,
    "msft_Button_52": 198,
    "msft_Button_53": 197,
    "msft_Button_54": 60,
    "msft_Button_55": 61,
    "msft_Button_56": 157,
    "msft_Button_58": 973,
    "msft_Button_6": 424,
    "msft_Button_60": 1008,
    "msft_Button_61": 142,
    "msft_Button_62": 48,
    "msft_Button_63": 75,
    "msft_Button_64": 381,
    "msft_Button_65": 1068,
    "msft_Button_66": 1050,
    "msft_Button_67": 753,
    "msft_Button_7": 425,
    "msft_Button_70": 606,
    "msft_Button_71": 631,
    "msft_Button_72": 643,
    "msft_Button_73": 618,
    "msft_Button_76": 179,
    "msft_Button_77": 588,
    "msft_Button_78": 571,
    "msft_Button_79": 575,
    "msft_Button_80": 574,
    "msft_Button_81": 581,
    "msft_Button_82": 586,
    "msft_Button_83": 176,
    "msft_Button_84": 177,
    "msft_Button_85": 180,
    "msft_Button_86": 446,
    "msft_DatePicker_2": 89,
    "msft_DatePicker_3": 90,
    "msft_DatePicker_4": 461,
    "msft_DatePicker_5": 462,
    "msft_Dropdown": 351,
    "msft_Dropdown_10": 108,
    "msft_Dropdown_19": 468,
    "msft_Dropdown_20": 480,
    "msft_Dropdown_21": 481,
    "msft_Dropdown_24": 469,
    "msft_Dropdown_27": 460,
    "msft_Dropdown_28": 99,
    "msft_Dropdown_29": 126,
    "msft_Dropdown_30": 100,
    "msft_Dropdown_31": 568,
    "msft_Dropdown_32": 92,
    "msft_Dropdown_33": 496,
    "msft_Dropdown_35": 569,
    "msft_Dropdown_36": 444,
    "msft_Dropdown_39": 178,
    "msft_Dropdown_40": 570,
    "msft_Dropdown_41": 445,
    "msft_Dropdown_9": 107,
    "msft_Label": 346,
    "msft_Label_1": 347,
    "msft_Label_10": 824,
    "msft_Label_11": 414,
    "msft_Label_12": 544,
    "msft_Label_13": 545,
    "msft_Label_14": 526,
    "msft_Label_15": 527,
    "msft_Label_16": 422,
    "msft_Label_17": 391,
    "msft_Label_18": 393,
    "msft_Label_19": 825,
    "msft_Label_2": 352,
    "msft_Label_3": 375,
    "msft_Label_34": 985,
    "msft_Label_35": 986,
    "msft_Label_36": 984,
    "msft_Label_37": 853,
    "msft_Label_38": 856,
    "msft_Label_39": 852,
    "msft_Label_4": 376,
    "msft_Label_40": 850,
    "msft_Label_41": 854,
    "msft_Label_42": 848,
    "msft_Label_43": 851,
    "msft_Label_44": 855,
    "msft_Label_45": 849,
    "msft_Label_5": 363,
    "msft_Label_6": 364,
    "msft_Label_7": 413,
    "msft_Label_8": 419,
    "msft_Label_9": 823,
    "msft_TextInput": 350,
    "msft_TextInput_1": 353,
    "msft_TextInput_10": 395,
    "msft_TextInput_11": 123,
    "msft_TextInput_12": 98,
    "msft_TextInput_13": 459,
    "msft_TextInput_14": 122,
    "msft_TextInput_15": 491,
    "msft_TextInput_16": 470,
    "msft_TextInput_17": 488,
    "msft_TextInput_19": 547,
    "msft_TextInput_2": 379,
    "msft_TextInput_20": 548,
    "msft_TextInput_21": 529,
    "msft_TextInput_22": 530,
    "msft_TextInput_3": 380,
    "msft_TextInput_4": 366,
    "msft_TextInput_5": 367,
    "msft_TextInput_6": 416,
    "msft_TextInput_7": 417,
    "msft_TextInput_8": 91,
    "msft_TextInput_9": 394,
    "msftcapability": 499,
    "msftcapabilitylists": 732,
    "msftcaregiverdiscipline": 998,
    "msftcaregivers": 1009,
    "msftcaregiverscount": 1040,
    "msftconfirmationscreen": 1051,
    "msftcostcenter": 1056,
    "msftDashboard": 15,
    "msftdiscipline": 19,
    "msfteditcapability": 35,
    "msfteditdiscipline": 50,
    "msfteditgroup": 62,
    "msfteditproject": 77,
    "msfteditprojectgoal": 129,
    "msfteditprojecttype": 143,
    "msfteditteam": 158,
    "msftedittechnology": 181,
    "msftgroup": 199,
    "msftgrouplists": 218,
    "msftMasterData": 231,
    "msftnewcategory": 338,
    "msftnewcategory2": 356,
    "msftnewcertification": 370,
    "msftnewdiscipline": 383,
    "msftnewgroup": 402,
    "msftnewMember": 427,
    "msftnewproject": 447,
    "msftnewprojectgoal": 518,
    "msftnewprojecttype": 537,
    "msftnewteam": 551,
    "msftpeopleskills": 589,
    "msftpeoplewithskillsadvanced": 607,
    "msftpeoplewithskillsbeginner": 619,
    "msftpeoplewithskillsintermediate": 632,
    "msftproject": 644,
    "msftprojectgoal": 701,
    "msftprojectgoallists": 721,
    "msftprojectscount": 743,
    "msftprojecttype": 754,
    "msftprojecttypelists": 774,
    "msfttechnology": 786,
    "msftUpdatecaregivers": 817,
    "msftUpdateSkill_Caregiver": 978,
    "msftUploadData": 992,
    "navBarHorizontal": 4,
    "navBarHorizontal_1": 820,
    "navBarHorizontal_10": 405,
    "navBarHorizontal_11": 201,
    "navBarHorizontal_12": 540,
    "navBarHorizontal_13": 703,
    "navBarHorizontal_14": 521,
    "navBarHorizontal_15": 501,
    "navBarHorizontal_16": 758,
    "navBarHorizontal_17": 386,
    "navBarHorizontal_18": 981,
    "navBarHorizontal_19": 52,
    "navBarHorizontal_2": 341,
    "navBarHorizontal_20": 64,
    "navBarHorizontal_21": 37,
    "navBarHorizontal_22": 131,
    "navBarHorizontal_23": 146,
    "navBarHorizontal_24": 184,
    "navBarHorizontal_25": 777,
    "navBarHorizontal_26": 220,
    "navBarHorizontal_27": 734,
    "navBarHorizontal_28": 723,
    "navBarHorizontal_29": 1012,
    "navBarHorizontal_3": 359,
    "navBarHorizontal_30": 650,
    "navBarHorizontal_31": 372,
    "navBarHorizontal_32": 994,
    "navBarHorizontal_33": 1058,
    "navBarHorizontal_34": 1042,
    "navBarHorizontal_35": 745,
    "navBarHorizontal_36": 591,
    "navBarHorizontal_37": 621,
    "navBarHorizontal_38": 634,
    "navBarHorizontal_39": 609,
    "navBarHorizontal_4": 17,
    "navBarHorizontal_40": 1000,
    "navBarHorizontal_41": 161,
    "navBarHorizontal_42": 554,
    "navBarHorizontal_43": 432,
    "navBarHorizontal_5": 236,
    "navBarHorizontal_6": 80,
    "navBarHorizontal_7": 450,
    "navBarHorizontal_8": 789,
    "navBarHorizontal_9": 21,
    "navBarVertical_admin": 6,
    "navBarVertical_admin_1": 16,
    "navBarVertical_admin_10": 20,
    "navBarVertical_admin_11": 51,
    "navBarVertical_admin_12": 788,
    "navBarVertical_admin_13": 183,
    "navBarVertical_admin_14": 757,
    "navBarVertical_admin_15": 776,
    "navBarVertical_admin_16": 145,
    "navBarVertical_admin_17": 702,
    "navBarVertical_admin_18": 722,
    "navBarVertical_admin_19": 130,
    "navBarVertical_admin_2": 340,
    "navBarVertical_admin_20": 500,
    "navBarVertical_admin_21": 733,
    "navBarVertical_admin_22": 36,
    "navBarVertical_admin_23": 200,
    "navBarVertical_admin_24": 219,
    "navBarVertical_admin_25": 63,
    "navBarVertical_admin_26": 818,
    "navBarVertical_admin_27": 1010,
    "navBarVertical_admin_28": 649,
    "navBarVertical_admin_29": 234,
    "navBarVertical_admin_3": 358,
    "navBarVertical_admin_30": 979,
    "navBarVertical_admin_31": 371,
    "navBarVertical_admin_32": 993,
    "navBarVertical_admin_33": 1057,
    "navBarVertical_admin_34": 1041,
    "navBarVertical_admin_35": 744,
    "navBarVertical_admin_36": 590,
    "navBarVertical_admin_37": 620,
    "navBarVertical_admin_38": 633,
    "navBarVertical_admin_39": 608,
    "navBarVertical_admin_4": 385,
    "navBarVertical_admin_40": 999,
    "navBarVertical_admin_41": 160,
    "navBarVertical_admin_42": 553,
    "navBarVertical_admin_43": 430,
    "navBarVertical_admin_5": 404,
    "navBarVertical_admin_6": 539,
    "navBarVertical_admin_7": 520,
    "navBarVertical_admin_8": 449,
    "navBarVertical_admin_9": 79,
    "navBarVertical_cg": 11,
    "navBarVertical_cg_1": 1011,
    "navBarVertical_cg_2": 980,
    "navBarVertical_cg_3": 819,
    "New Category": 361,
    "New Category_1": 410,
    "New Category_2": 542,
    "New Category_3": 524,
    "New Category_4": 389,
    "New Project_1": 82,
    "New Project_10": 163,
    "New Project_11": 164,
    "New Project_12": 556,
    "New Project_13": 557,
    "New Project_14": 434,
    "New Project_2": 452,
    "New Project_3": 66,
    "New Project_4": 39,
    "New Project_5": 132,
    "New Project_6": 148,
    "New Project_7": 186,
    "New Project_8": 54,
    "New Project_9": 83,
    "New Technology": 343,
    "New Technology_1": 373,
    "NextArrow11": 320,
    "NextArrow13": 334,
    "NextArrow17": 313,
    "NextArrow19": 306,
    "NextArrow4": 327,
    "NextArrow5": 286,
    "Owner Header": 674,
    "Owner Label": 675,
    "Owner Label_1": 680,
    "paginationBar": 14,
    "PowerBI2": 18,
    "Projects_1": 652,
    "projectsactivelabel": 214,
    "React is a JavaScript library for building user interfaces. It is declarative, efficient, and flexible. React makes it easy to create interactive UIs by using a component-based approach.": 803,
    "React is a JavaScript library for building user interfaces. It is declarative, efficient, and flexible. React makes it easy to create interactive UIs by using a component-based approach._1": 29,
    "Rectangle 31": 339,
    "Rectangle 31_10": 519,
    "Rectangle 31_11": 384,
    "Rectangle 31_12": 144,
    "Rectangle 31_13": 182,
    "Rectangle 31_14": 775,
    "Rectangle 31_15": 159,
    "Rectangle 31_16": 552,
    "Rectangle 31_17": 428,
    "Rectangle 31_2": 357,
    "Rectangle 31_3": 448,
    "Rectangle 31_4": 78,
    "Rectangle 31_5": 787,
    "Rectangle 31_6": 403,
    "Rectangle 31_7": 756,
    "Rectangle 31_8": 538,
    "Rectangle 31_9": 648,
    "Rectangle 32": 342,
    "Rectangle 32_10": 523,
    "Rectangle 32_11": 388,
    "Rectangle 32_12": 147,
    "Rectangle 32_13": 185,
    "Rectangle 32_14": 778,
    "Rectangle 32_15": 162,
    "Rectangle 32_16": 555,
    "Rectangle 32_17": 433,
    "Rectangle 32_2": 360,
    "Rectangle 32_3": 451,
    "Rectangle 32_4": 81,
    "Rectangle 32_5": 790,
    "Rectangle 32_6": 407,
    "Rectangle 32_7": 759,
    "Rectangle 32_8": 541,
    "Rectangle 32_9": 651,
    "Rectangle1": 170,
    "Rectangle12": 319,
    "Rectangle14": 333,
    "Rectangle18": 312,
    "Rectangle2": 1052,
    "Rectangle20": 305,
    "Rectangle3": 840,
    "Rectangle3_3": 983,
    "Rectangle3_4": 165,
    "Rectangle3_6": 587,
    "Rectangle4_3": 396,
    "Rectangle4_4": 408,
    "Rectangle4_6": 531,
    "Rectangle5": 326,
    "Rectangle6_2": 387,
    "Rectangle6_3": 406,
    "Rectangle6_5": 522,
    "Rectangle7": 285,
    "Refreshed On Header": 670,
    "Refreshed On Header_1": 672,
    "Refreshed On Header_2": 683,
    "Refreshed On Label": 671,
    "Refreshed On Label_1": 673,
    "Refreshed On Label_2": 684,
    "Report Header": 792,
    "Report Header_1": 796,
    "Report Header_10": 67,
    "Report Header_11": 40,
    "Report Header_12": 134,
    "Report Header_13": 150,
    "Report Header_14": 152,
    "Report Header_15": 188,
    "Report Header_16": 192,
    "Report Header_17": 55,
    "Report Header_18": 660,
    "Report Header_2": 25,
    "Report Header_20": 664,
    "Report Header_21": 1061,
    "Report Header_22": 1045,
    "Report Header_23": 748,
    "Report Header_24": 594,
    "Report Header_25": 596,
    "Report Header_26": 598,
    "Report Header_27": 625,
    "Report Header_28": 638,
    "Report Header_29": 613,
    "Report Header_3": 705,
    "Report Header_4": 203,
    "Report Header_5": 503,
    "Report Header_6": 659,
    "Report Header_7": 662,
    "Report Header_8": 761,
    "Report Header_9": 765,
    "Report Label": 793,
    "Report Label_1": 797,
    "Report Label_10": 68,
    "Report Label_11": 41,
    "Report Label_12": 135,
    "Report Label_13": 151,
    "Report Label_14": 153,
    "Report Label_15": 189,
    "Report Label_16": 193,
    "Report Label_17": 56,
    "Report Label_18": 661,
    "Report Label_2": 26,
    "Report Label_20": 665,
    "Report Label_21": 1063,
    "Report Label_22": 1046,
    "Report Label_23": 749,
    "Report Label_24": 595,
    "Report Label_25": 597,
    "Report Label_26": 599,
    "Report Label_27": 626,
    "Report Label_28": 639,
    "Report Label_29": 614,
    "Report Label_3": 706,
    "Report Label_4": 204,
    "Report Label_5": 504,
    "Report Label_6": 1062,
    "Report Label_7": 663,
    "Report Label_8": 762,
    "Report Label_9": 766,
    "rowCount": 1039,
    "search": 1016,
    "searchLevel": 1017,
    "Separator1": 1031,
    "Separator1_2": 296,
    "Separator1_4": 302,
    "Separator12": 323,
    "Separator14": 337,
    "Separator18": 316,
    "Separator20": 309,
    "Separator5": 290,
    "Separator6": 330,
    "skillCategory_6": 987,
    "skillCategory_7": 866,
    "skillCategory_8": 860,
    "skillCategory_9": 861,
    "SkillLabel": 804,
    "SkillLabel_1": 769,
    "skillName": 988,
    "skillName_1": 867,
    "skillName_2": 862,
    "skillName_3": 863,
    "Subtitle1": 1029,
    "Subtitle1_14": 300,
    "Subtitle1_15": 301,
    "Subtitle1_2": 1028,
    "Subtitle1_3": 1030,
    "Subtitle1_8": 294,
    "Subtitle1_9": 295,
    "Subtitle13": 322,
    "Subtitle22": 336,
    "Subtitle25": 315,
    "Subtitle27": 308,
    "Subtitle5": 289,
    "Subtitle6": 329,
    "Table Headers Container": 658,
    "Team_3": 166,
    "Team_5": 558,
    "TextInput1": 259,
    "TextInput1_1": 267,
    "TextInput1_2": 261,
    "TextInput1_3": 264,
    "TextInput1_4": 265,
    "TextInput1_5": 260,
    "TextInput1_6": 266,
    "TextInput1_7": 262,
    "TextInput1_8": 657,
    "TextInput2": 73,
    "TextInput2_1": 74,
    "TextInput2_10": 59,
    "TextInput2_2": 46,
    "TextInput2_3": 47,
    "TextInput2_4": 139,
    "TextInput2_5": 140,
    "TextInput2_6": 154,
    "TextInput2_7": 155,
    "TextInput2_8": 196,
    "TextInput2_9": 194,
    "Title1_2": 293,
    "Title1_4": 299,
    "Title14": 321,
    "Title2": 898,
    "Title2_1": 902,
    "Title2_10": 903,
    "Title2_100": 957,
    "Title2_101": 960,
    "Title2_102": 963,
    "Title2_103": 966,
    "Title2_104": 969,
    "Title2_105": 972,
    "Title2_106": 953,
    "Title2_107": 955,
    "Title2_108": 959,
    "Title2_109": 971,
    "Title2_11": 907,
    "Title2_110": 965,
    "Title2_111": 968,
    "Title2_112": 962,
    "Title2_113": 954,
    "Title2_114": 958,
    "Title2_115": 956,
    "Title2_116": 961,
    "Title2_117": 967,
    "Title2_118": 964,
    "Title2_119": 970,
    "Title2_12": 919,
    "Title2_13": 913,
    "Title2_14": 916,
    "Title2_15": 910,
    "Title2_16": 873,
    "Title2_17": 874,
    "Title2_18": 876,
    "Title2_19": 878,
    "Title2_2": 904,
    "Title2_20": 882,
    "Title2_21": 894,
    "Title2_22": 888,
    "Title2_23": 891,
    "Title2_24": 885,
    "Title2_3": 906,
    "Title2_33": 877,
    "Title2_34": 881,
    "Title2_35": 879,
    "Title2_36": 884,
    "Title2_37": 890,
    "Title2_38": 887,
    "Title2_39": 893,
    "Title2_4": 909,
    "Title2_48": 897,
    "Title2_49": 900,
    "Title2_5": 915,
    "Title2_50": 905,
    "Title2_51": 908,
    "Title2_52": 911,
    "Title2_53": 914,
    "Title2_54": 917,
    "Title2_55": 872,
    "Title2_56": 875,
    "Title2_57": 880,
    "Title2_58": 883,
    "Title2_59": 886,
    "Title2_6": 912,
    "Title2_60": 920,
    "Title2_61": 889,
    "Title2_62": 892,
    "Title2_63": 895,
    "Title2_64": 924,
    "Title2_65": 925,
    "Title2_66": 923,
    "Title2_67": 926,
    "Title2_68": 931,
    "Title2_69": 934,
    "Title2_7": 918,
    "Title2_70": 937,
    "Title2_71": 940,
    "Title2_72": 943,
    "Title2_73": 946,
    "Title2_74": 927,
    "Title2_75": 929,
    "Title2_76": 933,
    "Title2_77": 945,
    "Title2_78": 939,
    "Title2_79": 942,
    "Title2_8": 899,
    "Title2_80": 936,
    "Title2_81": 928,
    "Title2_82": 932,
    "Title2_83": 930,
    "Title2_84": 935,
    "Title2_85": 941,
    "Title2_86": 938,
    "Title2_87": 944,
    "Title2_9": 901,
    "Title2_96": 950,
    "Title2_97": 951,
    "Title2_98": 949,
    "Title2_99": 952,
    "Title23": 335,
    "Title27": 314,
    "Title29": 307,
    "Title5": 287,
    "Title9": 328,
    "Toggle1": 124,
    "Toggle1_1": 492,
    "txtCaregiverID": 831,
    "Update Caregivers": 821,
    "Update Caregivers_1": 238,
    "Update Caregivers_2": 982
  },
  "FunctionParamsInvariantScripts": {},
  "FunctionParamsInvariantScriptsOnInstances": {},
  "HeaderLastSavedDateTimeUTC": "02/06/2024 09:30:48",
  "IsLegacyComponentAllowGlobalScopeCase": false,
  "LocalConnectionIDReferences": {
    "32590a84-3559-4086-97c2-95457209ae4b": "\"/providers/microsoft.powerapps/apis/shared_powerbi/connections/1e03acde460a487ab761ada9f101b869\"",
    "489129e9-0231-4cb4-a2d5-07eb9d9b3bcd": "\"/providers/microsoft.powerapps/apis/shared_logicflows/connections/e3d5d06878054d8ea37454b3f642f52e-95333b98cc7b06c3\"",
    "ac5e3fa2-316b-4d7d-9cd1-ba57171d3f8a": "\"/providers/microsoft.powerapps/apis/shared_sharepointonline/connections/9633fd352ce246268519c44be9cf01d5\"",
    "ea650aae-b066-489b-bded-4f7f8c599893": "\"/providers/microsoft.powerapps/apis/shared_excelonlinebusiness/connections/cf43774a0e264e61a4d47daf991346e0\""
  },
  "LocalDatabaseReferencesAsEmpty": false,
  "LocalResourceFileNames": {
    "caregivers": "0001.png",
    "dashboard": "0002.png",
    "leftArrow": "0003.png",
    "logo": "0004.png",
    "master_data": "0005.png",
    "MicrosoftTeams-image (10)": "0006.png",
    "Projects_2": "0007.png",
    "Prov Infinite Loader": "0008.gif",
    "Prov Loader 1": "0009.svg",
    "rightArrow": "0010.png"
  },
  "LocalResourceRootPaths": {
    "caregivers": "https://docserverpwaprodeus.blob.core.windows.net/cf0eba13-e4ad-4b2d-b16e-fbe537a4fd64-1/resource/Assets0Images00001.png?skoid=58690ece-ec83-4ce2-9ce8-883d4d6a54ee&sktid=975f013f-7f24-47e8-a7d3-abc4752bf346&skt=2024-02-06T08%3A59%3A31Z&ske=2024-02-07T09%3A14%3A31Z&sks=b&skv=2022-11-02&sv=2022-11-02&spr=https&se=2024-02-07T09%3A14%3A31Z&sr=b&sp=r&sig=cd2ETpkgHP3RIEwgXYHnesSE61iDpidWPgNDi2zAEwE%3D",
    "dashboard": "https://docserverpwaprodeus.blob.core.windows.net/cf0eba13-e4ad-4b2d-b16e-fbe537a4fd64-1/resource/Assets0Images00002.png?skoid=58690ece-ec83-4ce2-9ce8-883d4d6a54ee&sktid=975f013f-7f24-47e8-a7d3-abc4752bf346&skt=2024-02-06T08%3A59%3A31Z&ske=2024-02-07T09%3A14%3A31Z&sks=b&skv=2022-11-02&sv=2022-11-02&spr=https&se=2024-02-07T09%3A14%3A31Z&sr=b&sp=r&sig=UazK5Sw1hl4y4wc9fmgKXv7kChcNIxSCselPgBCnDG0%3D",
    "leftArrow": "https://docserverpwaprodeus.blob.core.windows.net/cf0eba13-e4ad-4b2d-b16e-fbe537a4fd64-1/resource/Assets0Images00003.png?skoid=58690ece-ec83-4ce2-9ce8-883d4d6a54ee&sktid=975f013f-7f24-47e8-a7d3-abc4752bf346&skt=2024-02-06T08%3A59%3A31Z&ske=2024-02-07T09%3A14%3A31Z&sks=b&skv=2022-11-02&sv=2022-11-02&spr=https&se=2024-02-07T09%3A14%3A31Z&sr=b&sp=r&sig=KwY9%2BT79fsm9VbvHykR7Mo37VwICHTz5GFlSMmG3m0w%3D",
    "logo": "https://docserverpwaprodeus.blob.core.windows.net/cf0eba13-e4ad-4b2d-b16e-fbe537a4fd64-1/resource/Assets0Images00004.png?skoid=58690ece-ec83-4ce2-9ce8-883d4d6a54ee&sktid=975f013f-7f24-47e8-a7d3-abc4752bf346&skt=2024-02-06T08%3A59%3A31Z&ske=2024-02-07T09%3A14%3A31Z&sks=b&skv=2022-11-02&sv=2022-11-02&spr=https&se=2024-02-07T09%3A14%3A31Z&sr=b&sp=r&sig=uEixXBq%2Fi11q3k%2FDkGlLk%2Fojxn1uQ2iT%2B%2FXG1JyXfbE%3D",
    "master_data": "https://docserverpwaprodeus.blob.core.windows.net/cf0eba13-e4ad-4b2d-b16e-fbe537a4fd64-1/resource/Assets0Images00005.png?skoid=58690ece-ec83-4ce2-9ce8-883d4d6a54ee&sktid=975f013f-7f24-47e8-a7d3-abc4752bf346&skt=2024-02-06T08%3A59%3A31Z&ske=2024-02-07T09%3A14%3A31Z&sks=b&skv=2022-11-02&sv=2022-11-02&spr=https&se=2024-02-07T09%3A14%3A31Z&sr=b&sp=r&sig=Cr9je%2FM3E6cvT7mDfiRDw5ktz0sxzjUT1wt%2F4VpNFKI%3D",
    "MicrosoftTeams-image (10)": "https://docserverpwaprodeus.blob.core.windows.net/cf0eba13-e4ad-4b2d-b16e-fbe537a4fd64-1/resource/Assets0Images00006.png?skoid=58690ece-ec83-4ce2-9ce8-883d4d6a54ee&sktid=975f013f-7f24-47e8-a7d3-abc4752bf346&skt=2024-02-06T08%3A59%3A31Z&ske=2024-02-07T09%3A14%3A31Z&sks=b&skv=2022-11-02&sv=2022-11-02&spr=https&se=2024-02-07T09%3A14%3A31Z&sr=b&sp=r&sig=ueHtecOPqk9NjG%2F0WwMP5rIIL7zfipYqOn69liS7%2B6A%3D",
    "Projects_2": "https://docserverpwaprodeus.blob.core.windows.net/cf0eba13-e4ad-4b2d-b16e-fbe537a4fd64-1/resource/Assets0Images00007.png?skoid=58690ece-ec83-4ce2-9ce8-883d4d6a54ee&sktid=975f013f-7f24-47e8-a7d3-abc4752bf346&skt=2024-02-06T08%3A59%3A31Z&ske=2024-02-07T09%3A14%3A31Z&sks=b&skv=2022-11-02&sv=2022-11-02&spr=https&se=2024-02-07T09%3A14%3A31Z&sr=b&sp=r&sig=DYCMNPgUKFU6ee2y8cDiDnDNDUWidPRJph17Gir9jj8%3D",
    "Prov Infinite Loader": "https://docserverpwaprodeus.blob.core.windows.net/cf0eba13-e4ad-4b2d-b16e-fbe537a4fd64-1/resource/Assets0Images00008.gif?skoid=58690ece-ec83-4ce2-9ce8-883d4d6a54ee&sktid=975f013f-7f24-47e8-a7d3-abc4752bf346&skt=2024-02-06T08%3A59%3A31Z&ske=2024-02-07T09%3A14%3A31Z&sks=b&skv=2022-11-02&sv=2022-11-02&spr=https&se=2024-02-07T09%3A14%3A31Z&sr=b&sp=r&sig=5R7rpXr352PVs%2BMSMi7S3t8MtEMqO6zwJqRI6bdNF7I%3D",
    "Prov Loader 1": "https://docserverpwaprodeus.blob.core.windows.net/cf0eba13-e4ad-4b2d-b16e-fbe537a4fd64-1/resource/Assets0Images00009.svg?skoid=58690ece-ec83-4ce2-9ce8-883d4d6a54ee&sktid=975f013f-7f24-47e8-a7d3-abc4752bf346&skt=2024-02-06T08%3A59%3A31Z&ske=2024-02-07T09%3A14%3A31Z&sks=b&skv=2022-11-02&sv=2022-11-02&spr=https&se=2024-02-07T09%3A14%3A31Z&sr=b&sp=r&sig=33g9JPmcZFzH8YcXuzpfpWGGIUIF2J5dQxSFHAp1hRk%3D",
    "rightArrow": "https://docserverpwaprodeus.blob.core.windows.net/cf0eba13-e4ad-4b2d-b16e-fbe537a4fd64-1/resource/Assets0Images00010.png?skoid=58690ece-ec83-4ce2-9ce8-883d4d6a54ee&sktid=975f013f-7f24-47e8-a7d3-abc4752bf346&skt=2024-02-06T08%3A59%3A31Z&ske=2024-02-07T09%3A14%3A31Z&sks=b&skv=2022-11-02&sv=2022-11-02&spr=https&se=2024-02-07T09%3A14%3A31Z&sr=b&sp=r&sig=0YslExKbmCx4lJRuf9VpdU9SeOBlbQSC%2BNonM455yrQ%3D"
  },
  "OldLogoFileName": "logo.jpg",
  "OrderComponentMetadata": {
    "0aacb1eb065c442095080747033d8c13": 2,
    "8ae730d7ee9341c68951ab00b8cc853a": 1,
    "e4379836dfc64dbda2b19049e588929b": 3,
    "f8bd1ef8470046c38c37a4a87233147e": 0
  },
  "OrderComponentTemplate": {
    "0aacb1eb065c442095080747033d8c13": 2,
    "8ae730d7ee9341c68951ab00b8cc853a": 1,
    "e4379836dfc64dbda2b19049e588929b": 3,
    "f8bd1ef8470046c38c37a4a87233147e": 0
  },
  "OrderDataSource": {
    "Advanced": 2,
    "Beginner": 3,
    "Capabilities": 4,
    "Capabilities_1": 5,
    "Caregiver Skills": 6,
    "CaregiverData": 21,
    "Caregivers_1": 7,
    "Certifications": 8,
    "CG": 22,
    "combinedData": 23,
    "ComboBoxSample": 9,
    "Cost Center": 10,
    "CustomGallerySample": 11,
    "Discipline": 12,
    "DropDownSample": 13,
    "FilteredAdvancedSkills": 24,
    "FilteredBeginnerSkills": 25,
    "FilteredCaregivers": 26,
    "FilteredCostCenters_Caregiver": 27,
    "FilteredCostCenters_Project": 28,
    "FilteredDiscipline": 29,
    "FilteredIntermediateSkills": 30,
    "FilteredProjects": 31,
    "FilteredProjectsCapability": 32,
    "FilteredProjectsCollection": 33,
    "FilteredProjectsGroup": 34,
    "FilteredProjectsType": 35,
    "Intermediate": 14,
    "PowerBI": 0,
    "Project": 18,
    "Project Goals": 15,
    "Project Parent Group": 16,
    "Project Type": 17,
    "SelectedCapabilities": 36,
    "Skills": 19,
    "Skills_1": 20,
    "uploadFile": 1
  },
  "OrderGroupControls": {
    "Group1": {},
    "Group2_3": {
      "Button7_3": 2,
      "Label32_3": 1,
      "Rectangle4_3": 0
    },
    "Group2_4": {
      "Button7_4": 2,
      "Label32_4": 1,
      "Rectangle4_4": 0
    },
    "Group2_6": {
      "Button7_6": 2,
      "Label32_6": 1,
      "Rectangle4_6": 0
    },
    "Group3": {
      "Button8": 6,
      "comment_1": 4,
      "Label7": 7,
      "msft_Label_37": 2,
      "msft_Label_38": 3,
      "msft_Label_39": 5,
      "skillCategory_7": 1,
      "skillName_1": 0
    },
    "Group3_1": {
      "Button8_1": 6,
      "comment_2": 4,
      "Label7_1": 7,
      "msft_Label_40": 2,
      "msft_Label_41": 3,
      "msft_Label_42": 5,
      "skillCategory_8": 1,
      "skillName_2": 0
    },
    "Group3_2": {
      "Button8_2": 6,
      "comment_3": 4,
      "Label7_2": 7,
      "msft_Label_43": 2,
      "msft_Label_44": 3,
      "msft_Label_45": 5,
      "skillCategory_9": 1,
      "skillName_3": 0
    },
    "Group7_4": {
      "comment": 4,
      "msft_Label_34": 2,
      "msft_Label_35": 3,
      "msft_Label_36": 5,
      "skillCategory_6": 1,
      "skillName": 0
    }
  },
  "OrderPcfTemplate": {},
  "OrderTemplate": {},
  "OrderXMLTemplate": {
    "attachments": 13,
    "button": 4,
    "checkbox": 14,
    "combobox": 11,
    "datepicker": 9,
    "dropdown": 6,
    "gallery": 12,
    "groupContainer": 3,
    "icon": 8,
    "image": 0,
    "label": 2,
    "powerbi": 1,
    "rectangle": 7,
    "text": 5,
    "toggleSwitch": 10
  },
  "OverridablePropertiesEntry": {
    "Action Header": {},
    "Action Header_2": {},
    "Action Header_3": {},
    "Action Header_4": {},
    "Action Header_5": {},
    "Action Header_6": {},
    "Action Header_7": {},
    "Action Label": {},
    "Action Label_2": {},
    "Action Label_3": {},
    "Action Label_4": {},
    "Action Label_5": {},
    "Action Label_6": {},
    "Action Label_7": {},
    "App": {},
    "attachCard_1": {},
    "Body3": {},
    "Button1": {},
    "Button2": {},
    "Button2_1": {},
    "Button2_2": {},
    "Button3": {},
    "Button3_1": {},
    "Button4": {},
    "Button5": {},
    "Button5_1": {},
    "Button5_10": {},
    "Button5_11": {},
    "Button5_12": {},
    "Button5_13": {},
    "Button5_2": {},
    "Button5_3": {},
    "Button5_4": {},
    "Button5_5": {},
    "Button5_6": {},
    "Button5_7": {},
    "Button5_8": {},
    "Button5_9": {},
    "Button7": {},
    "Button7_3": {},
    "Button7_4": {},
    "Button7_6": {},
    "Button8": {},
    "Button8_1": {},
    "Button8_2": {},
    "Button9": {},
    "Button9_1": {},
    "Button9_2": {},
    "Button9_3": {},
    "Button9_4": {},
    "Capability": {},
    "Capability_1": {},
    "capabilitydpdwn": {},
    "Caregivers": {},
    "Category": {},
    "Category Header": {},
    "Category Header_1": {},
    "Category Header_10": {},
    "Category Header_11": {},
    "Category Header_12": {},
    "Category Header_13": {},
    "Category Header_14": {},
    "Category Header_15": {},
    "Category Header_16": {},
    "Category Header_2": {},
    "Category Header_3": {},
    "Category Header_4": {},
    "Category Header_5": {},
    "Category Header_6": {},
    "Category Header_7": {},
    "Category Header_8": {},
    "Category Header_9": {},
    "Category Label": {},
    "Category Label_1": {},
    "Category Label_10": {},
    "Category Label_11": {},
    "Category Label_14": {},
    "Category Label_16": {},
    "Category Label_17": {},
    "Category Label_2": {},
    "Category Label_3": {},
    "Category Label_4": {},
    "Category Label_5": {},
    "Category Label_6": {},
    "Category Label_7": {},
    "Category Label_8": {},
    "Category Label_9": {},
    "Category_1": {},
    "Category_10": {},
    "Category_11": {},
    "Category_12": {},
    "Category_13": {},
    "Category_14": {},
    "Category_15": {},
    "Category_16": {},
    "Category_17": {},
    "Category_18": {},
    "Category_19": {},
    "Category_2": {},
    "Category_20": {},
    "Category_21": {},
    "Category_23": {},
    "Category_24": {},
    "Category_25": {},
    "Category_26": {},
    "Category_27": {},
    "Category_28": {},
    "Category_29": {},
    "Category_3": {},
    "Category_30": {},
    "Category_31": {},
    "Category_32": {},
    "Category_4": {},
    "Category_5": {},
    "Category_6": {},
    "Category_7": {},
    "Category_8": {},
    "Category_9": {},
    "CategoryLabel": {},
    "Checkbox1": {},
    "Column - Header 13": {},
    "Column - Header 4_2": {},
    "ComboBox1": {},
    "ComboBox1_1": {},
    "ComboBox2": {},
    "ComboBox2_1": {},
    "ComboBox3": {},
    "ComboBox3_1": {},
    "ComboBox3_2": {},
    "ComboBox5": {},
    "ComboBox5_1": {},
    "comment": {},
    "comment_1": {},
    "comment_2": {},
    "comment_3": {},
    "Data Analytics_1": {},
    "Data Analytics_3": {},
    "DatePicker1": {},
    "DatePicker1_1": {},
    "Description Header": {},
    "Description Header_1": {},
    "Description Header_2": {},
    "Description Label": {},
    "Description Label_1": {},
    "Description Label_2": {},
    "descriptionlabel": {},
    "descriptionlabel_1": {},
    "descriptionlabel_2": {},
    "Dropdown1_1": {},
    "Dropdown1_2": {},
    "Favourite Header": {},
    "Favourite Label": {},
    "Gallery1": {},
    "Gallery1_2": {},
    "Gallery1_4": {},
    "Gallery10": {},
    "Gallery11": {},
    "Gallery12": {},
    "Gallery13": {},
    "Gallery14": {},
    "Gallery15": {},
    "Gallery16": {},
    "Gallery17": {},
    "Gallery18": {},
    "Gallery18_1": {},
    "Gallery18_2": {},
    "Gallery18_3": {},
    "Gallery19": {},
    "Gallery2_1": {},
    "Gallery20": {},
    "Gallery21": {},
    "Gallery28": {},
    "Gallery29": {},
    "Gallery3": {},
    "Gallery3_1": {},
    "Gallery31": {},
    "Gallery33": {},
    "Gallery4": {},
    "Gallery5": {},
    "Gallery5_1": {},
    "Gallery5_2": {},
    "Gallery5_3": {},
    "Gallery6": {},
    "Gallery6_1": {},
    "Gallery7": {},
    "Gallery7_1": {},
    "Gallery7_2": {},
    "Gallery8": {},
    "Gallery9": {},
    "Gallery9_1": {},
    "Gallery9_2": {},
    "galleryTemplate1": {},
    "galleryTemplate1_2": {},
    "galleryTemplate1_4": {},
    "galleryTemplate10": {},
    "galleryTemplate10_1": {},
    "galleryTemplate10_2": {},
    "galleryTemplate11": {},
    "galleryTemplate12": {},
    "galleryTemplate13": {},
    "galleryTemplate14": {},
    "galleryTemplate15": {},
    "galleryTemplate16": {},
    "galleryTemplate17": {},
    "galleryTemplate18": {},
    "galleryTemplate19": {},
    "galleryTemplate19_1": {},
    "galleryTemplate19_2": {},
    "galleryTemplate19_3": {},
    "galleryTemplate2": {},
    "galleryTemplate20": {},
    "galleryTemplate21": {},
    "galleryTemplate22": {},
    "galleryTemplate29": {},
    "galleryTemplate3_1": {},
    "galleryTemplate30": {},
    "galleryTemplate32": {},
    "galleryTemplate34": {},
    "galleryTemplate4": {},
    "galleryTemplate4_1": {},
    "galleryTemplate5": {},
    "galleryTemplate6": {},
    "galleryTemplate6_1": {},
    "galleryTemplate6_3": {},
    "galleryTemplate6_4": {},
    "galleryTemplate7": {},
    "galleryTemplate7_1": {},
    "galleryTemplate8": {},
    "galleryTemplate8_1": {},
    "galleryTemplate8_2": {},
    "galleryTemplate9": {},
    "Group1": {},
    "Group2_3": {},
    "Group2_4": {},
    "Group2_6": {},
    "Group3": {},
    "Group3_1": {},
    "Group3_2": {},
    "Group7_4": {},
    "grouplabel": {},
    "hiddenGallery": {},
    "Host": {},
    "Icon1_19": {},
    "Icon1_2": {},
    "Icon1_20": {},
    "Icon1_21": {},
    "Icon1_24": {},
    "Icon1_26": {},
    "Icon1_27": {},
    "Icon1_28": {},
    "Icon1_29": {},
    "Icon1_3": {},
    "Icon1_30": {},
    "Icon1_31": {},
    "Icon1_32": {},
    "Icon1_33": {},
    "Icon1_34": {},
    "Icon1_35": {},
    "Icon1_36": {},
    "Icon1_37": {},
    "Icon1_40": {},
    "Icon1_41": {},
    "Icon1_42": {},
    "Icon1_43": {},
    "Icon1_44": {},
    "Icon1_45": {},
    "Icon1_46": {},
    "Icon1_47": {},
    "Icon1_48": {},
    "Icon1_5": {},
    "Icon1_51": {},
    "Icon1_52": {},
    "Icon1_6": {},
    "Icon1_7": {},
    "Icon1_8": {},
    "Image1": {},
    "Image3": {},
    "Image4": {},
    "Image5_10": {},
    "Image5_11": {},
    "Image5_6": {},
    "Image5_7": {},
    "Image5_8": {},
    "Image5_9": {},
    "Image8": {},
    "Image8_1": {},
    "Image8_2": {},
    "Image8_3": {},
    "Image8_4": {},
    "Image8_5": {},
    "Image8_6": {},
    "Image8_7": {},
    "Label1": {},
    "Label10": {},
    "Label10_1": {},
    "Label10_2": {},
    "Label10_3": {},
    "Label11": {},
    "Label11_1": {},
    "Label11_2": {},
    "Label12": {},
    "Label13": {},
    "Label13_3": {},
    "Label13_4": {},
    "Label13_5": {},
    "Label14": {},
    "Label14_1": {},
    "Label15": {},
    "Label15_1": {},
    "Label15_2": {},
    "Label16": {},
    "Label16_1": {},
    "Label16_2": {},
    "Label16_4": {},
    "Label16_5": {},
    "Label16_6": {},
    "Label17": {},
    "Label17_1": {},
    "Label18": {},
    "Label19_3": {},
    "Label19_4": {},
    "Label19_5": {},
    "Label2": {},
    "Label2_1": {},
    "Label2_10": {},
    "Label2_12": {},
    "Label2_13": {},
    "Label2_14": {},
    "Label2_15": {},
    "Label2_2": {},
    "Label2_3": {},
    "Label2_8": {},
    "Label2_9": {},
    "Label20": {},
    "Label20_1": {},
    "Label21": {},
    "Label21_1": {},
    "Label21_2": {},
    "Label21_3": {},
    "Label21_4": {},
    "Label22": {},
    "Label23": {},
    "Label24": {},
    "Label24_1": {},
    "Label24_3": {},
    "Label24_4": {},
    "Label24_5": {},
    "Label24_6": {},
    "Label24_7": {},
    "Label24_8": {},
    "Label24_9": {},
    "Label25": {},
    "Label26": {},
    "Label27": {},
    "Label27_1": {},
    "Label27_2": {},
    "Label27_3": {},
    "Label27_4": {},
    "Label28": {},
    "Label28_1": {},
    "Label29": {},
    "Label3": {},
    "Label3_1": {},
    "Label3_11": {},
    "Label3_12": {},
    "Label3_13": {},
    "Label3_16": {},
    "Label3_17": {},
    "Label3_18": {},
    "Label3_19": {},
    "Label3_2": {},
    "Label3_20": {},
    "Label3_21": {},
    "Label3_22": {},
    "Label3_23": {},
    "Label3_24": {},
    "Label3_25": {},
    "Label3_26": {},
    "Label3_27": {},
    "Label3_28": {},
    "Label3_29": {},
    "Label3_30": {},
    "Label3_31": {},
    "Label3_32": {},
    "Label3_33": {},
    "Label3_34": {},
    "Label3_35": {},
    "Label3_36": {},
    "Label3_37": {},
    "Label3_38": {},
    "Label3_4": {},
    "Label3_5": {},
    "Label3_7": {},
    "Label3_8": {},
    "Label3_9": {},
    "Label30": {},
    "Label31": {},
    "Label32": {},
    "Label32_3": {},
    "Label32_4": {},
    "Label32_6": {},
    "Label33": {},
    "Label34": {},
    "Label34_1": {},
    "Label34_2": {},
    "Label34_3": {},
    "Label34_5": {},
    "Label35": {},
    "Label36": {},
    "Label36_1": {},
    "Label36_2": {},
    "Label37": {},
    "Label37_1": {},
    "Label37_2": {},
    "Label38": {},
    "Label4": {},
    "Label5": {},
    "Label6": {},
    "Label6_12": {},
    "Label6_13": {},
    "Label6_14": {},
    "Label6_15": {},
    "Label6_16": {},
    "Label6_17": {},
    "Label6_18": {},
    "Label6_19": {},
    "Label6_20": {},
    "Label6_21": {},
    "Label6_23": {},
    "Label6_25": {},
    "Label6_26": {},
    "Label6_27": {},
    "Label6_29": {},
    "Label6_3": {},
    "Label6_31": {},
    "Label6_33": {},
    "Label6_34": {},
    "Label6_35": {},
    "Label6_37": {},
    "Label6_38": {},
    "Label6_39": {},
    "Label6_4": {},
    "Label6_40": {},
    "Label6_41": {},
    "Label6_42": {},
    "Label6_43": {},
    "Label6_44": {},
    "Label6_45": {},
    "Label6_5": {},
    "Label7": {},
    "Label7_1": {},
    "Label7_2": {},
    "Label8": {},
    "Label8_1": {},
    "Label8_2": {},
    "Label8_3": {},
    "Label8_4": {},
    "Label8_5": {},
    "Label8_6": {},
    "Label9": {},
    "Label9_1": {},
    "msft_Button": {},
    "msft_Button_11": {},
    "msft_Button_12": {},
    "msft_Button_13": {},
    "msft_Button_14": {},
    "msft_Button_15": {},
    "msft_Button_16": {},
    "msft_Button_17": {},
    "msft_Button_18": {},
    "msft_Button_19": {},
    "msft_Button_20": {},
    "msft_Button_21": {},
    "msft_Button_22": {},
    "msft_Button_23": {},
    "msft_Button_24": {},
    "msft_Button_25": {},
    "msft_Button_27": {},
    "msft_Button_28": {},
    "msft_Button_30": {},
    "msft_Button_31": {},
    "msft_Button_32": {},
    "msft_Button_33": {},
    "msft_Button_34": {},
    "msft_Button_35": {},
    "msft_Button_36": {},
    "msft_Button_37": {},
    "msft_Button_38": {},
    "msft_Button_39": {},
    "msft_Button_4": {},
    "msft_Button_40": {},
    "msft_Button_41": {},
    "msft_Button_42": {},
    "msft_Button_43": {},
    "msft_Button_44": {},
    "msft_Button_45": {},
    "msft_Button_46": {},
    "msft_Button_47": {},
    "msft_Button_48": {},
    "msft_Button_49": {},
    "msft_Button_5": {},
    "msft_Button_50": {},
    "msft_Button_51": {},
    "msft_Button_52": {},
    "msft_Button_53": {},
    "msft_Button_54": {},
    "msft_Button_55": {},
    "msft_Button_56": {},
    "msft_Button_58": {},
    "msft_Button_6": {},
    "msft_Button_60": {},
    "msft_Button_61": {},
    "msft_Button_62": {},
    "msft_Button_63": {},
    "msft_Button_64": {},
    "msft_Button_65": {},
    "msft_Button_66": {},
    "msft_Button_67": {},
    "msft_Button_7": {},
    "msft_Button_70": {},
    "msft_Button_71": {},
    "msft_Button_72": {},
    "msft_Button_73": {},
    "msft_Button_76": {},
    "msft_Button_77": {},
    "msft_Button_78": {},
    "msft_Button_79": {},
    "msft_Button_80": {},
    "msft_Button_81": {},
    "msft_Button_82": {},
    "msft_Button_83": {},
    "msft_Button_84": {},
    "msft_Button_85": {},
    "msft_Button_86": {},
    "msft_DatePicker_2": {},
    "msft_DatePicker_3": {},
    "msft_DatePicker_4": {},
    "msft_DatePicker_5": {},
    "msft_Dropdown": {},
    "msft_Dropdown_10": {},
    "msft_Dropdown_19": {},
    "msft_Dropdown_20": {},
    "msft_Dropdown_21": {},
    "msft_Dropdown_24": {},
    "msft_Dropdown_27": {},
    "msft_Dropdown_28": {},
    "msft_Dropdown_29": {},
    "msft_Dropdown_30": {},
    "msft_Dropdown_31": {},
    "msft_Dropdown_32": {},
    "msft_Dropdown_33": {},
    "msft_Dropdown_35": {},
    "msft_Dropdown_36": {},
    "msft_Dropdown_39": {},
    "msft_Dropdown_40": {},
    "msft_Dropdown_41": {},
    "msft_Dropdown_9": {},
    "msft_Label": {},
    "msft_Label_1": {},
    "msft_Label_10": {},
    "msft_Label_11": {},
    "msft_Label_12": {},
    "msft_Label_13": {},
    "msft_Label_14": {},
    "msft_Label_15": {},
    "msft_Label_16": {},
    "msft_Label_17": {},
    "msft_Label_18": {},
    "msft_Label_19": {},
    "msft_Label_2": {},
    "msft_Label_3": {},
    "msft_Label_34": {},
    "msft_Label_35": {},
    "msft_Label_36": {},
    "msft_Label_37": {},
    "msft_Label_38": {},
    "msft_Label_39": {},
    "msft_Label_4": {},
    "msft_Label_40": {},
    "msft_Label_41": {},
    "msft_Label_42": {},
    "msft_Label_43": {},
    "msft_Label_44": {},
    "msft_Label_45": {},
    "msft_Label_5": {},
    "msft_Label_6": {},
    "msft_Label_7": {},
    "msft_Label_8": {},
    "msft_Label_9": {},
    "msft_TextInput": {},
    "msft_TextInput_1": {},
    "msft_TextInput_10": {},
    "msft_TextInput_11": {},
    "msft_TextInput_12": {},
    "msft_TextInput_13": {},
    "msft_TextInput_14": {},
    "msft_TextInput_15": {},
    "msft_TextInput_16": {},
    "msft_TextInput_17": {},
    "msft_TextInput_19": {},
    "msft_TextInput_2": {},
    "msft_TextInput_20": {},
    "msft_TextInput_21": {},
    "msft_TextInput_22": {},
    "msft_TextInput_3": {},
    "msft_TextInput_4": {},
    "msft_TextInput_5": {},
    "msft_TextInput_6": {},
    "msft_TextInput_7": {},
    "msft_TextInput_8": {},
    "msft_TextInput_9": {},
    "msftcapability": {},
    "msftcapabilitylists": {},
    "msftcaregiverdiscipline": {},
    "msftcaregivers": {},
    "msftcaregiverscount": {},
    "msftconfirmationscreen": {},
    "msftcostcenter": {},
    "msftDashboard": {},
    "msftdiscipline": {},
    "msfteditcapability": {},
    "msfteditdiscipline": {},
    "msfteditgroup": {},
    "msfteditproject": {},
    "msfteditprojectgoal": {},
    "msfteditprojecttype": {},
    "msfteditteam": {},
    "msftedittechnology": {},
    "msftgroup": {},
    "msftgrouplists": {},
    "msftMasterData": {},
    "msftnewcategory": {},
    "msftnewcategory2": {},
    "msftnewcertification": {},
    "msftnewdiscipline": {},
    "msftnewgroup": {},
    "msftnewMember": {},
    "msftnewproject": {},
    "msftnewprojectgoal": {},
    "msftnewprojecttype": {},
    "msftnewteam": {},
    "msftpeopleskills": {},
    "msftpeoplewithskillsadvanced": {},
    "msftpeoplewithskillsbeginner": {},
    "msftpeoplewithskillsintermediate": {},
    "msftproject": {},
    "msftprojectgoal": {},
    "msftprojectgoallists": {},
    "msftprojectscount": {},
    "msftprojecttype": {},
    "msftprojecttypelists": {},
    "msfttechnology": {},
    "msftUpdatecaregivers": {},
    "msftUpdateSkill_Caregiver": {},
    "msftUploadData": {},
    "navBarHorizontal": {},
    "navBarHorizontal_1": {},
    "navBarHorizontal_10": {},
    "navBarHorizontal_11": {},
    "navBarHorizontal_12": {},
    "navBarHorizontal_13": {},
    "navBarHorizontal_14": {},
    "navBarHorizontal_15": {},
    "navBarHorizontal_16": {},
    "navBarHorizontal_17": {},
    "navBarHorizontal_18": {},
    "navBarHorizontal_19": {},
    "navBarHorizontal_2": {},
    "navBarHorizontal_20": {},
    "navBarHorizontal_21": {},
    "navBarHorizontal_22": {},
    "navBarHorizontal_23": {},
    "navBarHorizontal_24": {},
    "navBarHorizontal_25": {},
    "navBarHorizontal_26": {},
    "navBarHorizontal_27": {},
    "navBarHorizontal_28": {},
    "navBarHorizontal_29": {},
    "navBarHorizontal_3": {},
    "navBarHorizontal_30": {},
    "navBarHorizontal_31": {},
    "navBarHorizontal_32": {},
    "navBarHorizontal_33": {},
    "navBarHorizontal_34": {},
    "navBarHorizontal_35": {},
    "navBarHorizontal_36": {},
    "navBarHorizontal_37": {},
    "navBarHorizontal_38": {},
    "navBarHorizontal_39": {},
    "navBarHorizontal_4": {},
    "navBarHorizontal_40": {},
    "navBarHorizontal_41": {},
    "navBarHorizontal_42": {},
    "navBarHorizontal_43": {},
    "navBarHorizontal_5": {},
    "navBarHorizontal_6": {},
    "navBarHorizontal_7": {},
    "navBarHorizontal_8": {},
    "navBarHorizontal_9": {},
    "navBarVertical_admin": {},
    "navBarVertical_admin_1": {},
    "navBarVertical_admin_10": {},
    "navBarVertical_admin_11": {},
    "navBarVertical_admin_12": {},
    "navBarVertical_admin_13": {},
    "navBarVertical_admin_14": {},
    "navBarVertical_admin_15": {},
    "navBarVertical_admin_16": {},
    "navBarVertical_admin_17": {},
    "navBarVertical_admin_18": {},
    "navBarVertical_admin_19": {},
    "navBarVertical_admin_2": {},
    "navBarVertical_admin_20": {},
    "navBarVertical_admin_21": {},
    "navBarVertical_admin_22": {},
    "navBarVertical_admin_23": {},
    "navBarVertical_admin_24": {},
    "navBarVertical_admin_25": {},
    "navBarVertical_admin_26": {},
    "navBarVertical_admin_27": {},
    "navBarVertical_admin_28": {},
    "navBarVertical_admin_29": {},
    "navBarVertical_admin_3": {},
    "navBarVertical_admin_30": {},
    "navBarVertical_admin_31": {},
    "navBarVertical_admin_32": {},
    "navBarVertical_admin_33": {},
    "navBarVertical_admin_34": {},
    "navBarVertical_admin_35": {},
    "navBarVertical_admin_36": {},
    "navBarVertical_admin_37": {},
    "navBarVertical_admin_38": {},
    "navBarVertical_admin_39": {},
    "navBarVertical_admin_4": {},
    "navBarVertical_admin_40": {},
    "navBarVertical_admin_41": {},
    "navBarVertical_admin_42": {},
    "navBarVertical_admin_43": {},
    "navBarVertical_admin_5": {},
    "navBarVertical_admin_6": {},
    "navBarVertical_admin_7": {},
    "navBarVertical_admin_8": {},
    "navBarVertical_admin_9": {},
    "navBarVertical_cg": {},
    "navBarVertical_cg_1": {},
    "navBarVertical_cg_2": {},
    "navBarVertical_cg_3": {},
    "New Category": {},
    "New Category_1": {},
    "New Category_2": {},
    "New Category_3": {},
    "New Category_4": {},
    "New Project_1": {},
    "New Project_10": {},
    "New Project_11": {},
    "New Project_12": {},
    "New Project_13": {},
    "New Project_14": {},
    "New Project_2": {},
    "New Project_3": {},
    "New Project_4": {},
    "New Project_5": {},
    "New Project_6": {},
    "New Project_7": {},
    "New Project_8": {},
    "New Project_9": {},
    "New Technology": {},
    "New Technology_1": {},
    "NextArrow11": {},
    "NextArrow13": {},
    "NextArrow17": {},
    "NextArrow19": {},
    "NextArrow4": {},
    "NextArrow5": {},
    "Owner Header": {},
    "Owner Label": {},
    "Owner Label_1": {},
    "paginationBar": {},
    "PowerBI2": {},
    "Projects_1": {},
    "projectsactivelabel": {},
    "React is a JavaScript library for building user interfaces. It is declarative, efficient, and flexible. React makes it easy to create interactive UIs by using a component-based approach.": {},
    "React is a JavaScript library for building user interfaces. It is declarative, efficient, and flexible. React makes it easy to create interactive UIs by using a component-based approach._1": {},
    "Rectangle 31": {},
    "Rectangle 31_10": {},
    "Rectangle 31_11": {},
    "Rectangle 31_12": {},
    "Rectangle 31_13": {},
    "Rectangle 31_14": {},
    "Rectangle 31_15": {},
    "Rectangle 31_16": {},
    "Rectangle 31_17": {},
    "Rectangle 31_2": {},
    "Rectangle 31_3": {},
    "Rectangle 31_4": {},
    "Rectangle 31_5": {},
    "Rectangle 31_6": {},
    "Rectangle 31_7": {},
    "Rectangle 31_8": {},
    "Rectangle 31_9": {},
    "Rectangle 32": {},
    "Rectangle 32_10": {},
    "Rectangle 32_11": {},
    "Rectangle 32_12": {},
    "Rectangle 32_13": {},
    "Rectangle 32_14": {},
    "Rectangle 32_15": {},
    "Rectangle 32_16": {},
    "Rectangle 32_17": {},
    "Rectangle 32_2": {},
    "Rectangle 32_3": {},
    "Rectangle 32_4": {},
    "Rectangle 32_5": {},
    "Rectangle 32_6": {},
    "Rectangle 32_7": {},
    "Rectangle 32_8": {},
    "Rectangle 32_9": {},
    "Rectangle1": {},
    "Rectangle12": {},
    "Rectangle14": {},
    "Rectangle18": {},
    "Rectangle2": {},
    "Rectangle20": {},
    "Rectangle3": {},
    "Rectangle3_3": {},
    "Rectangle3_4": {},
    "Rectangle3_6": {},
    "Rectangle4_3": {},
    "Rectangle4_4": {},
    "Rectangle4_6": {},
    "Rectangle5": {},
    "Rectangle6_2": {},
    "Rectangle6_3": {},
    "Rectangle6_5": {},
    "Rectangle7": {},
    "Refreshed On Header": {},
    "Refreshed On Header_1": {},
    "Refreshed On Header_2": {},
    "Refreshed On Label": {},
    "Refreshed On Label_1": {},
    "Refreshed On Label_2": {},
    "Report Header": {},
    "Report Header_1": {},
    "Report Header_10": {},
    "Report Header_11": {},
    "Report Header_12": {},
    "Report Header_13": {},
    "Report Header_14": {},
    "Report Header_15": {},
    "Report Header_16": {},
    "Report Header_17": {},
    "Report Header_18": {},
    "Report Header_2": {},
    "Report Header_20": {},
    "Report Header_21": {},
    "Report Header_22": {},
    "Report Header_23": {},
    "Report Header_24": {},
    "Report Header_25": {},
    "Report Header_26": {},
    "Report Header_27": {},
    "Report Header_28": {},
    "Report Header_29": {},
    "Report Header_3": {},
    "Report Header_4": {},
    "Report Header_5": {},
    "Report Header_6": {},
    "Report Header_7": {},
    "Report Header_8": {},
    "Report Header_9": {},
    "Report Label": {},
    "Report Label_1": {},
    "Report Label_10": {},
    "Report Label_11": {},
    "Report Label_12": {},
    "Report Label_13": {},
    "Report Label_14": {},
    "Report Label_15": {},
    "Report Label_16": {},
    "Report Label_17": {},
    "Report Label_18": {},
    "Report Label_2": {},
    "Report Label_20": {},
    "Report Label_21": {},
    "Report Label_22": {},
    "Report Label_23": {},
    "Report Label_24": {},
    "Report Label_25": {},
    "Report Label_26": {},
    "Report Label_27": {},
    "Report Label_28": {},
    "Report Label_29": {},
    "Report Label_3": {},
    "Report Label_4": {},
    "Report Label_5": {},
    "Report Label_6": {},
    "Report Label_7": {},
    "Report Label_8": {},
    "Report Label_9": {},
    "rowCount": {},
    "search": {},
    "searchLevel": {},
    "Separator1": {},
    "Separator1_2": {},
    "Separator1_4": {},
    "Separator12": {},
    "Separator14": {},
    "Separator18": {},
    "Separator20": {},
    "Separator5": {},
    "Separator6": {},
    "skillCategory_6": {},
    "skillCategory_7": {},
    "skillCategory_8": {},
    "skillCategory_9": {},
    "SkillLabel": {},
    "SkillLabel_1": {},
    "skillName": {},
    "skillName_1": {},
    "skillName_2": {},
    "skillName_3": {},
    "Subtitle1": {},
    "Subtitle1_14": {},
    "Subtitle1_15": {},
    "Subtitle1_2": {},
    "Subtitle1_3": {},
    "Subtitle1_8": {},
    "Subtitle1_9": {},
    "Subtitle13": {},
    "Subtitle22": {},
    "Subtitle25": {},
    "Subtitle27": {},
    "Subtitle5": {},
    "Subtitle6": {},
    "Table Headers Container": {},
    "Team_3": {},
    "Team_5": {},
    "TextInput1": {},
    "TextInput1_1": {},
    "TextInput1_2": {},
    "TextInput1_3": {},
    "TextInput1_4": {},
    "TextInput1_5": {},
    "TextInput1_6": {},
    "TextInput1_7": {},
    "TextInput1_8": {},
    "TextInput2": {},
    "TextInput2_1": {},
    "TextInput2_10": {},
    "TextInput2_2": {},
    "TextInput2_3": {},
    "TextInput2_4": {},
    "TextInput2_5": {},
    "TextInput2_6": {},
    "TextInput2_7": {},
    "TextInput2_8": {},
    "TextInput2_9": {},
    "Title1_2": {},
    "Title1_4": {},
    "Title14": {},
    "Title2": {},
    "Title2_1": {},
    "Title2_10": {},
    "Title2_100": {},
    "Title2_101": {},
    "Title2_102": {},
    "Title2_103": {},
    "Title2_104": {},
    "Title2_105": {},
    "Title2_106": {},
    "Title2_107": {},
    "Title2_108": {},
    "Title2_109": {},
    "Title2_11": {},
    "Title2_110": {},
    "Title2_111": {},
    "Title2_112": {},
    "Title2_113": {},
    "Title2_114": {},
    "Title2_115": {},
    "Title2_116": {},
    "Title2_117": {},
    "Title2_118": {},
    "Title2_119": {},
    "Title2_12": {},
    "Title2_13": {},
    "Title2_14": {},
    "Title2_15": {},
    "Title2_16": {},
    "Title2_17": {},
    "Title2_18": {},
    "Title2_19": {},
    "Title2_2": {},
    "Title2_20": {},
    "Title2_21": {},
    "Title2_22": {},
    "Title2_23": {},
    "Title2_24": {},
    "Title2_3": {},
    "Title2_33": {},
    "Title2_34": {},
    "Title2_35": {},
    "Title2_36": {},
    "Title2_37": {},
    "Title2_38": {},
    "Title2_39": {},
    "Title2_4": {},
    "Title2_48": {},
    "Title2_49": {},
    "Title2_5": {},
    "Title2_50": {},
    "Title2_51": {},
    "Title2_52": {},
    "Title2_53": {},
    "Title2_54": {},
    "Title2_55": {},
    "Title2_56": {},
    "Title2_57": {},
    "Title2_58": {},
    "Title2_59": {},
    "Title2_6": {},
    "Title2_60": {},
    "Title2_61": {},
    "Title2_62": {},
    "Title2_63": {},
    "Title2_64": {},
    "Title2_65": {},
    "Title2_66": {},
    "Title2_67": {},
    "Title2_68": {},
    "Title2_69": {},
    "Title2_7": {},
    "Title2_70": {},
    "Title2_71": {},
    "Title2_72": {},
    "Title2_73": {},
    "Title2_74": {},
    "Title2_75": {},
    "Title2_76": {},
    "Title2_77": {},
    "Title2_78": {},
    "Title2_79": {},
    "Title2_8": {},
    "Title2_80": {},
    "Title2_81": {},
    "Title2_82": {},
    "Title2_83": {},
    "Title2_84": {},
    "Title2_85": {},
    "Title2_86": {},
    "Title2_87": {},
    "Title2_9": {},
    "Title2_96": {},
    "Title2_97": {},
    "Title2_98": {},
    "Title2_99": {},
    "Title23": {},
    "Title27": {},
    "Title29": {},
    "Title5": {},
    "Title9": {},
    "Toggle1": {},
    "Toggle1_1": {},
    "txtCaregiverID": {},
    "Update Caregivers": {},
    "Update Caregivers_1": {},
    "Update Caregivers_2": {}
  },
  "PCFDynamicSchemaForIRRetrievalEntry": {},
  "PCFTemplateEntry": {},
  "PublishOrderIndices": {
    "Action Header": 866,
    "Action Header_2": 789,
    "Action Header_3": 306,
    "Action Header_4": 753,
    "Action Header_5": 21,
    "Action Header_6": 832,
    "Action Header_7": 123,
    "Action Label": 882,
    "Action Label_2": 800,
    "Action Label_3": 317,
    "Action Label_4": 765,
    "Action Label_5": 32,
    "Action Label_6": 841,
    "Action Label_7": 133,
    "App": 0,
    "attachCard_1": 1065,
    "Body3": 395,
    "Button1": 390,
    "Button2": 939,
    "Button2_1": 384,
    "Button2_2": 941,
    "Button3": 386,
    "Button3_1": 388,
    "Button4": 1060,
    "Button5": 311,
    "Button5_1": 310,
    "Button5_10": 129,
    "Button5_11": 130,
    "Button5_12": 779,
    "Button5_13": 873,
    "Button5_2": 26,
    "Button5_3": 25,
    "Button5_4": 793,
    "Button5_5": 794,
    "Button5_6": 838,
    "Button5_7": 837,
    "Button5_8": 872,
    "Button5_9": 871,
    "Button7": 1067,
    "Button7_3": 498,
    "Button7_4": 511,
    "Button7_6": 614,
    "Button8": 916,
    "Button8_1": 914,
    "Button8_2": 915,
    "Button9": 111,
    "Button9_1": 112,
    "Button9_2": 681,
    "Button9_3": 682,
    "Button9_4": 683,
    "Capability": 122,
    "Capability_1": 153,
    "capabilitydpdwn": 360,
    "Caregivers": 59,
    "Category": 861,
    "Category Header": 863,
    "Category Header_1": 289,
    "Category Header_10": 168,
    "Category Header_11": 175,
    "Category Header_12": 740,
    "Category Header_13": 141,
    "Category Header_14": 148,
    "Category Header_15": 235,
    "Category Header_16": 241,
    "Category Header_2": 787,
    "Category Header_3": 304,
    "Category Header_4": 314,
    "Category Header_5": 747,
    "Category Header_6": 305,
    "Category Header_7": 797,
    "Category Header_8": 19,
    "Category Header_9": 29,
    "Category Label": 879,
    "Category Label_1": 297,
    "Category Label_10": 176,
    "Category Label_11": 766,
    "Category Label_14": 149,
    "Category Label_16": 242,
    "Category Label_17": 156,
    "Category Label_2": 798,
    "Category Label_3": 315,
    "Category Label_4": 799,
    "Category Label_5": 759,
    "Category Label_6": 316,
    "Category Label_7": 30,
    "Category Label_8": 31,
    "Category Label_9": 126,
    "Category_1": 785,
    "Category_10": 322,
    "Category_11": 37,
    "Category_12": 806,
    "Category_13": 850,
    "Category_14": 105,
    "Category_15": 106,
    "Category_16": 90,
    "Category_17": 89,
    "Category_18": 817,
    "Category_19": 816,
    "Category_2": 302,
    "Category_20": 673,
    "Category_21": 674,
    "Category_23": 703,
    "Category_24": 704,
    "Category_25": 705,
    "Category_26": 716,
    "Category_27": 717,
    "Category_28": 718,
    "Category_29": 691,
    "Category_3": 17,
    "Category_30": 693,
    "Category_31": 692,
    "Category_32": 48,
    "Category_4": 830,
    "Category_5": 165,
    "Category_6": 138,
    "Category_7": 233,
    "Category_8": 249,
    "Category_9": 287,
    "CategoryLabel": 869,
    "Checkbox1": 65,
    "Column - Header 13": 867,
    "Column - Header 4_2": 791,
    "ComboBox1": 595,
    "ComboBox1_1": 225,
    "ComboBox2": 271,
    "ComboBox2_1": 529,
    "ComboBox3": 726,
    "ComboBox3_1": 727,
    "ComboBox3_2": 728,
    "ComboBox5": 273,
    "ComboBox5_1": 531,
    "comment": 1059,
    "comment_1": 925,
    "comment_2": 921,
    "comment_3": 922,
    "Data Analytics_1": 801,
    "Data Analytics_3": 23,
    "DatePicker1": 520,
    "DatePicker1_1": 523,
    "Description Header": 865,
    "Description Header_1": 748,
    "Description Header_2": 834,
    "Description Label": 881,
    "Description Label_1": 760,
    "Description Label_2": 843,
    "descriptionlabel": 307,
    "descriptionlabel_1": 169,
    "descriptionlabel_2": 324,
    "Dropdown1_1": 292,
    "Dropdown1_2": 157,
    "Favourite Header": 752,
    "Favourite Label": 764,
    "Gallery1": 70,
    "Gallery1_2": 376,
    "Gallery1_4": 377,
    "Gallery10": 326,
    "Gallery11": 325,
    "Gallery12": 852,
    "Gallery13": 72,
    "Gallery14": 40,
    "Gallery15": 807,
    "Gallery16": 742,
    "Gallery17": 380,
    "Gallery18": 92,
    "Gallery18_1": 708,
    "Gallery18_2": 720,
    "Gallery18_3": 695,
    "Gallery19": 819,
    "Gallery2_1": 657,
    "Gallery20": 51,
    "Gallery21": 267,
    "Gallery28": 382,
    "Gallery29": 346,
    "Gallery3": 896,
    "Gallery3_1": 904,
    "Gallery31": 379,
    "Gallery33": 378,
    "Gallery4": 381,
    "Gallery5": 926,
    "Gallery5_1": 947,
    "Gallery5_2": 928,
    "Gallery5_3": 927,
    "Gallery6": 342,
    "Gallery6_1": 344,
    "Gallery7": 898,
    "Gallery7_1": 340,
    "Gallery7_2": 899,
    "Gallery8": 375,
    "Gallery9": 874,
    "Gallery9_1": 875,
    "Gallery9_2": 876,
    "galleryTemplate1": 77,
    "galleryTemplate1_2": 398,
    "galleryTemplate1_4": 403,
    "galleryTemplate10": 884,
    "galleryTemplate10_1": 885,
    "galleryTemplate10_2": 886,
    "galleryTemplate11": 330,
    "galleryTemplate12": 328,
    "galleryTemplate13": 854,
    "galleryTemplate14": 85,
    "galleryTemplate15": 42,
    "galleryTemplate16": 810,
    "galleryTemplate17": 772,
    "galleryTemplate18": 420,
    "galleryTemplate19": 95,
    "galleryTemplate19_1": 711,
    "galleryTemplate19_2": 723,
    "galleryTemplate19_3": 698,
    "galleryTemplate2": 84,
    "galleryTemplate20": 822,
    "galleryTemplate21": 53,
    "galleryTemplate22": 270,
    "galleryTemplate29": 432,
    "galleryTemplate3_1": 665,
    "galleryTemplate30": 389,
    "galleryTemplate32": 414,
    "galleryTemplate34": 408,
    "galleryTemplate4": 934,
    "galleryTemplate4_1": 942,
    "galleryTemplate5": 426,
    "galleryTemplate6": 948,
    "galleryTemplate6_1": 973,
    "galleryTemplate6_3": 998,
    "galleryTemplate6_4": 1023,
    "galleryTemplate7": 385,
    "galleryTemplate7_1": 387,
    "galleryTemplate8": 938,
    "galleryTemplate8_1": 383,
    "galleryTemplate8_2": 940,
    "galleryTemplate9": 391,
    "Group1": 932,
    "Group2_3": 501,
    "Group2_4": 526,
    "Group2_6": 617,
    "Group3": 933,
    "Group3_1": 930,
    "Group3_2": 931,
    "Group7_4": 1061,
    "grouplabel": 308,
    "hiddenGallery": 71,
    "Host": 0,
    "Icon1_19": 583,
    "Icon1_2": 554,
    "Icon1_20": 584,
    "Icon1_21": 585,
    "Icon1_24": 188,
    "Icon1_26": 197,
    "Icon1_27": 646,
    "Icon1_28": 206,
    "Icon1_29": 205,
    "Icon1_3": 567,
    "Icon1_30": 221,
    "Icon1_31": 220,
    "Icon1_32": 647,
    "Icon1_33": 541,
    "Icon1_34": 213,
    "Icon1_35": 214,
    "Icon1_36": 215,
    "Icon1_37": 542,
    "Icon1_40": 448,
    "Icon1_41": 449,
    "Icon1_42": 465,
    "Icon1_43": 492,
    "Icon1_44": 515,
    "Icon1_45": 627,
    "Icon1_46": 609,
    "Icon1_47": 477,
    "Icon1_48": 478,
    "Icon1_5": 575,
    "Icon1_51": 648,
    "Icon1_52": 543,
    "Icon1_6": 576,
    "Icon1_7": 593,
    "Icon1_8": 594,
    "Image1": 2,
    "Image3": 75,
    "Image4": 74,
    "Image5_10": 7,
    "Image5_11": 4,
    "Image5_6": 9,
    "Image5_7": 10,
    "Image5_8": 6,
    "Image5_9": 5,
    "Image8": 335,
    "Image8_1": 333,
    "Image8_2": 337,
    "Image8_3": 339,
    "Image8_4": 341,
    "Image8_5": 343,
    "Image8_6": 345,
    "Image8_7": 347,
    "Label1": 73,
    "Label10": 367,
    "Label10_1": 368,
    "Label10_2": 369,
    "Label10_3": 371,
    "Label11": 792,
    "Label11_1": 128,
    "Label11_2": 836,
    "Label12": 780,
    "Label13": 825,
    "Label13_3": 658,
    "Label13_4": 659,
    "Label13_5": 660,
    "Label14": 275,
    "Label14_1": 654,
    "Label15": 788,
    "Label15_1": 20,
    "Label15_2": 125,
    "Label16": 790,
    "Label16_1": 22,
    "Label16_2": 142,
    "Label16_4": 39,
    "Label16_5": 808,
    "Label16_6": 50,
    "Label17": 277,
    "Label17_1": 661,
    "Label18": 707,
    "Label19_3": 666,
    "Label19_4": 667,
    "Label19_5": 668,
    "Label2": 66,
    "Label2_1": 67,
    "Label2_10": 370,
    "Label2_12": 365,
    "Label2_13": 364,
    "Label2_14": 374,
    "Label2_15": 373,
    "Label2_2": 68,
    "Label2_3": 69,
    "Label2_8": 372,
    "Label2_9": 366,
    "Label20": 771,
    "Label20_1": 781,
    "Label21": 321,
    "Label21_1": 36,
    "Label21_2": 805,
    "Label21_3": 849,
    "Label21_4": 47,
    "Label22": 855,
    "Label23": 24,
    "Label24": 768,
    "Label24_1": 769,
    "Label24_3": 773,
    "Label24_4": 777,
    "Label24_5": 775,
    "Label24_6": 770,
    "Label24_7": 778,
    "Label24_8": 774,
    "Label24_9": 776,
    "Label25": 99,
    "Label26": 329,
    "Label27": 323,
    "Label27_1": 38,
    "Label27_2": 811,
    "Label27_3": 851,
    "Label27_4": 49,
    "Label28": 78,
    "Label28_1": 79,
    "Label29": 43,
    "Label3": 131,
    "Label3_1": 184,
    "Label3_11": 194,
    "Label3_12": 211,
    "Label3_13": 187,
    "Label3_16": 589,
    "Label3_17": 571,
    "Label3_18": 573,
    "Label3_19": 565,
    "Label3_2": 185,
    "Label3_20": 553,
    "Label3_21": 219,
    "Label3_22": 196,
    "Label3_23": 566,
    "Label3_24": 643,
    "Label3_25": 186,
    "Label3_26": 587,
    "Label3_27": 210,
    "Label3_28": 212,
    "Label3_29": 582,
    "Label3_30": 579,
    "Label3_31": 577,
    "Label3_32": 645,
    "Label3_33": 538,
    "Label3_34": 540,
    "Label3_35": 276,
    "Label3_36": 274,
    "Label3_37": 644,
    "Label3_38": 539,
    "Label3_4": 557,
    "Label3_5": 558,
    "Label3_7": 217,
    "Label3_8": 203,
    "Label3_9": 204,
    "Label30": 812,
    "Label31": 743,
    "Label32": 870,
    "Label32_3": 497,
    "Label32_4": 509,
    "Label32_6": 613,
    "Label33": 64,
    "Label34": 110,
    "Label34_1": 109,
    "Label34_2": 679,
    "Label34_3": 680,
    "Label34_5": 678,
    "Label35": 54,
    "Label36": 734,
    "Label36_1": 735,
    "Label36_2": 736,
    "Label37": 96,
    "Label37_1": 712,
    "Label37_2": 724,
    "Label38": 823,
    "Label4": 892,
    "Label5": 699,
    "Label6": 195,
    "Label6_12": 590,
    "Label6_13": 563,
    "Label6_14": 193,
    "Label6_15": 556,
    "Label6_16": 555,
    "Label6_17": 572,
    "Label6_18": 574,
    "Label6_19": 586,
    "Label6_20": 444,
    "Label6_21": 445,
    "Label6_23": 462,
    "Label6_25": 512,
    "Label6_26": 518,
    "Label6_27": 521,
    "Label6_29": 624,
    "Label6_3": 202,
    "Label6_31": 606,
    "Label6_33": 564,
    "Label6_34": 216,
    "Label6_35": 490,
    "Label6_37": 209,
    "Label6_38": 578,
    "Label6_39": 474,
    "Label6_4": 201,
    "Label6_40": 641,
    "Label6_41": 642,
    "Label6_42": 640,
    "Label6_43": 535,
    "Label6_44": 536,
    "Label6_45": 537,
    "Label6_5": 218,
    "Label7": 903,
    "Label7_1": 900,
    "Label7_2": 901,
    "Label8": 935,
    "Label8_1": 936,
    "Label8_2": 937,
    "Label8_3": 943,
    "Label8_4": 944,
    "Label8_5": 945,
    "Label8_6": 946,
    "Label9": 332,
    "Label9_1": 653,
    "msft_Button": 454,
    "msft_Button_11": 355,
    "msft_Button_12": 362,
    "msft_Button_13": 737,
    "msft_Button_14": 312,
    "msft_Button_15": 327,
    "msft_Button_16": 100,
    "msft_Button_17": 101,
    "msft_Button_18": 350,
    "msft_Button_19": 468,
    "msft_Button_20": 227,
    "msft_Button_21": 228,
    "msft_Button_22": 361,
    "msft_Button_23": 630,
    "msft_Button_24": 363,
    "msft_Button_25": 61,
    "msft_Button_27": 597,
    "msft_Button_28": 598,
    "msft_Button_30": 631,
    "msft_Button_31": 615,
    "msft_Button_32": 616,
    "msft_Button_33": 132,
    "msft_Button_34": 795,
    "msft_Button_35": 27,
    "msft_Button_36": 839,
    "msft_Button_37": 877,
    "msft_Button_38": 349,
    "msft_Button_39": 41,
    "msft_Button_4": 469,
    "msft_Button_40": 809,
    "msft_Button_41": 499,
    "msft_Button_42": 500,
    "msft_Button_43": 455,
    "msft_Button_44": 853,
    "msft_Button_45": 173,
    "msft_Button_46": 348,
    "msft_Button_47": 146,
    "msft_Button_48": 60,
    "msft_Button_49": 238,
    "msft_Button_5": 482,
    "msft_Button_50": 1066,
    "msft_Button_51": 254,
    "msft_Button_52": 295,
    "msft_Button_53": 294,
    "msft_Button_54": 159,
    "msft_Button_55": 160,
    "msft_Button_56": 255,
    "msft_Button_58": 929,
    "msft_Button_6": 524,
    "msft_Button_60": 52,
    "msft_Button_61": 239,
    "msft_Button_62": 145,
    "msft_Button_63": 172,
    "msft_Button_64": 481,
    "msft_Button_65": 113,
    "msft_Button_66": 93,
    "msft_Button_67": 820,
    "msft_Button_7": 525,
    "msft_Button_70": 684,
    "msft_Button_71": 709,
    "msft_Button_72": 721,
    "msft_Button_73": 696,
    "msft_Button_76": 268,
    "msft_Button_77": 664,
    "msft_Button_78": 652,
    "msft_Button_79": 656,
    "msft_Button_80": 655,
    "msft_Button_81": 669,
    "msft_Button_82": 662,
    "msft_Button_83": 278,
    "msft_Button_84": 279,
    "msft_Button_85": 269,
    "msft_Button_86": 546,
    "msft_DatePicker_2": 189,
    "msft_DatePicker_3": 190,
    "msft_DatePicker_4": 561,
    "msft_DatePicker_5": 562,
    "msft_Dropdown": 451,
    "msft_Dropdown_10": 208,
    "msft_Dropdown_19": 568,
    "msft_Dropdown_20": 580,
    "msft_Dropdown_21": 581,
    "msft_Dropdown_24": 569,
    "msft_Dropdown_27": 560,
    "msft_Dropdown_28": 199,
    "msft_Dropdown_29": 226,
    "msft_Dropdown_30": 200,
    "msft_Dropdown_31": 649,
    "msft_Dropdown_32": 192,
    "msft_Dropdown_33": 596,
    "msft_Dropdown_35": 650,
    "msft_Dropdown_36": 544,
    "msft_Dropdown_39": 280,
    "msft_Dropdown_40": 651,
    "msft_Dropdown_41": 545,
    "msft_Dropdown_9": 207,
    "msft_Label": 446,
    "msft_Label_1": 447,
    "msft_Label_10": 894,
    "msft_Label_11": 514,
    "msft_Label_12": 625,
    "msft_Label_13": 626,
    "msft_Label_14": 607,
    "msft_Label_15": 608,
    "msft_Label_16": 522,
    "msft_Label_17": 491,
    "msft_Label_18": 493,
    "msft_Label_19": 895,
    "msft_Label_2": 452,
    "msft_Label_3": 475,
    "msft_Label_34": 1055,
    "msft_Label_35": 1056,
    "msft_Label_36": 1054,
    "msft_Label_37": 910,
    "msft_Label_38": 913,
    "msft_Label_39": 909,
    "msft_Label_4": 476,
    "msft_Label_40": 907,
    "msft_Label_41": 911,
    "msft_Label_42": 905,
    "msft_Label_43": 908,
    "msft_Label_44": 912,
    "msft_Label_45": 906,
    "msft_Label_5": 463,
    "msft_Label_6": 464,
    "msft_Label_7": 513,
    "msft_Label_8": 519,
    "msft_Label_9": 893,
    "msft_TextInput": 450,
    "msft_TextInput_1": 453,
    "msft_TextInput_10": 495,
    "msft_TextInput_11": 223,
    "msft_TextInput_12": 198,
    "msft_TextInput_13": 559,
    "msft_TextInput_14": 222,
    "msft_TextInput_15": 591,
    "msft_TextInput_16": 570,
    "msft_TextInput_17": 588,
    "msft_TextInput_19": 628,
    "msft_TextInput_2": 479,
    "msft_TextInput_20": 629,
    "msft_TextInput_21": 610,
    "msft_TextInput_22": 611,
    "msft_TextInput_3": 480,
    "msft_TextInput_4": 466,
    "msft_TextInput_5": 467,
    "msft_TextInput_6": 516,
    "msft_TextInput_7": 517,
    "msft_TextInput_8": 191,
    "msft_TextInput_9": 494,
    "msftcapability": 14,
    "msftcapabilitylists": 33,
    "msftcaregiverdiscipline": 44,
    "msftcaregivers": 55,
    "msftcaregiverscount": 86,
    "msftconfirmationscreen": 97,
    "msftcostcenter": 102,
    "msftDashboard": 115,
    "msftdiscipline": 119,
    "msfteditcapability": 135,
    "msfteditdiscipline": 150,
    "msfteditgroup": 162,
    "msfteditproject": 177,
    "msfteditprojectgoal": 229,
    "msfteditprojecttype": 243,
    "msfteditteam": 258,
    "msftedittechnology": 281,
    "msftgroup": 299,
    "msftgrouplists": 318,
    "msftMasterData": 331,
    "msftnewcategory": 438,
    "msftnewcategory2": 456,
    "msftnewcertification": 470,
    "msftnewdiscipline": 483,
    "msftnewgroup": 502,
    "msftnewMember": 527,
    "msftnewproject": 547,
    "msftnewprojectgoal": 599,
    "msftnewprojecttype": 618,
    "msftnewteam": 632,
    "msftpeopleskills": 670,
    "msftpeoplewithskillsadvanced": 688,
    "msftpeoplewithskillsbeginner": 700,
    "msftpeoplewithskillsintermediate": 713,
    "msftproject": 725,
    "msftprojectgoal": 782,
    "msftprojectgoallists": 802,
    "msftprojectscount": 813,
    "msftprojecttype": 824,
    "msftprojecttypelists": 844,
    "msfttechnology": 856,
    "msftUpdatecaregivers": 887,
    "msftUpdateSkill_Caregiver": 1048,
    "msftUploadData": 1062,
    "navBarHorizontal": 1,
    "navBarHorizontal_1": 890,
    "navBarHorizontal_10": 505,
    "navBarHorizontal_11": 301,
    "navBarHorizontal_12": 621,
    "navBarHorizontal_13": 784,
    "navBarHorizontal_14": 602,
    "navBarHorizontal_15": 16,
    "navBarHorizontal_16": 828,
    "navBarHorizontal_17": 486,
    "navBarHorizontal_18": 1051,
    "navBarHorizontal_19": 152,
    "navBarHorizontal_2": 441,
    "navBarHorizontal_20": 164,
    "navBarHorizontal_21": 137,
    "navBarHorizontal_22": 231,
    "navBarHorizontal_23": 246,
    "navBarHorizontal_24": 284,
    "navBarHorizontal_25": 847,
    "navBarHorizontal_26": 320,
    "navBarHorizontal_27": 35,
    "navBarHorizontal_28": 804,
    "navBarHorizontal_29": 58,
    "navBarHorizontal_3": 459,
    "navBarHorizontal_30": 731,
    "navBarHorizontal_31": 472,
    "navBarHorizontal_32": 1064,
    "navBarHorizontal_33": 104,
    "navBarHorizontal_34": 88,
    "navBarHorizontal_35": 815,
    "navBarHorizontal_36": 672,
    "navBarHorizontal_37": 702,
    "navBarHorizontal_38": 715,
    "navBarHorizontal_39": 690,
    "navBarHorizontal_4": 117,
    "navBarHorizontal_40": 46,
    "navBarHorizontal_41": 261,
    "navBarHorizontal_42": 635,
    "navBarHorizontal_43": 532,
    "navBarHorizontal_5": 336,
    "navBarHorizontal_6": 180,
    "navBarHorizontal_7": 550,
    "navBarHorizontal_8": 859,
    "navBarHorizontal_9": 121,
    "navBarVertical_admin": 3,
    "navBarVertical_admin_1": 116,
    "navBarVertical_admin_10": 120,
    "navBarVertical_admin_11": 151,
    "navBarVertical_admin_12": 858,
    "navBarVertical_admin_13": 283,
    "navBarVertical_admin_14": 827,
    "navBarVertical_admin_15": 846,
    "navBarVertical_admin_16": 245,
    "navBarVertical_admin_17": 783,
    "navBarVertical_admin_18": 803,
    "navBarVertical_admin_19": 230,
    "navBarVertical_admin_2": 440,
    "navBarVertical_admin_20": 15,
    "navBarVertical_admin_21": 34,
    "navBarVertical_admin_22": 136,
    "navBarVertical_admin_23": 300,
    "navBarVertical_admin_24": 319,
    "navBarVertical_admin_25": 163,
    "navBarVertical_admin_26": 888,
    "navBarVertical_admin_27": 56,
    "navBarVertical_admin_28": 730,
    "navBarVertical_admin_29": 334,
    "navBarVertical_admin_3": 458,
    "navBarVertical_admin_30": 1049,
    "navBarVertical_admin_31": 471,
    "navBarVertical_admin_32": 1063,
    "navBarVertical_admin_33": 103,
    "navBarVertical_admin_34": 87,
    "navBarVertical_admin_35": 814,
    "navBarVertical_admin_36": 671,
    "navBarVertical_admin_37": 701,
    "navBarVertical_admin_38": 714,
    "navBarVertical_admin_39": 689,
    "navBarVertical_admin_4": 485,
    "navBarVertical_admin_40": 45,
    "navBarVertical_admin_41": 260,
    "navBarVertical_admin_42": 634,
    "navBarVertical_admin_43": 530,
    "navBarVertical_admin_5": 504,
    "navBarVertical_admin_6": 620,
    "navBarVertical_admin_7": 601,
    "navBarVertical_admin_8": 549,
    "navBarVertical_admin_9": 179,
    "navBarVertical_cg": 8,
    "navBarVertical_cg_1": 57,
    "navBarVertical_cg_2": 1050,
    "navBarVertical_cg_3": 889,
    "New Category": 461,
    "New Category_1": 510,
    "New Category_2": 623,
    "New Category_3": 605,
    "New Category_4": 489,
    "New Project_1": 182,
    "New Project_10": 263,
    "New Project_11": 264,
    "New Project_12": 637,
    "New Project_13": 638,
    "New Project_14": 534,
    "New Project_2": 552,
    "New Project_3": 166,
    "New Project_4": 139,
    "New Project_5": 232,
    "New Project_6": 248,
    "New Project_7": 286,
    "New Project_8": 154,
    "New Project_9": 183,
    "New Technology": 443,
    "New Technology_1": 473,
    "NextArrow11": 422,
    "NextArrow13": 434,
    "NextArrow17": 416,
    "NextArrow19": 410,
    "NextArrow4": 428,
    "NextArrow5": 393,
    "Owner Header": 751,
    "Owner Label": 763,
    "Owner Label_1": 754,
    "paginationBar": 11,
    "PowerBI2": 118,
    "Projects_1": 733,
    "projectsactivelabel": 309,
    "React is a JavaScript library for building user interfaces. It is declarative, efficient, and flexible. React makes it easy to create interactive UIs by using a component-based approach.": 883,
    "React is a JavaScript library for building user interfaces. It is declarative, efficient, and flexible. React makes it easy to create interactive UIs by using a component-based approach._1": 127,
    "Rectangle 31": 439,
    "Rectangle 31_10": 600,
    "Rectangle 31_11": 484,
    "Rectangle 31_12": 244,
    "Rectangle 31_13": 282,
    "Rectangle 31_14": 845,
    "Rectangle 31_15": 259,
    "Rectangle 31_16": 633,
    "Rectangle 31_17": 528,
    "Rectangle 31_2": 457,
    "Rectangle 31_3": 548,
    "Rectangle 31_4": 178,
    "Rectangle 31_5": 857,
    "Rectangle 31_6": 503,
    "Rectangle 31_7": 826,
    "Rectangle 31_8": 619,
    "Rectangle 31_9": 729,
    "Rectangle 32": 442,
    "Rectangle 32_10": 604,
    "Rectangle 32_11": 488,
    "Rectangle 32_12": 247,
    "Rectangle 32_13": 285,
    "Rectangle 32_14": 848,
    "Rectangle 32_15": 262,
    "Rectangle 32_16": 636,
    "Rectangle 32_17": 533,
    "Rectangle 32_2": 460,
    "Rectangle 32_3": 551,
    "Rectangle 32_4": 181,
    "Rectangle 32_5": 860,
    "Rectangle 32_6": 507,
    "Rectangle 32_7": 829,
    "Rectangle 32_8": 622,
    "Rectangle 32_9": 732,
    "Rectangle1": 272,
    "Rectangle12": 421,
    "Rectangle14": 433,
    "Rectangle18": 415,
    "Rectangle2": 98,
    "Rectangle20": 409,
    "Rectangle3": 902,
    "Rectangle3_3": 1053,
    "Rectangle3_4": 265,
    "Rectangle3_6": 663,
    "Rectangle4_3": 496,
    "Rectangle4_4": 508,
    "Rectangle4_6": 612,
    "Rectangle5": 427,
    "Rectangle6_2": 487,
    "Rectangle6_3": 506,
    "Rectangle6_5": 603,
    "Rectangle7": 392,
    "Refreshed On Header": 749,
    "Refreshed On Header_1": 750,
    "Refreshed On Header_2": 741,
    "Refreshed On Label": 761,
    "Refreshed On Label_1": 762,
    "Refreshed On Label_2": 767,
    "Report Header": 862,
    "Report Header_1": 864,
    "Report Header_10": 167,
    "Report Header_11": 140,
    "Report Header_12": 234,
    "Report Header_13": 250,
    "Report Header_14": 251,
    "Report Header_15": 288,
    "Report Header_16": 290,
    "Report Header_17": 155,
    "Report Header_18": 755,
    "Report Header_2": 124,
    "Report Header_20": 746,
    "Report Header_21": 107,
    "Report Header_22": 91,
    "Report Header_23": 818,
    "Report Header_24": 675,
    "Report Header_25": 676,
    "Report Header_26": 677,
    "Report Header_27": 706,
    "Report Header_28": 719,
    "Report Header_29": 694,
    "Report Header_3": 786,
    "Report Header_4": 303,
    "Report Header_5": 18,
    "Report Header_6": 744,
    "Report Header_7": 745,
    "Report Header_8": 831,
    "Report Header_9": 833,
    "Report Label": 878,
    "Report Label_1": 880,
    "Report Label_10": 174,
    "Report Label_11": 147,
    "Report Label_12": 240,
    "Report Label_13": 256,
    "Report Label_14": 257,
    "Report Label_15": 296,
    "Report Label_16": 298,
    "Report Label_17": 161,
    "Report Label_18": 756,
    "Report Label_2": 134,
    "Report Label_20": 758,
    "Report Label_21": 108,
    "Report Label_22": 94,
    "Report Label_23": 821,
    "Report Label_24": 685,
    "Report Label_25": 686,
    "Report Label_26": 687,
    "Report Label_27": 710,
    "Report Label_28": 722,
    "Report Label_29": 697,
    "Report Label_3": 796,
    "Report Label_4": 313,
    "Report Label_5": 28,
    "Report Label_6": 114,
    "Report Label_7": 757,
    "Report Label_8": 840,
    "Report Label_9": 842,
    "rowCount": 76,
    "search": 62,
    "searchLevel": 63,
    "Separator1": 83,
    "Separator1_2": 402,
    "Separator1_4": 407,
    "Separator12": 425,
    "Separator14": 437,
    "Separator18": 419,
    "Separator20": 413,
    "Separator5": 397,
    "Separator6": 431,
    "skillCategory_6": 1057,
    "skillCategory_7": 923,
    "skillCategory_8": 917,
    "skillCategory_9": 918,
    "SkillLabel": 868,
    "SkillLabel_1": 835,
    "skillName": 1058,
    "skillName_1": 924,
    "skillName_2": 919,
    "skillName_3": 920,
    "Subtitle1": 81,
    "Subtitle1_14": 405,
    "Subtitle1_15": 406,
    "Subtitle1_2": 80,
    "Subtitle1_3": 82,
    "Subtitle1_8": 400,
    "Subtitle1_9": 401,
    "Subtitle13": 424,
    "Subtitle22": 436,
    "Subtitle25": 418,
    "Subtitle27": 412,
    "Subtitle5": 396,
    "Subtitle6": 430,
    "Table Headers Container": 739,
    "Team_3": 266,
    "Team_5": 639,
    "TextInput1": 351,
    "TextInput1_1": 359,
    "TextInput1_2": 353,
    "TextInput1_3": 356,
    "TextInput1_4": 357,
    "TextInput1_5": 352,
    "TextInput1_6": 358,
    "TextInput1_7": 354,
    "TextInput1_8": 738,
    "TextInput2": 170,
    "TextInput2_1": 171,
    "TextInput2_10": 158,
    "TextInput2_2": 143,
    "TextInput2_3": 144,
    "TextInput2_4": 236,
    "TextInput2_5": 237,
    "TextInput2_6": 252,
    "TextInput2_7": 253,
    "TextInput2_8": 293,
    "TextInput2_9": 291,
    "Title1_2": 399,
    "Title1_4": 404,
    "Title14": 423,
    "Title2": 950,
    "Title2_1": 954,
    "Title2_10": 955,
    "Title2_100": 1032,
    "Title2_101": 1035,
    "Title2_102": 1038,
    "Title2_103": 1041,
    "Title2_104": 1044,
    "Title2_105": 1047,
    "Title2_106": 1028,
    "Title2_107": 1030,
    "Title2_108": 1034,
    "Title2_109": 1046,
    "Title2_11": 959,
    "Title2_110": 1040,
    "Title2_111": 1043,
    "Title2_112": 1037,
    "Title2_113": 1029,
    "Title2_114": 1033,
    "Title2_115": 1031,
    "Title2_116": 1036,
    "Title2_117": 1042,
    "Title2_118": 1039,
    "Title2_119": 1045,
    "Title2_12": 971,
    "Title2_13": 965,
    "Title2_14": 968,
    "Title2_15": 962,
    "Title2_16": 975,
    "Title2_17": 976,
    "Title2_18": 978,
    "Title2_19": 980,
    "Title2_2": 956,
    "Title2_20": 984,
    "Title2_21": 996,
    "Title2_22": 990,
    "Title2_23": 993,
    "Title2_24": 987,
    "Title2_3": 958,
    "Title2_33": 979,
    "Title2_34": 983,
    "Title2_35": 981,
    "Title2_36": 986,
    "Title2_37": 992,
    "Title2_38": 989,
    "Title2_39": 995,
    "Title2_4": 961,
    "Title2_48": 949,
    "Title2_49": 952,
    "Title2_5": 967,
    "Title2_50": 957,
    "Title2_51": 960,
    "Title2_52": 963,
    "Title2_53": 966,
    "Title2_54": 969,
    "Title2_55": 974,
    "Title2_56": 977,
    "Title2_57": 982,
    "Title2_58": 985,
    "Title2_59": 988,
    "Title2_6": 964,
    "Title2_60": 972,
    "Title2_61": 991,
    "Title2_62": 994,
    "Title2_63": 997,
    "Title2_64": 1000,
    "Title2_65": 1001,
    "Title2_66": 999,
    "Title2_67": 1002,
    "Title2_68": 1007,
    "Title2_69": 1010,
    "Title2_7": 970,
    "Title2_70": 1013,
    "Title2_71": 1016,
    "Title2_72": 1019,
    "Title2_73": 1022,
    "Title2_74": 1003,
    "Title2_75": 1005,
    "Title2_76": 1009,
    "Title2_77": 1021,
    "Title2_78": 1015,
    "Title2_79": 1018,
    "Title2_8": 951,
    "Title2_80": 1012,
    "Title2_81": 1004,
    "Title2_82": 1008,
    "Title2_83": 1006,
    "Title2_84": 1011,
    "Title2_85": 1017,
    "Title2_86": 1014,
    "Title2_87": 1020,
    "Title2_9": 953,
    "Title2_96": 1025,
    "Title2_97": 1026,
    "Title2_98": 1024,
    "Title2_99": 1027,
    "Title23": 435,
    "Title27": 417,
    "Title29": 411,
    "Title5": 394,
    "Title9": 429,
    "Toggle1": 224,
    "Toggle1_1": 592,
    "txtCaregiverID": 897,
    "Update Caregivers": 891,
    "Update Caregivers_1": 338,
    "Update Caregivers_2": 1052
  },
  "ResourcesJsonIndices": {
    "Image-caregivers": 2,
    "Image-dashboard": 3,
    "Image-leftArrow": 4,
    "Image-logo": 5,
    "Image-master_data": 6,
    "Image-MicrosoftTeams-image (10)": 7,
    "Image-Projects_2": 8,
    "Image-Prov Infinite Loader": 9,
    "Image-Prov Loader 1": 10,
    "Image-rightArrow": 11,
    "Image-SampleImage": 0,
    "Video-SampleVideo": 1
  },
  "RuleScreenIdWithoutScreen": {},
  "TemplateVersions": {},
  "VolatileProperties": {
    "AnalysisLoadTime": 3.4429118,
    "ControlCount": {
      "0aacb1eb065c442095080747033d8c13": 4,
      "8ae730d7ee9341c68951ab00b8cc853a": 44,
      "attachments": 1,
      "button": 106,
      "checkbox": 1,
      "combobox": 9,
      "datepicker": 6,
      "dropdown": 31,
      "e4379836dfc64dbda2b19049e588929b": 1,
      "f8bd1ef8470046c38c37a4a87233147e": 44,
      "gallery": 40,
      "galleryTemplate": 40,
      "group": 8,
      "groupContainer": 64,
      "icon": 39,
      "image": 18,
      "label": 455,
      "powerbi": 1,
      "rectangle": 61,
      "screen": 44,
      "text": 47,
      "toggleSwitch": 2
    },
    "DeserializationLoadTime": 3.8422716
  },
  "WasLocalDatabaseReferencesEmpty": true
}